Workbook

Sheet Dashboard
A1: ALL AVAILABLE PRODUCT TYPES – NET MARGIN DASHBOARD
A4: Landing Value Excl GST | C4: Product Cost | E4: Gross Margin | G4: Operating Costs
B5: ='Product Type Summary'!E8 -> 0 | D5: ='Product Type Summary'!D8 -> 0 | F5: ='Product Type Summary'!F8 -> 0 | H5: ='Product Type Summary'!L8 -> 0
A8: Net Margin | C8: Net Margin % | E8: Target Net Margin % | G8: Items Below Target
B9: ='Product Type Summary'!M8 -> 0 | D9: ='Product Type Summary'!N8 -> 0 | F9: =Assumptions!B3 -> 0.3 | H9: ='Product Type Summary'!O8 -> 0
A12: Academic Year | B12: Product Type | C12: Items | D12: Landing Value | E12: Product Cost | F12: Gross Margin % | G12: Operating Cost | H12: Net Margin | I12: Net Margin %
A13: ='Product Type Summary'!A2 -> 2027-2028 | B13: ='Product Type Summary'!B2 -> Core | C13: ='Product Type Summary'!C2 -> 0 | D13: ='Product Type Summary'!E2 -> 0 | E13: ='Product Type Summary'!D2 -> 0 | F13: ='Product Type Summary'!G2 -> 0 | G13: ='Product Type Summary'!L2 -> 0 | H13: ='Product Type Summary'!M2 -> 0 | I13: ='Product Type Summary'!N2 -> 0
A14: ='Product Type Summary'!A3 -> 2027-2028 | B14: ='Product Type Summary'!B3 -> MINI | C14: ='Product Type Summary'!C3 -> 0 | D14: ='Product Type Summary'!E3 -> 0 | E14: ='Product Type Summary'!D3 -> 0 | F14: ='Product Type Summary'!G3 -> 0 | G14: ='Product Type Summary'!L3 -> 0 | H14: ='Product Type Summary'!M3 -> 0 | I14: ='Product Type Summary'!N3 -> 0
A15: ='Product Type Summary'!A4 -> 2027-2028 | B15: ='Product Type Summary'!B4 -> MINI+WB | C15: ='Product Type Summary'!C4 -> 0 | D15: ='Product Type Summary'!E4 -> 0 | E15: ='Product Type Summary'!D4 -> 0 | F15: ='Product Type Summary'!G4 -> 0 | G15: ='Product Type Summary'!L4 -> 0 | H15: ='Product Type Summary'!M4 -> 0 | I15: ='Product Type Summary'!N4 -> 0
A16: ='Product Type Summary'!A5 -> 2026-2027 | B16: ='Product Type Summary'!B5 -> Optional | C16: ='Product Type Summary'!C5 -> 0 | D16: ='Product Type Summary'!E5 -> 0 | E16: ='Product Type Summary'!D5 -> 0 | F16: ='Product Type Summary'!G5 -> 0 | G16: ='Product Type Summary'!L5 -> 0 | H16: ='Product Type Summary'!M5 -> 0 | I16: ='Product Type Summary'!N5 -> 0
A17: ='Product Type Summary'!A6 -> 2026-2027 | B17: ='Product Type Summary'!B6 -> CSR | C17: ='Product Type Summary'!C6 -> 0 | D17: ='Product Type Summary'!E6 -> 0 | E17: ='Product Type Summary'!D6 -> 0 | F17: ='Product Type Summary'!G6 -> 0 | G17: ='Product Type Summary'!L6 -> 0 | H17: ='Product Type Summary'!M6 -> 0 | I17: ='Product Type Summary'!N6 -> 0
A18: ='Product Type Summary'!A7 -> 2025-2026 | B18: ='Product Type Summary'!B7 -> CSR | C18: ='Product Type Summary'!C7 -> 0 | D18: ='Product Type Summary'!E7 -> 0 | E18: ='Product Type Summary'!D7 -> 0 | F18: ='Product Type Summary'!G7 -> 0 | G18: ='Product Type Summary'!L7 -> 0 | H18: ='Product Type Summary'!M7 -> 0 | I18: ='Product Type Summary'!N7 -> 0

Sheet Product Type Summary
A1: Academic Year | B1: Product Type | C1: Items | D1: Product Cost (₹) | E1: Landing Value Excl GST (₹) | F1: Gross Margin (₹) | G1: Gross Margin % | H1: Transport (₹) | I1: Warehouse (₹) | J1: Salary (₹) | K1: Additional Services (₹) | L1: Operating Cost (₹) | M1: Net Margin (₹) | N1: Net Margin % | O1: Items Below Target
A2: 2027-2028 | B2: Core | C2: =COUNTIFS('Margin Analysis'!$Y$2:$Y$645,$A2,'Margin Analysis'!$X$2:$X$645,$B2) -> 0 | D2: =SUMIFS('Margin Analysis'!$AB$2:$AB$645,'Margin Analysis'!$Y$2:$Y$645,$A2,'Margin Analysis'!$X$2:$X$645,$B2) -> 0 | E2: =SUMIFS('Margin Analysis'!$AA$2:$AA$645,'Margin Analysis'!$Y$2:$Y$645,$A2,'Margin Analysis'!$X$2:$X$645,$B2) -> 0 | F2: =E2-D2 -> 0 | G2: =IFERROR(F2/E2,0) -> 0 | H2: =SUMIFS('Margin Analysis'!$AG$2:$AG$645,'Margin Analysis'!$Y$2:$Y$645,$A2,'Margin Analysis'!$X$2:$X$645,$B2) -> 0 | I2: =SUMIFS('Margin Analysis'!$AH$2:$AH$645,'Margin Analysis'!$Y$2:$Y$645,$A2,'Margin Analysis'!$X$2:$X$645,$B2) -> 0 | J2: =SUMIFS('Margin Analysis'!$AI$2:$AI$645,'Margin Analysis'!$Y$2:$Y$645,$A2,'Margin Analysis'!$X$2:$X$645,$B2) -> 0 | K2: =SUMIFS('Margin Analysis'!$AJ$2:$AJ$645,'Margin Analysis'!$Y$2:$Y$645,$A2,'Margin Analysis'!$X$2:$X$645,$B2) -> 0 | L2: =SUM(H2:K2) -> 0 | M2: =F2-L2 -> 0 | N2: =IFERROR(M2/E2,0) -> 0 | O2: =COUNTIFS('Margin Analysis'!$Y$2:$Y$645,$A2,'Margin Analysis'!$X$2:$X$645,$B2,'Margin Analysis'!$AN$2:$AN$645,"<"&Assumptions!$B$3) -> 0
A3: 2027-2028 | B3: MINI | C3: =COUNTIFS('Margin Analysis'!$Y$2:$Y$645,$A3,'Margin Analysis'!$X$2:$X$645,$B3) -> 0 | D3: =SUMIFS('Margin Analysis'!$AB$2:$AB$645,'Margin Analysis'!$Y$2:$Y$645,$A3,'Margin Analysis'!$X$2:$X$645,$B3) -> 0 | E3: =SUMIFS('Margin Analysis'!$AA$2:$AA$645,'Margin Analysis'!$Y$2:$Y$645,$A3,'Margin Analysis'!$X$2:$X$645,$B3) -> 0 | F3: =E3-D3 -> 0 | G3: =IFERROR(F3/E3,0) -> 0 | H3: =SUMIFS('Margin Analysis'!$AG$2:$AG$645,'Margin Analysis'!$Y$2:$Y$645,$A3,'Margin Analysis'!$X$2:$X$645,$B3) -> 0 | I3: =SUMIFS('Margin Analysis'!$AH$2:$AH$645,'Margin Analysis'!$Y$2:$Y$645,$A3,'Margin Analysis'!$X$2:$X$645,$B3) -> 0 | J3: =SUMIFS('Margin Analysis'!$AI$2:$AI$645,'Margin Analysis'!$Y$2:$Y$645,$A3,'Margin Analysis'!$X$2:$X$645,$B3) -> 0 | K3: =SUMIFS('Margin Analysis'!$AJ$2:$AJ$645,'Margin Analysis'!$Y$2:$Y$645,$A3,'Margin Analysis'!$X$2:$X$645,$B3) -> 0 | L3: =SUM(H3:K3) -> 0 | M3: =F3-L3 -> 0 | N3: =IFERROR(M3/E3,0) -> 0 | O3: =COUNTIFS('Margin Analysis'!$Y$2:$Y$645,$A3,'Margin Analysis'!$X$2:$X$645,$B3,'Margin Analysis'!$AN$2:$AN$645,"<"&Assumptions!$B$3) -> 0
A4: 2027-2028 | B4: MINI+WB | C4: =COUNTIFS('Margin Analysis'!$Y$2:$Y$645,$A4,'Margin Analysis'!$X$2:$X$645,$B4) -> 0 | D4: =SUMIFS('Margin Analysis'!$AB$2:$AB$645,'Margin Analysis'!$Y$2:$Y$645,$A4,'Margin Analysis'!$X$2:$X$645,$B4) -> 0 | E4: =SUMIFS('Margin Analysis'!$AA$2:$AA$645,'Margin Analysis'!$Y$2:$Y$645,$A4,'Margin Analysis'!$X$2:$X$645,$B4) -> 0 | F4: =E4-D4 -> 0 | G4: =IFERROR(F4/E4,0) -> 0 | H4: =SUMIFS('Margin Analysis'!$AG$2:$AG$645,'Margin Analysis'!$Y$2:$Y$645,$A4,'Margin Analysis'!$X$2:$X$645,$B4) -> 0 | I4: =SUMIFS('Margin Analysis'!$AH$2:$AH$645,'Margin Analysis'!$Y$2:$Y$645,$A4,'Margin Analysis'!$X$2:$X$645,$B4) -> 0 | J4: =SUMIFS('Margin Analysis'!$AI$2:$AI$645,'Margin Analysis'!$Y$2:$Y$645,$A4,'Margin Analysis'!$X$2:$X$645,$B4) -> 0 | K4: =SUMIFS('Margin Analysis'!$AJ$2:$AJ$645,'Margin Analysis'!$Y$2:$Y$645,$A4,'Margin Analysis'!$X$2:$X$645,$B4) -> 0 | L4: =SUM(H4:K4) -> 0 | M4: =F4-L4 -> 0 | N4: =IFERROR(M4/E4,0) -> 0 | O4: =COUNTIFS('Margin Analysis'!$Y$2:$Y$645,$A4,'Margin Analysis'!$X$2:$X$645,$B4,'Margin Analysis'!$AN$2:$AN$645,"<"&Assumptions!$B$3) -> 0
A5: 2026-2027 | B5: Optional | C5: =COUNTIFS('Margin Analysis'!$Y$2:$Y$645,$A5,'Margin Analysis'!$X$2:$X$645,$B5) -> 0 | D5: =SUMIFS('Margin Analysis'!$AB$2:$AB$645,'Margin Analysis'!$Y$2:$Y$645,$A5,'Margin Analysis'!$X$2:$X$645,$B5) -> 0 | E5: =SUMIFS('Margin Analysis'!$AA$2:$AA$645,'Margin Analysis'!$Y$2:$Y$645,$A5,'Margin Analysis'!$X$2:$X$645,$B5) -> 0 | F5: =E5-D5 -> 0 | G5: =IFERROR(F5/E5,0) -> 0 | H5: =SUMIFS('Margin Analysis'!$AG$2:$AG$645,'Margin Analysis'!$Y$2:$Y$645,$A5,'Margin Analysis'!$X$2:$X$645,$B5) -> 0 | I5: =SUMIFS('Margin Analysis'!$AH$2:$AH$645,'Margin Analysis'!$Y$2:$Y$645,$A5,'Margin Analysis'!$X$2:$X$645,$B5) -> 0 | J5: =SUMIFS('Margin Analysis'!$AI$2:$AI$645,'Margin Analysis'!$Y$2:$Y$645,$A5,'Margin Analysis'!$X$2:$X$645,$B5) -> 0 | K5: =SUMIFS('Margin Analysis'!$AJ$2:$AJ$645,'Margin Analysis'!$Y$2:$Y$645,$A5,'Margin Analysis'!$X$2:$X$645,$B5) -> 0 | L5: =SUM(H5:K5) -> 0 | M5: =F5-L5 -> 0 | N5: =IFERROR(M5/E5,0) -> 0 | O5: =COUNTIFS('Margin Analysis'!$Y$2:$Y$645,$A5,'Margin Analysis'!$X$2:$X$645,$B5,'Margin Analysis'!$AN$2:$AN$645,"<"&Assumptions!$B$3) -> 0
A6: 2026-2027 | B6: CSR | C6: =COUNTIFS('Margin Analysis'!$Y$2:$Y$645,$A6,'Margin Analysis'!$X$2:$X$645,$B6) -> 0 | D6: =SUMIFS('Margin Analysis'!$AB$2:$AB$645,'Margin Analysis'!$Y$2:$Y$645,$A6,'Margin Analysis'!$X$2:$X$645,$B6) -> 0 | E6: =SUMIFS('Margin Analysis'!$AA$2:$AA$645,'Margin Analysis'!$Y$2:$Y$645,$A6,'Margin Analysis'!$X$2:$X$645,$B6) -> 0 | F6: =E6-D6 -> 0 | G6: =IFERROR(F6/E6,0) -> 0 | H6: =SUMIFS('Margin Analysis'!$AG$2:$AG$645,'Margin Analysis'!$Y$2:$Y$645,$A6,'Margin Analysis'!$X$2:$X$645,$B6) -> 0 | I6: =SUMIFS('Margin Analysis'!$AH$2:$AH$645,'Margin Analysis'!$Y$2:$Y$645,$A6,'Margin Analysis'!$X$2:$X$645,$B6) -> 0 | J6: =SUMIFS('Margin Analysis'!$AI$2:$AI$645,'Margin Analysis'!$Y$2:$Y$645,$A6,'Margin Analysis'!$X$2:$X$645,$B6) -> 0 | K6: =SUMIFS('Margin Analysis'!$AJ$2:$AJ$645,'Margin Analysis'!$Y$2:$Y$645,$A6,'Margin Analysis'!$X$2:$X$645,$B6) -> 0 | L6: =SUM(H6:K6) -> 0 | M6: =F6-L6 -> 0 | N6: =IFERROR(M6/E6,0) -> 0 | O6: =COUNTIFS('Margin Analysis'!$Y$2:$Y$645,$A6,'Margin Analysis'!$X$2:$X$645,$B6,'Margin Analysis'!$AN$2:$AN$645,"<"&Assumptions!$B$3) -> 0
A7: 2025-2026 | B7: CSR | C7: =COUNTIFS('Margin Analysis'!$Y$2:$Y$645,$A7,'Margin Analysis'!$X$2:$X$645,$B7) -> 0 | D7: =SUMIFS('Margin Analysis'!$AB$2:$AB$645,'Margin Analysis'!$Y$2:$Y$645,$A7,'Margin Analysis'!$X$2:$X$645,$B7) -> 0 | E7: =SUMIFS('Margin Analysis'!$AA$2:$AA$645,'Margin Analysis'!$Y$2:$Y$645,$A7,'Margin Analysis'!$X$2:$X$645,$B7) -> 0 | F7: =E7-D7 -> 0 | G7: =IFERROR(F7/E7,0) -> 0 | H7: =SUMIFS('Margin Analysis'!$AG$2:$AG$645,'Margin Analysis'!$Y$2:$Y$645,$A7,'Margin Analysis'!$X$2:$X$645,$B7) -> 0 | I7: =SUMIFS('Margin Analysis'!$AH$2:$AH$645,'Margin Analysis'!$Y$2:$Y$645,$A7,'Margin Analysis'!$X$2:$X$645,$B7) -> 0 | J7: =SUMIFS('Margin Analysis'!$AI$2:$AI$645,'Margin Analysis'!$Y$2:$Y$645,$A7,'Margin Analysis'!$X$2:$X$645,$B7) -> 0 | K7: =SUMIFS('Margin Analysis'!$AJ$2:$AJ$645,'Margin Analysis'!$Y$2:$Y$645,$A7,'Margin Analysis'!$X$2:$X$645,$B7) -> 0 | L7: =SUM(H7:K7) -> 0 | M7: =F7-L7 -> 0 | N7: =IFERROR(M7/E7,0) -> 0 | O7: =COUNTIFS('Margin Analysis'!$Y$2:$Y$645,$A7,'Margin Analysis'!$X$2:$X$645,$B7,'Margin Analysis'!$AN$2:$AN$645,"<"&Assumptions!$B$3) -> 0
A8: ALL | B8: TOTAL | C8: =SUM(C2:C7) -> 0 | D8: =SUM(D2:D7) -> 0 | E8: =SUM(E2:E7) -> 0 | F8: =SUM(F2:F7) -> 0 | G8: =IFERROR(F8/E8,0) -> 0 | H8: =SUM(H2:H7) -> 0 | I8: =SUM(I2:I7) -> 0 | J8: =SUM(J2:J7) -> 0 | K8: =SUM(K2:K7) -> 0 | L8: =SUM(L2:L7) -> 0 | M8: =SUM(M2:M7) -> 0 | N8: =IFERROR(M8/E8,0) -> 0 | O8: =SUM(O2:O7) -> 0

Sheet Academic Year Summary
A1: Academic Year | B1: Items | C1: Product Cost (₹) | D1: Landing Value Excl GST (₹) | E1: Gross Margin (₹) | F1: Gross Margin % | G1: Operating Cost (₹) | H1: Net Margin (₹) | I1: Net Margin % | J1: Items Below Target
A2: 2027-2028 | B2: =COUNTIF('Margin Analysis'!$Y$2:$Y$645,A2) -> 0 | C2: =SUMIF('Margin Analysis'!$Y$2:$Y$645,A2,'Margin Analysis'!$AB$2:$AB$645) -> 0 | D2: =SUMIF('Margin Analysis'!$Y$2:$Y$645,A2,'Margin Analysis'!$AA$2:$AA$645) -> 0 | E2: =D2-C2 -> 0 | F2: =IFERROR(E2/D2,0) -> 0 | G2: =SUMIF('Margin Analysis'!$Y$2:$Y$645,A2,'Margin Analysis'!$AK$2:$AK$645) -> 0 | H2: =SUMIF('Margin Analysis'!$Y$2:$Y$645,A2,'Margin Analysis'!$AM$2:$AM$645) -> 0 | I2: =IFERROR(H2/D2,0) -> 0 | J2: =COUNTIFS('Margin Analysis'!$Y$2:$Y$645,A2,'Margin Analysis'!$AN$2:$AN$645,"<"&Assumptions!$B$3) -> 0
A3: 2026-2027 | B3: =COUNTIF('Margin Analysis'!$Y$2:$Y$645,A3) -> 0 | C3: =SUMIF('Margin Analysis'!$Y$2:$Y$645,A3,'Margin Analysis'!$AB$2:$AB$645) -> 0 | D3: =SUMIF('Margin Analysis'!$Y$2:$Y$645,A3,'Margin Analysis'!$AA$2:$AA$645) -> 0 | E3: =D3-C3 -> 0 | F3: =IFERROR(E3/D3,0) -> 0 | G3: =SUMIF('Margin Analysis'!$Y$2:$Y$645,A3,'Margin Analysis'!$AK$2:$AK$645) -> 0 | H3: =SUMIF('Margin Analysis'!$Y$2:$Y$645,A3,'Margin Analysis'!$AM$2:$AM$645) -> 0 | I3: =IFERROR(H3/D3,0) -> 0 | J3: =COUNTIFS('Margin Analysis'!$Y$2:$Y$645,A3,'Margin Analysis'!$AN$2:$AN$645,"<"&Assumptions!$B$3) -> 0
A4: 2025-2026 | B4: =COUNTIF('Margin Analysis'!$Y$2:$Y$645,A4) -> 0 | C4: =SUMIF('Margin Analysis'!$Y$2:$Y$645,A4,'Margin Analysis'!$AB$2:$AB$645) -> 0 | D4: =SUMIF('Margin Analysis'!$Y$2:$Y$645,A4,'Margin Analysis'!$AA$2:$AA$645) -> 0 | E4: =D4-C4 -> 0 | F4: =IFERROR(E4/D4,0) -> 0 | G4: =SUMIF('Margin Analysis'!$Y$2:$Y$645,A4,'Margin Analysis'!$AK$2:$AK$645) -> 0 | H4: =SUMIF('Margin Analysis'!$Y$2:$Y$645,A4,'Margin Analysis'!$AM$2:$AM$645) -> 0 | I4: =IFERROR(H4/D4,0) -> 0 | J4: =COUNTIFS('Margin Analysis'!$Y$2:$Y$645,A4,'Margin Analysis'!$AN$2:$AN$645,"<"&Assumptions!$B$3) -> 0
A5: TOTAL | B5: =SUM(B2:B4) -> 0 | C5: =SUM(C2:C4) -> 0 | D5: =SUM(D2:D4) -> 0 | E5: =SUM(E2:E4) -> 0 | F5: =IFERROR(E5/D5,0) -> 0 | G5: =SUM(G2:G4) -> 0 | H5: =SUM(H2:H4) -> 0 | I5: =IFERROR(H5/D5,0) -> 0 | J5: =SUM(J2:J4) -> 0

Sheet Grade Summary
A1: Academic Year | B1: Product Type | C1: Grade | D1: Items | E1: Product Cost (₹) | F1: Landing Value Excl GST (₹) | G1: Gross Margin (₹) | H1: Gross Margin % | I1: Operating Cost (₹) | J1: Net Margin (₹) | K1: Net Margin % | L1: Items Below Target
A2: 2027-2028 | B2: Core | C2: Grade 1 | D2: =COUNTIFS('Margin Analysis'!$Y$2:$Y$645,$A2,'Margin Analysis'!$X$2:$X$645,$B2,'Margin Analysis'!$B$2:$B$645,$C2) -> 0 | E2: =SUMIFS('Margin Analysis'!$AB$2:$AB$645,'Margin Analysis'!$Y$2:$Y$645,$A2,'Margin Analysis'!$X$2:$X$645,$B2,'Margin Analysis'!$B$2:$B$645,$C2) -> 0 | F2: =SUMIFS('Margin Analysis'!$AA$2:$AA$645,'Margin Analysis'!$Y$2:$Y$645,$A2,'Margin Analysis'!$X$2:$X$645,$B2,'Margin Analysis'!$B$2:$B$645,$C2) -> 0 | G2: =F2-E2 -> 0 | H2: =IFERROR(G2/F2,0) -> 0 | I2: =SUMIFS('Margin Analysis'!$AK$2:$AK$645,'Margin Analysis'!$Y$2:$Y$645,$A2,'Margin Analysis'!$X$2:$X$645,$B2,'Margin Analysis'!$B$2:$B$645,$C2) -> 0 | J2: =SUMIFS('Margin Analysis'!$AM$2:$AM$645,'Margin Analysis'!$Y$2:$Y$645,$A2,'Margin Analysis'!$X$2:$X$645,$B2,'Margin Analysis'!$B$2:$B$645,$C2) -> 0 | K2: =IFERROR(J2/F2,0) -> 0 | L2: =COUNTIFS('Margin Analysis'!$Y$2:$Y$645,$A2,'Margin Analysis'!$X$2:$X$645,$B2,'Margin Analysis'!$B$2:$B$645,$C2,'Margin Analysis'!$AN$2:$AN$645,"<"&Assumptions!$B$3) -> 0
A3: 2027-2028 | B3: Core | C3: Grade 2 | D3: =COUNTIFS('Margin Analysis'!$Y$2:$Y$645,$A3,'Margin Analysis'!$X$2:$X$645,$B3,'Margin Analysis'!$B$2:$B$645,$C3) -> 0 | E3: =SUMIFS('Margin Analysis'!$AB$2:$AB$645,'Margin Analysis'!$Y$2:$Y$645,$A3,'Margin Analysis'!$X$2:$X$645,$B3,'Margin Analysis'!$B$2:$B$645,$C3) -> 0 | F3: =SUMIFS('Margin Analysis'!$AA$2:$AA$645,'Margin Analysis'!$Y$2:$Y$645,$A3,'Margin Analysis'!$X$2:$X$645,$B3,'Margin Analysis'!$B$2:$B$645,$C3) -> 0 | G3: =F3-E3 -> 0 | H3: =IFERROR(G3/F3,0) -> 0 | I3: =SUMIFS('Margin Analysis'!$AK$2:$AK$645,'Margin Analysis'!$Y$2:$Y$645,$A3,'Margin Analysis'!$X$2:$X$645,$B3,'Margin Analysis'!$B$2:$B$645,$C3) -> 0 | J3: =SUMIFS('Margin Analysis'!$AM$2:$AM$645,'Margin Analysis'!$Y$2:$Y$645,$A3,'Margin Analysis'!$X$2:$X$645,$B3,'Margin Analysis'!$B$2:$B$645,$C3) -> 0 | K3: =IFERROR(J3/F3,0) -> 0 | L3: =COUNTIFS('Margin Analysis'!$Y$2:$Y$645,$A3,'Margin Analysis'!$X$2:$X$645,$B3,'Margin Analysis'!$B$2:$B$645,$C3,'Margin Analysis'!$AN$2:$AN$645,"<"&Assumptions!$B$3) -> 0
A4: 2027-2028 | B4: Core | C4: Grade 3 | D4: =COUNTIFS('Margin Analysis'!$Y$2:$Y$645,$A4,'Margin Analysis'!$X$2:$X$645,$B4,'Margin Analysis'!$B$2:$B$645,$C4) -> 0 | E4: =SUMIFS('Margin Analysis'!$AB$2:$AB$645,'Margin Analysis'!$Y$2:$Y$645,$A4,'Margin Analysis'!$X$2:$X$645,$B4,'Margin Analysis'!$B$2:$B$645,$C4) -> 0 | F4: =SUMIFS('Margin Analysis'!$AA$2:$AA$645,'Margin Analysis'!$Y$2:$Y$645,$A4,'Margin Analysis'!$X$2:$X$645,$B4,'Margin Analysis'!$B$2:$B$645,$C4) -> 0 | G4: =F4-E4 -> 0 | H4: =IFERROR(G4/F4,0) -> 0 | I4: =SUMIFS('Margin Analysis'!$AK$2:$AK$645,'Margin Analysis'!$Y$2:$Y$645,$A4,'Margin Analysis'!$X$2:$X$645,$B4,'Margin Analysis'!$B$2:$B$645,$C4) -> 0 | J4: =SUMIFS('Margin Analysis'!$AM$2:$AM$645,'Margin Analysis'!$Y$2:$Y$645,$A4,'Margin Analysis'!$X$2:$X$645,$B4,'Margin Analysis'!$B$2:$B$645,$C4) -> 0 | K4: =IFERROR(J4/F4,0) -> 0 | L4: =COUNTIFS('Margin Analysis'!$Y$2:$Y$645,$A4,'Margin Analysis'!$X$2:$X$645,$B4,'Margin Analysis'!$B$2:$B$645,$C4,'Margin Analysis'!$AN$2:$AN$645,"<"&Assumptions!$B$3) -> 0
A5: 2027-2028 | B5: Core | C5: Grade 4 | D5: =COUNTIFS('Margin Analysis'!$Y$2:$Y$645,$A5,'Margin Analysis'!$X$2:$X$645,$B5,'Margin Analysis'!$B$2:$B$645,$C5) -> 0 | E5: =SUMIFS('Margin Analysis'!$AB$2:$AB$645,'Margin Analysis'!$Y$2:$Y$645,$A5,'Margin Analysis'!$X$2:$X$645,$B5,'Margin Analysis'!$B$2:$B$645,$C5) -> 0 | F5: =SUMIFS('Margin Analysis'!$AA$2:$AA$645,'Margin Analysis'!$Y$2:$Y$645,$A5,'Margin Analysis'!$X$2:$X$645,$B5,'Margin Analysis'!$B$2:$B$645,$C5) -> 0 | G5: =F5-E5 -> 0 | H5: =IFERROR(G5/F5,0) -> 0 | I5: =SUMIFS('Margin Analysis'!$AK$2:$AK$645,'Margin Analysis'!$Y$2:$Y$645,$A5,'Margin Analysis'!$X$2:$X$645,$B5,'Margin Analysis'!$B$2:$B$645,$C5) -> 0 | J5: =SUMIFS('Margin Analysis'!$AM$2:$AM$645,'Margin Analysis'!$Y$2:$Y$645,$A5,'Margin Analysis'!$X$2:$X$645,$B5,'Margin Analysis'!$B$2:$B$645,$C5) -> 0 | K5: =IFERROR(J5/F5,0) -> 0 | L5: =COUNTIFS('Margin Analysis'!$Y$2:$Y$645,$A5,'Margin Analysis'!$X$2:$X$645,$B5,'Margin Analysis'!$B$2:$B$645,$C5,'Margin Analysis'!$AN$2:$AN$645,"<"&Assumptions!$B$3) -> 0
A6: 2027-2028 | B6: Core | C6: Grade 5 | D6: =COUNTIFS('Margin Analysis'!$Y$2:$Y$645,$A6,'Margin Analysis'!$X$2:$X$645,$B6,'Margin Analysis'!$B$2:$B$645,$C6) -> 0 | E6: =SUMIFS('Margin Analysis'!$AB$2:$AB$645,'Margin Analysis'!$Y$2:$Y$645,$A6,'Margin Analysis'!$X$2:$X$645,$B6,'Margin Analysis'!$B$2:$B$645,$C6) -> 0 | F6: =SUMIFS('Margin Analysis'!$AA$2:$AA$645,'Margin Analysis'!$Y$2:$Y$645,$A6,'Margin Analysis'!$X$2:$X$645,$B6,'Margin Analysis'!$B$2:$B$645,$C6) -> 0 | G6: =F6-E6 -> 0 | H6: =IFERROR(G6/F6,0) -> 0 | I6: =SUMIFS('Margin Analysis'!$AK$2:$AK$645,'Margin Analysis'!$Y$2:$Y$645,$A6,'Margin Analysis'!$X$2:$X$645,$B6,'Margin Analysis'!$B$2:$B$645,$C6) -> 0 | J6: =SUMIFS('Margin Analysis'!$AM$2:$AM$645,'Margin Analysis'!$Y$2:$Y$645,$A6,'Margin Analysis'!$X$2:$X$645,$B6,'Margin Analysis'!$B$2:$B$645,$C6) -> 0 | K6: =IFERROR(J6/F6,0) -> 0 | L6: =COUNTIFS('Margin Analysis'!$Y$2:$Y$645,$A6,'Margin Analysis'!$X$2:$X$645,$B6,'Margin Analysis'!$B$2:$B$645,$C6,'Margin Analysis'!$AN$2:$AN$645,"<"&Assumptions!$B$3) -> 0
A7: 2027-2028 | B7: Core | C7: Grade 6 | D7: =COUNTIFS('Margin Analysis'!$Y$2:$Y$645,$A7,'Margin Analysis'!$X$2:$X$645,$B7,'Margin Analysis'!$B$2:$B$645,$C7) -> 0 | E7: =SUMIFS('Margin Analysis'!$AB$2:$AB$645,'Margin Analysis'!$Y$2:$Y$645,$A7,'Margin Analysis'!$X$2:$X$645,$B7,'Margin Analysis'!$B$2:$B$645,$C7) -> 0 | F7: =SUMIFS('Margin Analysis'!$AA$2:$AA$645,'Margin Analysis'!$Y$2:$Y$645,$A7,'Margin Analysis'!$X$2:$X$645,$B7,'Margin Analysis'!$B$2:$B$645,$C7) -> 0 | G7: =F7-E7 -> 0 | H7: =IFERROR(G7/F7,0) -> 0 | I7: =SUMIFS('Margin Analysis'!$AK$2:$AK$645,'Margin Analysis'!$Y$2:$Y$645,$A7,'Margin Analysis'!$X$2:$X$645,$B7,'Margin Analysis'!$B$2:$B$645,$C7) -> 0 | J7: =SUMIFS('Margin Analysis'!$AM$2:$AM$645,'Margin Analysis'!$Y$2:$Y$645,$A7,'Margin Analysis'!$X$2:$X$645,$B7,'Margin Analysis'!$B$2:$B$645,$C7) -> 0 | K7: =IFERROR(J7/F7,0) -> 0 | L7: =COUNTIFS('Margin Analysis'!$Y$2:$Y$645,$A7,'Margin Analysis'!$X$2:$X$645,$B7,'Margin Analysis'!$B$2:$B$645,$C7,'Margin Analysis'!$AN$2:$AN$645,"<"&Assumptions!$B$3) -> 0
A8: 2027-2028 | B8: Core | C8: Grade 7 | D8: =COUNTIFS('Margin Analysis'!$Y$2:$Y$645,$A8,'Margin Analysis'!$X$2:$X$645,$B8,'Margin Analysis'!$B$2:$B$645,$C8) -> 0 | E8: =SUMIFS('Margin Analysis'!$AB$2:$AB$645,'Margin Analysis'!$Y$2:$Y$645,$A8,'Margin Analysis'!$X$2:$X$645,$B8,'Margin Analysis'!$B$2:$B$645,$C8) -> 0 | F8: =SUMIFS('Margin Analysis'!$AA$2:$AA$645,'Margin Analysis'!$Y$2:$Y$645,$A8,'Margin Analysis'!$X$2:$X$645,$B8,'Margin Analysis'!$B$2:$B$645,$C8) -> 0 | G8: =F8-E8 -> 0 | H8: =IFERROR(G8/F8,0) -> 0 | I8: =SUMIFS('Margin Analysis'!$AK$2:$AK$645,'Margin Analysis'!$Y$2:$Y$645,$A8,'Margin Analysis'!$X$2:$X$645,$B8,'Margin Analysis'!$B$2:$B$645,$C8) -> 0 | J8: =SUMIFS('Margin Analysis'!$AM$2:$AM$645,'Margin Analysis'!$Y$2:$Y$645,$A8,'Margin Analysis'!$X$2:$X$645,$B8,'Margin Analysis'!$B$2:$B$645,$C8) -> 0 | K8: =IFERROR(J8/F8,0) -> 0 | L8: =COUNTIFS('Margin Analysis'!$Y$2:$Y$645,$A8,'Margin Analysis'!$X$2:$X$645,$B8,'Margin Analysis'!$B$2:$B$645,$C8,'Margin Analysis'!$AN$2:$AN$645,"<"&Assumptions!$B$3) -> 0
A9: 2027-2028 | B9: Core | C9: Grade 8 | D9: =COUNTIFS('Margin Analysis'!$Y$2:$Y$645,$A9,'Margin Analysis'!$X$2:$X$645,$B9,'Margin Analysis'!$B$2:$B$645,$C9) -> 0 | E9: =SUMIFS('Margin Analysis'!$AB$2:$AB$645,'Margin Analysis'!$Y$2:$Y$645,$A9,'Margin Analysis'!$X$2:$X$645,$B9,'Margin Analysis'!$B$2:$B$645,$C9) -> 0 | F9: =SUMIFS('Margin Analysis'!$AA$2:$AA$645,'Margin Analysis'!$Y$2:$Y$645,$A9,'Margin Analysis'!$X$2:$X$645,$B9,'Margin Analysis'!$B$2:$B$645,$C9) -> 0 | G9: =F9-E9 -> 0 | H9: =IFERROR(G9/F9,0) -> 0 | I9: =SUMIFS('Margin Analysis'!$AK$2:$AK$645,'Margin Analysis'!$Y$2:$Y$645,$A9,'Margin Analysis'!$X$2:$X$645,$B9,'Margin Analysis'!$B$2:$B$645,$C9) -> 0 | J9: =SUMIFS('Margin Analysis'!$AM$2:$AM$645,'Margin Analysis'!$Y$2:$Y$645,$A9,'Margin Analysis'!$X$2:$X$645,$B9,'Margin Analysis'!$B$2:$B$645,$C9) -> 0 | K9: =IFERROR(J9/F9,0) -> 0 | L9: =COUNTIFS('Margin Analysis'!$Y$2:$Y$645,$A9,'Margin Analysis'!$X$2:$X$645,$B9,'Margin Analysis'!$B$2:$B$645,$C9,'Margin Analysis'!$AN$2:$AN$645,"<"&Assumptions!$B$3) -> 0
A10: 2027-2028 | B10: Core | C10: K1 | D10: =COUNTIFS('Margin Analysis'!$Y$2:$Y$645,$A10,'Margin Analysis'!$X$2:$X$645,$B10,'Margin Analysis'!$B$2:$B$645,$C10) -> 0 | E10: =SUMIFS('Margin Analysis'!$AB$2:$AB$645,'Margin Analysis'!$Y$2:$Y$645,$A10,'Margin Analysis'!$X$2:$X$645,$B10,'Margin Analysis'!$B$2:$B$645,$C10) -> 0 | F10: =SUMIFS('Margin Analysis'!$AA$2:$AA$645,'Margin Analysis'!$Y$2:$Y$645,$A10,'Margin Analysis'!$X$2:$X$645,$B10,'Margin Analysis'!$B$2:$B$645,$C10) -> 0 | G10: =F10-E10 -> 0 | H10: =IFERROR(G10/F10,0) -> 0 | I10: =SUMIFS('Margin Analysis'!$AK$2:$AK$645,'Margin Analysis'!$Y$2:$Y$645,$A10,'Margin Analysis'!$X$2:$X$645,$B10,'Margin Analysis'!$B$2:$B$645,$C10) -> 0 | J10: =SUMIFS('Margin Analysis'!$AM$2:$AM$645,'Margin Analysis'!$Y$2:$Y$645,$A10,'Margin Analysis'!$X$2:$X$645,$B10,'Margin Analysis'!$B$2:$B$645,$C10) -> 0 | K10: =IFERROR(J10/F10,0) -> 0 | L10: =COUNTIFS('Margin Analysis'!$Y$2:$Y$645,$A10,'Margin Analysis'!$X$2:$X$645,$B10,'Margin Analysis'!$B$2:$B$645,$C10,'Margin Analysis'!$AN$2:$AN$645,"<"&Assumptions!$B$3) -> 0
A11: 2027-2028 | B11: Core | C11: K2 | D11: =COUNTIFS('Margin Analysis'!$Y$2:$Y$645,$A11,'Margin Analysis'!$X$2:$X$645,$B11,'Margin Analysis'!$B$2:$B$645,$C11) -> 0 | E11: =SUMIFS('Margin Analysis'!$AB$2:$AB$645,'Margin Analysis'!$Y$2:$Y$645,$A11,'Margin Analysis'!$X$2:$X$645,$B11,'Margin Analysis'!$B$2:$B$645,$C11) -> 0 | F11: =SUMIFS('Margin Analysis'!$AA$2:$AA$645,'Margin Analysis'!$Y$2:$Y$645,$A11,'Margin Analysis'!$X$2:$X$645,$B11,'Margin Analysis'!$B$2:$B$645,$C11) -> 0 | G11: =F11-E11 -> 0 | H11: =IFERROR(G11/F11,0) -> 0 | I11: =SUMIFS('Margin Analysis'!$AK$2:$AK$645,'Margin Analysis'!$Y$2:$Y$645,$A11,'Margin Analysis'!$X$2:$X$645,$B11,'Margin Analysis'!$B$2:$B$645,$C11) -> 0 | J11: =SUMIFS('Margin Analysis'!$AM$2:$AM$645,'Margin Analysis'!$Y$2:$Y$645,$A11,'Margin Analysis'!$X$2:$X$645,$B11,'Margin Analysis'!$B$2:$B$645,$C11) -> 0 | K11: =IFERROR(J11/F11,0) -> 0 | L11: =COUNTIFS('Margin Analysis'!$Y$2:$Y$645,$A11,'Margin Analysis'!$X$2:$X$645,$B11,'Margin Analysis'!$B$2:$B$645,$C11,'Margin Analysis'!$AN$2:$AN$645,"<"&Assumptions!$B$3) -> 0
A12: 2027-2028 | B12: Core | C12: Nursery | D12: =COUNTIFS('Margin Analysis'!$Y$2:$Y$645,$A12,'Margin Analysis'!$X$2:$X$645,$B12,'Margin Analysis'!$B$2:$B$645,$C12) -> 0 | E12: =SUMIFS('Margin Analysis'!$AB$2:$AB$645,'Margin Analysis'!$Y$2:$Y$645,$A12,'Margin Analysis'!$X$2:$X$645,$B12,'Margin Analysis'!$B$2:$B$645,$C12) -> 0 | F12: =SUMIFS('Margin Analysis'!$AA$2:$AA$645,'Margin Analysis'!$Y$2:$Y$645,$A12,'Margin Analysis'!$X$2:$X$645,$B12,'Margin Analysis'!$B$2:$B$645,$C12) -> 0 | G12: =F12-E12 -> 0 | H12: =IFERROR(G12/F12,0) -> 0 | I12: =SUMIFS('Margin Analysis'!$AK$2:$AK$645,'Margin Analysis'!$Y$2:$Y$645,$A12,'Margin Analysis'!$X$2:$X$645,$B12,'Margin Analysis'!$B$2:$B$645,$C12) -> 0 | J12: =SUMIFS('Margin Analysis'!$AM$2:$AM$645,'Margin Analysis'!$Y$2:$Y$645,$A12,'Margin Analysis'!$X$2:$X$645,$B12,'Margin Analysis'!$B$2:$B$645,$C12) -> 0 | K12: =IFERROR(J12/F12,0) -> 0 | L12: =COUNTIFS('Margin Analysis'!$Y$2:$Y$645,$A12,'Margin Analysis'!$X$2:$X$645,$B12,'Margin Analysis'!$B$2:$B$645,$C12,'Margin Analysis'!$AN$2:$AN$645,"<"&Assumptions!$B$3) -> 0
A13: 2027-2028 | B13: Core | C13: Pre Nursery | D13: =COUNTIFS('Margin Analysis'!$Y$2:$Y$645,$A13,'Margin Analysis'!$X$2:$X$645,$B13,'Margin Analysis'!$B$2:$B$645,$C13) -> 0 | E13: =SUMIFS('Margin Analysis'!$AB$2:$AB$645,'Margin Analysis'!$Y$2:$Y$645,$A13,'Margin Analysis'!$X$2:$X$645,$B13,'Margin Analysis'!$B$2:$B$645,$C13) -> 0 | F13: =SUMIFS('Margin Analysis'!$AA$2:$AA$645,'Margin Analysis'!$Y$2:$Y$645,$A13,'Margin Analysis'!$X$2:$X$645,$B13,'Margin Analysis'!$B$2:$B$645,$C13) -> 0 | G13: =F13-E13 -> 0 | H13: =IFERROR(G13/F13,0) -> 0 | I13: =SUMIFS('Margin Analysis'!$AK$2:$AK$645,'Margin Analysis'!$Y$2:$Y$645,$A13,'Margin Analysis'!$X$2:$X$645,$B13,'Margin Analysis'!$B$2:$B$645,$C13) -> 0 | J13: =SUMIFS('Margin Analysis'!$AM$2:$AM$645,'Margin Analysis'!$Y$2:$Y$645,$A13,'Margin Analysis'!$X$2:$X$645,$B13,'Margin Analysis'!$B$2:$B$645,$C13) -> 0 | K13: =IFERROR(J13/F13,0) -> 0 | L13: =COUNTIFS('Margin Analysis'!$Y$2:$Y$645,$A13,'Margin Analysis'!$X$2:$X$645,$B13,'Margin Analysis'!$B$2:$B$645,$C13,'Margin Analysis'!$AN$2:$AN$645,"<"&Assumptions!$B$3) -> 0
... A68: 2025-2026 | B68: CSR | C68: Grade 9 | D68: =COUNTIFS('Margin Analysis'!$Y$2:$Y$645,$A68,'Margin Analysis'!$X$2:$X$645,$B68,'Margin Analysis'!$B$2:$B$645,$C68) -> 0 | E68: =SUMIFS('Margin Analysis'!$AB$2:$AB$645,'Margin Analysis'!$Y$2:$Y$645,$A68,'Margin Analysis'!$X$2:$X$645,$B68,'Margin Analysis'!$B$2:$B$645,$C68) -> 0 | F68: =SUMIFS('Margin Analysis'!$AA$2:$AA$645,'Margin Analysis'!$Y$2:$Y$645,$A68,'Margin Analysis'!$X$2:$X$645,$B68,'Margin Analysis'!$B$2:$B$645,$C68) -> 0 | G68: =F68-E68 -> 0 | H68: =IFERROR(G68/F68,0) -> 0 | I68: =SUMIFS('Margin Analysis'!$AK$2:$AK$645,'Margin Analysis'!$Y$2:$Y$645,$A68,'Margin Analysis'!$X$2:$X$645,$B68,'Margin Analysis'!$B$2:$B$645,$C68) -> 0 | J68: =SUMIFS('Margin Analysis'!$AM$2:$AM$645,'Margin Analysis'!$Y$2:$Y$645,$A68,'Margin Analysis'!$X$2:$X$645,$B68,'Margin Analysis'!$B$2:$B$645,$C68) -> 0 | K68: =IFERROR(J68/F68,0) -> 0 | L68: =COUNTIFS('Margin Analysis'!$Y$2:$Y$645,$A68,'Margin Analysis'!$X$2:$X$645,$B68,'Margin Analysis'!$B$2:$B$645,$C68,'Margin Analysis'!$AN$2:$AN$645,"<"&Assumptions!$B$3) -> 0

Sheet Margin Analysis
A1: Product Name | B1: Grades | C1: Subjects | D1: Item Name | E1: Ratio | F1: Item Type | G1: Edition | H1: Type | I1: Core Kit SKU | J1: CP | K1: Aprox Margin | L1: CP + Margin | M1: GST % | N1: GST Value | O1: Base Price with GST | P1: Base % | Q1: Base Bundle | R1: MRP Bundle | S1: MRP IND | T1: Value Type | U1: Selling Price | V1: Selling Price After Discount @30% (₹) | W1: HSN Code | X1: Product Type | Y1: Academic Year | Z1: Allocated Landing Price (Incl GST) (₹) | AA1: Landing Price (Excl GST) (₹) | AB1: Cost Price (₹) | AC1: Gross Margin (₹) | AD1: Gross Margin % | AE1: Markup on Cost % | AF1: Gross Margin Status | AG1: Transportation Cost (₹) | AH1: Warehouse & Facility Cost (₹) | AI1: Employee Salary Cost (₹) | AJ1: Additional Services Cost (₹) | AK1: Total Operating Cost (₹) | AL1: Operating Cost % Applied | AM1: Net Margin (₹) | AN1: Net Margin % | AO1: Net Margin Status
A2: Corekit AY 2027-2028 | B2: Grade 1 | C2: Maths | D2: T1_G1_Math_Scholars_TB B2B (27) | E2: 1:1 | F2: Book | G2: 2027-2028 | H2: Term 1 | I2: 4000011860 | J2: 44.16 | L2: =J2+K2 -> 44.16 | M2: 0 | N2: =M2*L2 -> 0 | O2: =L2+N2 -> 44.16 | P2: =IFERROR(O2/Q2,"") -> 0.13933676 | Q2: =SUMIFS(O:O,T:T,T2,B:B,B2,A:A,A2,G:G,G2,E:E,E2) -> 316.93 | R2: =V2-SUMIFS(Q:Q,A:A,A2,B:B,B2,G:G,G2,E:E,E2,T:T,"Fixed Price ( Base Price with GST)") -> 2402.3364 | S2: =IF(T2="Fixed Price ( Base Price with GST)",O2,P2*R2) -> 334.73378 | T2: Based on Base % | U2: 4499 | V2: =IFERROR(U2*(1-30%),0) -> 3149.3 | W2: 490110 | X2: Core | Y2: =IFERROR(S2,0) -> 334.73378 | Z2: =IF(ISNUMBER(S2),S2,0) -> 334.73378 | AA2: =IFERROR(Z2/(1+M2),Z2) -> 334.73378 | AB2: =IF(ISNUMBER(J2),J2,0) -> 44.16 | AC2: =AA2-AB2 -> 290.57378 | AD2: =IFERROR(AC2/AA2,0) -> 0.86807426 | AE2: =IFERROR(AC2/AB2,0) -> 6.5800221 | AF2: =IF(AD2>=Assumptions!$B$3,"OK","Review") -> OK | AG2: =IFERROR(IF(Assumptions!$B$13="Cost Price",AB2,AA2)*SUMIF(Assumptions!$A$6:$A$10,X2,Assumptions!$B$6:$B$10),0) -> 26.778702 | AH2: =IFERROR(IF(Assumptions!$B$13="Cost Price",AB2,AA2)*SUMIF(Assumptions!$A$6:$A$10,X2,Assumptions!$C$6:$C$10),0) -> 16.736689 | AI2: =IFERROR(IF(Assumptions!$B$13="Cost Price",AB2,AA2)*SUMIF(Assumptions!$A$6:$A$10,X2,Assumptions!$D$6:$D$10),0) -> 33.473378 | AJ2: 33.473378 | AK2: =SUM(AG2:AJ2) -> 110.46215 | AL2: 0.33 | AM2: =AC2-AK2 -> 180.11163 | AN2: =IFERROR(AM2/AA2,0) -> 0.53807426 | AO2: =IF(AN2>=Assumptions!$B$3,"OK","Review") -> OK
A3: Corekit AY 2027-2028 | B3: Grade 1 | C3: Maths | D3: T1_G1_Math_Scholars_WB B2B (27) | E3: 1:1 | F3: Book | G3: 2027-2028 | H3: Term 1 | I3: 4000011852 | J3: 20.94 | L3: =J3+K3 -> 20.94 | M3: 0 | N3: =M3*L3 -> 0 | O3: =L3+N3 -> 20.94 | P3: =IFERROR(O3/Q3,"") -> 0.066071372 | Q3: =SUMIFS(O:O,T:T,T3,B:B,B3,A:A,A3,G:G,G3,E:E,E3) -> 316.93 | R3: =V3-SUMIFS(Q:Q,A:A,A3,B:B,B3,G:G,G3,E:E,E3,T:T,"Fixed Price ( Base Price with GST)") -> 2402.3364 | S3: =IF(T3="Fixed Price ( Base Price with GST)",O3,P3*R3) -> 158.72566 | T3: Based on Base % | U3: 4499 | V3: =IFERROR(U3*(1-30%),0) -> 3149.3 | W3: 490110 | X3: Core | Y3: =IFERROR(S3,0) -> 158.72566 | Z3: =IF(ISNUMBER(S3),S3,0) -> 158.72566 | AA3: =IFERROR(Z3/(1+M3),Z3) -> 158.72566 | AB3: =IF(ISNUMBER(J3),J3,0) -> 20.94 | AC3: =AA3-AB3 -> 137.78566 | AD3: =IFERROR(AC3/AA3,0) -> 0.86807426 | AE3: =IFERROR(AC3/AB3,0) -> 6.5800221 | AF3: =IF(AD3>=Assumptions!$B$3,"OK","Review") -> OK | AG3: =IFERROR(IF(Assumptions!$B$13="Cost Price",AB3,AA3)*SUMIF(Assumptions!$A$6:$A$10,X3,Assumptions!$B$6:$B$10),0) -> 12.698053 | AH3: =IFERROR(IF(Assumptions!$B$13="Cost Price",AB3,AA3)*SUMIF(Assumptions!$A$6:$A$10,X3,Assumptions!$C$6:$C$10),0) -> 7.9362831 | AI3: =IFERROR(IF(Assumptions!$B$13="Cost Price",AB3,AA3)*SUMIF(Assumptions!$A$6:$A$10,X3,Assumptions!$D$6:$D$10),0) -> 15.872566 | AJ3: 24.790219 | AK3: =SUM(AG3:AJ3) -> 61.297122 | AL3: 0.33 | AM3: =AC3-AK3 -> 76.488541 | AN3: =IFERROR(AM3/AA3,0) -> 0.48189146 | AO3: =IF(AN3>=Assumptions!$B$3,"OK","Review") -> OK
A4: Corekit AY 2027-2028 | B4: Grade 1 | C4: English | D4: Annual_G1_English_RB B2B (27) | E4: 1:1 | F4: Book | G4: 2027-2028 | H4: Term 1 | I4: 4000011794 | J4: 19.56 | L4: =J4+K4 -> 19.56 | M4: 0 | N4: =M4*L4 -> 0 | O4: =L4+N4 -> 19.56 | P4: =IFERROR(O4/Q4,"") -> 0.061717098 | Q4: =SUMIFS(O:O,T:T,T4,B:B,B4,A:A,A4,G:G,G4,E:E,E4) -> 316.93 | R4: =V4-SUMIFS(Q:Q,A:A,A4,B:B,B4,G:G,G4,E:E,E4,T:T,"Fixed Price ( Base Price with GST)") -> 2402.3364 | S4: =IF(T4="Fixed Price ( Base Price with GST)",O4,P4*R4) -> 148.26523 | T4: Based on Base % | U4: 4499 | V4: =IFERROR(U4*(1-30%),0) -> 3149.3 | W4: 490110 | X4: Core | Y4: =IFERROR(S4,0) -> 148.26523 | Z4: =IF(ISNUMBER(S4),S4,0) -> 148.26523 | AA4: =IFERROR(Z4/(1+M4),Z4) -> 148.26523 | AB4: =IF(ISNUMBER(J4),J4,0) -> 19.56 | AC4: =AA4-AB4 -> 128.70523 | AD4: =IFERROR(AC4/AA4,0) -> 0.86807426 | AE4: =IFERROR(AC4/AB4,0) -> 6.5800221 | AF4: =IF(AD4>=Assumptions!$B$3,"OK","Review") -> OK | AG4: =IFERROR(IF(Assumptions!$B$13="Cost Price",AB4,AA4)*SUMIF(Assumptions!$A$6:$A$10,X4,Assumptions!$B$6:$B$10),0) -> 11.861219 | AH4: =IFERROR(IF(Assumptions!$B$13="Cost Price",AB4,AA4)*SUMIF(Assumptions!$A$6:$A$10,X4,Assumptions!$C$6:$C$10),0) -> 7.4132616 | AI4: =IFERROR(IF(Assumptions!$B$13="Cost Price",AB4,AA4)*SUMIF(Assumptions!$A$6:$A$10,X4,Assumptions!$D$6:$D$10),0) -> 14.826523 | AJ4: 23.15648 | AK4: =SUM(AG4:AJ4) -> 57.257483 | AL4: 0.33 | AM4: =AC4-AK4 -> 71.447749 | AN4: =IFERROR(AM4/AA4,0) -> 0.48189146 | AO4: =IF(AN4>=Assumptions!$B$3,"OK","Review") -> OK
A5: Corekit AY 2027-2028 | B5: Grade 1 | C5: English | D5: T1_G1_English_RC B2B (27) | E5: 1:1 | F5: Workbook | G5: 2027-2028 | H5: Term 1 | I5: 4000011783 | J5: 60.15 | L5: =J5+K5 -> 60.15 | M5: 0 | N5: =M5*L5 -> 0 | O5: =L5+N5 -> 60.15 | P5: =IFERROR(O5/Q5,"") -> 0.18978954 | Q5: =SUMIFS(O:O,T:T,T5,B:B,B5,A:A,A5,G:G,G5,E:E,E5) -> 316.93 | R5: =V5-SUMIFS(Q:Q,A:A,A5,B:B,B5,G:G,G5,E:E,E5,T:T,"Fixed Price ( Base Price with GST)") -> 2402.3364 | S5: =IF(T5="Fixed Price ( Base Price with GST)",O5,P5*R5) -> 455.93833 | T5: Based on Base % | U5: 4499 | V5: =IFERROR(U5*(1-30%),0) -> 3149.3 | W5: 490110 | X5: Core | Y5: =IFERROR(S5,0) -> 455.93833 | Z5: =IF(ISNUMBER(S5),S5,0) -> 455.93833 | AA5: =IFERROR(Z5/(1+M5),Z5) -> 455.93833 | AB5: =IF(ISNUMBER(J5),J5,0) -> 60.15 | AC5: =AA5-AB5 -> 395.78833 | AD5: =IFERROR(AC5/AA5,0) -> 0.86807426 | AE5: =IFERROR(AC5/AB5,0) -> 6.5800221 | AF5: =IF(AD5>=Assumptions!$B$3,"OK","Review") -> OK | AG5: =IFERROR(IF(Assumptions!$B$13="Cost Price",AB5,AA5)*SUMIF(Assumptions!$A$6:$A$10,X5,Assumptions!$B$6:$B$10),0) -> 36.475066 | AH5: =IFERROR(IF(Assumptions!$B$13="Cost Price",AB5,AA5)*SUMIF(Assumptions!$A$6:$A$10,X5,Assumptions!$C$6:$C$10),0) -> 22.796916 | AI5: =IFERROR(IF(Assumptions!$B$13="Cost Price",AB5,AA5)*SUMIF(Assumptions!$A$6:$A$10,X5,Assumptions!$D$6:$D$10),0) -> 45.593833 | AJ5: 71.209728 | AK5: =SUM(AG5:AJ5) -> 176.07554 | AL5: 0.33 | AM5: =AC5-AK5 -> 219.71279 | AN5: =IFERROR(AM5/AA5,0) -> 0.48189146 | AO5: =IF(AN5>=Assumptions!$B$3,"OK","Review") -> OK
A6: Corekit AY 2027-2028 | B6: Grade 1 | C6: English | D6: T1_G1_English_WB B2B (27) | E6: 1:1 | F6: Workbook | G6: 2027-2028 | H6: Term 1 | I6: 4000011805 | J6: 20.94 | L6: =J6+K6 -> 20.94 | M6: 0 | N6: =M6*L6 -> 0 | O6: =L6+N6 -> 20.94 | P6: =IFERROR(O6/Q6,"") -> 0.066071372 | Q6: =SUMIFS(O:O,T:T,T6,B:B,B6,A:A,A6,G:G,G6,E:E,E6) -> 316.93 | R6: =V6-SUMIFS(Q:Q,A:A,A6,B:B,B6,G:G,G6,E:E,E6,T:T,"Fixed Price ( Base Price with GST)") -> 2402.3364 | S6: =IF(T6="Fixed Price ( Base Price with GST)",O6,P6*R6) -> 158.72566 | T6: Based on Base % | U6: 4499 | V6: =IFERROR(U6*(1-30%),0) -> 3149.3 | W6: 490110 | X6: Core | Y6: =IFERROR(S6,0) -> 158.72566 | Z6: =IF(ISNUMBER(S6),S6,0) -> 158.72566 | AA6: =IFERROR(Z6/(1+M6),Z6) -> 158.72566 | AB6: =IF(ISNUMBER(J6),J6,0) -> 20.94 | AC6: =AA6-AB6 -> 137.78566 | AD6: =IFERROR(AC6/AA6,0) -> 0.86807426 | AE6: =IFERROR(AC6/AB6,0) -> 6.5800221 | AF6: =IF(AD6>=Assumptions!$B$3,"OK","Review") -> OK | AG6: =IFERROR(IF(Assumptions!$B$13="Cost Price",AB6,AA6)*SUMIF(Assumptions!$A$6:$A$10,X6,Assumptions!$B$6:$B$10),0) -> 12.698053 | AH6: =IFERROR(IF(Assumptions!$B$13="Cost Price",AB6,AA6)*SUMIF(Assumptions!$A$6:$A$10,X6,Assumptions!$C$6:$C$10),0) -> 7.9362831 | AI6: =IFERROR(IF(Assumptions!$B$13="Cost Price",AB6,AA6)*SUMIF(Assumptions!$A$6:$A$10,X6,Assumptions!$D$6:$D$10),0) -> 15.872566 | AJ6: 24.790219 | AK6: =SUM(AG6:AJ6) -> 61.297122 | AL6: 0.33 | AM6: =AC6-AK6 -> 76.488541 | AN6: =IFERROR(AM6/AA6,0) -> 0.48189146 | AO6: =IF(AN6>=Assumptions!$B$3,"OK","Review") -> OK
A7: Corekit AY 2027-2028 | B7: Grade 1 | C7: Maths | D7: T2_G1_Math_Scholars_TB B2B (27) | E7: 1:1 | F7: Book | G7: 2027-2028 | H7: Term 2 | I7: 4000011816 | J7: 46.25 | L7: =J7+K7 -> 46.25 | M7: 0 | N7: =M7*L7 -> 0 | O7: =L7+N7 -> 46.25 | P7: =IFERROR(O7/Q7,"") -> 0.14593128 | Q7: =SUMIFS(O:O,T:T,T7,B:B,B7,A:A,A7,G:G,G7,E:E,E7) -> 316.93 | R7: =V7-SUMIFS(Q:Q,A:A,A7,B:B,B7,G:G,G7,E:E,E7,T:T,"Fixed Price ( Base Price with GST)") -> 2402.3364 | S7: =IF(T7="Fixed Price ( Base Price with GST)",O7,P7*R7) -> 350.57602 | T7: Based on Base % | U7: 4499 | V7: =IFERROR(U7*(1-30%),0) -> 3149.3 | W7: 490110 | X7: Core | Y7: =IFERROR(S7,0) -> 350.57602 | Z7: =IF(ISNUMBER(S7),S7,0) -> 350.57602 | AA7: =IFERROR(Z7/(1+M7),Z7) -> 350.57602 | AB7: =IF(ISNUMBER(J7),J7,0) -> 46.25 | AC7: =AA7-AB7 -> 304.32602 | AD7: =IFERROR(AC7/AA7,0) -> 0.86807426 | AE7: =IFERROR(AC7/AB7,0) -> 6.5800221 | AF7: =IF(AD7>=Assumptions!$B$3,"OK","Review") -> OK | AG7: =IFERROR(IF(Assumptions!$B$13="Cost Price",AB7,AA7)*SUMIF(Assumptions!$A$6:$A$10,X7,Assumptions!$B$6:$B$10),0) -> 28.046082 | AH7: =IFERROR(IF(Assumptions!$B$13="Cost Price",AB7,AA7)*SUMIF(Assumptions!$A$6:$A$10,X7,Assumptions!$C$6:$C$10),0) -> 17.528801 | AI7: =IFERROR(IF(Assumptions!$B$13="Cost Price",AB7,AA7)*SUMIF(Assumptions!$A$6:$A$10,X7,Assumptions!$D$6:$D$10),0) -> 35.057602 | AJ7: 54.753947 | AK7: =SUM(AG7:AJ7) -> 135.38643 | AL7: 0.33 | AM7: =AC7-AK7 -> 168.93959 | AN7: =IFERROR(AM7/AA7,0) -> 0.48189146 | AO7: =IF(AN7>=Assumptions!$B$3,"OK","Review") -> OK
A8: Corekit AY 2027-2028 | B8: Grade 1 | C8: Maths | D8: T2_G1_Math_Scholars_WB B2B (27) | E8: 1:1 | F8: Book | G8: 2027-2028 | H8: Term 2 | I8: 4000011747 | J8: 19.51 | L8: =J8+K8 -> 19.51 | M8: 0 | N8: =M8*L8 -> 0 | O8: =L8+N8 -> 19.51 | P8: =IFERROR(O8/Q8,"") -> 0.061559335 | Q8: =SUMIFS(O:O,T:T,T8,B:B,B8,A:A,A8,G:G,G8,E:E,E8) -> 316.93 | R8: =V8-SUMIFS(Q:Q,A:A,A8,B:B,B8,G:G,G8,E:E,E8,T:T,"Fixed Price ( Base Price with GST)") -> 2402.3364 | S8: =IF(T8="Fixed Price ( Base Price with GST)",O8,P8*R8) -> 147.88623 | T8: Based on Base % | U8: 4499 | V8: =IFERROR(U8*(1-30%),0) -> 3149.3 | W8: 490110 | X8: Core | Y8: =IFERROR(S8,0) -> 147.88623 | Z8: =IF(ISNUMBER(S8),S8,0) -> 147.88623 | AA8: =IFERROR(Z8/(1+M8),Z8) -> 147.88623 | AB8: =IF(ISNUMBER(J8),J8,0) -> 19.51 | AC8: =AA8-AB8 -> 128.37623 | AD8: =IFERROR(AC8/AA8,0) -> 0.86807426 | AE8: =IFERROR(AC8/AB8,0) -> 6.5800221 | AF8: =IF(AD8>=Assumptions!$B$3,"OK","Review") -> OK | AG8: =IFERROR(IF(Assumptions!$B$13="Cost Price",AB8,AA8)*SUMIF(Assumptions!$A$6:$A$10,X8,Assumptions!$B$6:$B$10),0) -> 11.830898 | AH8: =IFERROR(IF(Assumptions!$B$13="Cost Price",AB8,AA8)*SUMIF(Assumptions!$A$6:$A$10,X8,Assumptions!$C$6:$C$10),0) -> 7.3943115 | AI8: =IFERROR(IF(Assumptions!$B$13="Cost Price",AB8,AA8)*SUMIF(Assumptions!$A$6:$A$10,X8,Assumptions!$D$6:$D$10),0) -> 14.788623 | AJ8: 23.097287 | AK8: =SUM(AG8:AJ8) -> 57.11112 | AL8: 0.33 | AM8: =AC8-AK8 -> 71.265111 | AN8: =IFERROR(AM8/AA8,0) -> 0.48189146 | AO8: =IF(AN8>=Assumptions!$B$3,"OK","Review") -> OK
A9: Corekit AY 2027-2028 | B9: Grade 1 | C9: English | D9: T2_G1_English_RC B2B (27) | E9: 1:1 | F9: Workbook | G9: 2027-2028 | H9: Term 2 | I9: 4000011758 | J9: 65.91 | L9: =J9+K9 -> 65.91 | M9: 0 | N9: =M9*L9 -> 0 | O9: =L9+N9 -> 65.91 | P9: =IFERROR(O9/Q9,"") -> 0.2079639 | Q9: =SUMIFS(O:O,T:T,T9,B:B,B9,A:A,A9,G:G,G9,E:E,E9) -> 316.93 | R9: =V9-SUMIFS(Q:Q,A:A,A9,B:B,B9,G:G,G9,E:E,E9,T:T,"Fixed Price ( Base Price with GST)") -> 2402.3364 | S9: =IF(T9="Fixed Price ( Base Price with GST)",O9,P9*R9) -> 499.59926 | T9: Based on Base % | U9: 4499 | V9: =IFERROR(U9*(1-30%),0) -> 3149.3 | W9: 490110 | X9: Core | Y9: =IFERROR(S9,0) -> 499.59926 | Z9: =IF(ISNUMBER(S9),S9,0) -> 499.59926 | AA9: =IFERROR(Z9/(1+M9),Z9) -> 499.59926 | AB9: =IF(ISNUMBER(J9),J9,0) -> 65.91 | AC9: =AA9-AB9 -> 433.68926 | AD9: =IFERROR(AC9/AA9,0) -> 0.86807426 | AE9: =IFERROR(AC9/AB9,0) -> 6.5800221 | AF9: =IF(AD9>=Assumptions!$B$3,"OK","Review") -> OK | AG9: =IFERROR(IF(Assumptions!$B$13="Cost Price",AB9,AA9)*SUMIF(Assumptions!$A$6:$A$10,X9,Assumptions!$B$6:$B$10),0) -> 39.96794 | AH9: =IFERROR(IF(Assumptions!$B$13="Cost Price",AB9,AA9)*SUMIF(Assumptions!$A$6:$A$10,X9,Assumptions!$C$6:$C$10),0) -> 24.979963 | AI9: =IFERROR(IF(Assumptions!$B$13="Cost Price",AB9,AA9)*SUMIF(Assumptions!$A$6:$A$10,X9,Assumptions!$D$6:$D$10),0) -> 49.959926 | AJ9: 78.028814 | AK9: =SUM(AG9:AJ9) -> 192.93664 | AL9: 0.33 | AM9: =AC9-AK9 -> 240.75261 | AN9: =IFERROR(AM9/AA9,0) -> 0.48189146 | AO9: =IF(AN9>=Assumptions!$B$3,"OK","Review") -> OK
A10: Corekit AY 2027-2028 | B10: Grade 1 | C10: English | D10: T2_G1_English_WB B2B (27) | E10: 1:1 | F10: Workbook | G10: 2027-2028 | H10: Term 2 | I10: 4000011769 | J10: 19.51 | L10: =J10+K10 -> 19.51 | M10: 0 | N10: =M10*L10 -> 0 | O10: =L10+N10 -> 19.51 | P10: =IFERROR(O10/Q10,"") -> 0.061559335 | Q10: =SUMIFS(O:O,T:T,T10,B:B,B10,A:A,A10,G:G,G10,E:E,E10) -> 316.93 | R10: =V10-SUMIFS(Q:Q,A:A,A10,B:B,B10,G:G,G10,E:E,E10,T:T,"Fixed Price ( Base Price with GST)") -> 2402.3364 | S10: =IF(T10="Fixed Price ( Base Price with GST)",O10,P10*R10) -> 147.88623 | T10: Based on Base % | U10: 4499 | V10: =IFERROR(U10*(1-30%),0) -> 3149.3 | W10: 490110 | X10: Core | Y10: =IFERROR(S10,0) -> 147.88623 | Z10: =IF(ISNUMBER(S10),S10,0) -> 147.88623 | AA10: =IFERROR(Z10/(1+M10),Z10) -> 147.88623 | AB10: =IF(ISNUMBER(J10),J10,0) -> 19.51 | AC10: =AA10-AB10 -> 128.37623 | AD10: =IFERROR(AC10/AA10,0) -> 0.86807426 | AE10: =IFERROR(AC10/AB10,0) -> 6.5800221 | AF10: =IF(AD10>=Assumptions!$B$3,"OK","Review") -> OK | AG10: =IFERROR(IF(Assumptions!$B$13="Cost Price",AB10,AA10)*SUMIF(Assumptions!$A$6:$A$10,X10,Assumptions!$B$6:$B$10),0) -> 11.830898 | AH10: =IFERROR(IF(Assumptions!$B$13="Cost Price",AB10,AA10)*SUMIF(Assumptions!$A$6:$A$10,X10,Assumptions!$C$6:$C$10),0) -> 7.3943115 | AI10: =IFERROR(IF(Assumptions!$B$13="Cost Price",AB10,AA10)*SUMIF(Assumptions!$A$6:$A$10,X10,Assumptions!$D$6:$D$10),0) -> 14.788623 | AJ10: 23.097287 | AK10: =SUM(AG10:AJ10) -> 57.11112 | AL10: 0.33 | AM10: =AC10-AK10 -> 71.265111 | AN10: =IFERROR(AM10/AA10,0) -> 0.48189146 | AO10: =IF(AN10>=Assumptions!$B$3,"OK","Review") -> OK
A11: Corekit AY 2027-2028 | B11: Grade 1 | C11: Combo Kit | D11: B2B Sci-Pi Visual Maths Kit G1 27-28 | E11: 1:1 | F11: Kit | G11: 2027-2028 | H11: Term 1 | I11: 7000000216 | J11: 210.51 | K11: 10 | L11: =J11+K11 -> 220.51 | M11: 0.18 | N11: =M11*L11 -> 39.6918 | O11: =L11+N11 -> 260.2018 | P11: =IFERROR(O11/Q11,"") -> 0.69669205 | Q11: =SUMIFS(O:O,T:T,T11,B:B,B11,A:A,A11,G:G,G11,E:E,E11) -> 373.4818 | R11: =V11-SUMIFS(Q:Q,A:A,A11,B:B,B11,G:G,G11,E:E,E11,T:T,"Fixed Price ( Base Price with GST)") -> 2402.3364 | S11: =IF(T11="Fixed Price ( Base Price with GST)",O11,P11*R11) -> 260.2018 | T11: Fixed Price ( Base Price with GST) | U11: 4499 | V11: =IFERROR(U11*(1-30%),0) -> 3149.3 | W11: 49119990 | X11: Core | Y11: =IFERROR(S11,0) -> 260.2018 | Z11: =IF(ISNUMBER(S11),S11,0) -> 260.2018 | AA11: =IFERROR(Z11/(1+M11),Z11) -> 220.51 | AB11: =IF(ISNUMBER(J11),J11,0) -> 210.51 | AC11: =AA11-AB11 -> 10 | AD11: =IFERROR(AC11/AA11,0) -> 0.045349417 | AE11: =IFERROR(AC11/AB11,0) -> 0.047503682 | AF11: =IF(AD11>=Assumptions!$B$3,"OK","Review") -> Review | AG11: =IFERROR(IF(Assumptions!$B$13="Cost Price",AB11,AA11)*SUMIF(Assumptions!$A$6:$A$10,X11,Assumptions!$B$6:$B$10),0) -> 17.6408 | AH11: =IFERROR(IF(Assumptions!$B$13="Cost Price",AB11,AA11)*SUMIF(Assumptions!$A$6:$A$10,X11,Assumptions!$C$6:$C$10),0) -> 11.0255 | AI11: =IFERROR(IF(Assumptions!$B$13="Cost Price",AB11,AA11)*SUMIF(Assumptions!$A$6:$A$10,X11,Assumptions!$D$6:$D$10),0) -> 22.051 | AJ11: 22.051 | AK11: =SUM(AG11:AJ11) -> 72.7683 | AL11: 0.33 | AM11: =AC11-AK11 -> -62.7683 | AN11: =IFERROR(AM11/AA11,0) -> -0.28465058 | AO11: =IF(AN11>=Assumptions!$B$3,"OK","Review") -> Review
A12: Corekit AY 2027-2028 | B12: Grade 1 | C12: Service | D12: Services Charges_25_26 | E12: 1:1 | F12: Services Charges | G12: 2027-2028 | H12: Term 1 | I12: 8400007 | J12: 96 | L12: =J12+K12 -> 96 | M12: 0.18 | N12: =M12*L12 -> 17.28 | O12: =L12+N12 -> 113.28 | P12: =IFERROR(O12/Q12,"") -> 0.30330795 | Q12: =SUMIFS(O:O,T:T,T12,B:B,B12,A:A,A12,G:G,G12,E:E,E12) -> 373.4818 | R12: =V12-SUMIFS(Q:Q,A:A,A12,B:B,B12,G:G,G12,E:E,E12,T:T,"Fixed Price ( Base Price with GST)") -> 2402.3364 | S12: =IF(T12="Fixed Price ( Base Price with GST)",O12,P12*R12) -> 113.28 | T12: Fixed Price ( Base Price with GST) | U12: 4499 | V12: =IFERROR(U12*(1-30%),0) -> 3149.3 | W12: 999299 | X12: Core | Y12: =IFERROR(S12,0) -> 113.28 | Z12: =IF(ISNUMBER(S12),S12,0) -> 113.28 | AA12: =IFERROR(Z12/(1+M12),Z12) -> 96 | AB12: =IF(ISNUMBER(J12),J12,0) -> 96 | AC12: =AA12-AB12 -> 0 | AD12: =IFERROR(AC12/AA12,0) -> 0 | AE12: =IFERROR(AC12/AB12,0) -> 0 | AF12: =IF(AD12>=Assumptions!$B$3,"OK","Review") -> Review | AG12: =IFERROR(IF(Assumptions!$B$13="Cost Price",AB12,AA12)*SUMIF(Assumptions!$A$6:$A$10,X12,Assumptions!$B$6:$B$10),0) -> 7.68 | AH12: =IFERROR(IF(Assumptions!$B$13="Cost Price",AB12,AA12)*SUMIF(Assumptions!$A$6:$A$10,X12,Assumptions!$C$6:$C$10),0) -> 4.8 | AI12: =IFERROR(IF(Assumptions!$B$13="Cost Price",AB12,AA12)*SUMIF(Assumptions!$A$6:$A$10,X12,Assumptions!$D$6:$D$10),0) -> 9.6 | AJ12: 9.6 | AK12: =SUM(AG12:AJ12) -> 31.68 | AL12: 0.33 | AM12: =AC12-AK12 -> -31.68 | AN12: =IFERROR(AM12/AA12,0) -> -0.33 | AO12: =IF(AN12>=Assumptions!$B$3,"OK","Review") -> Review
A13: Corekit AY 2027-2028 | B13: Grade 2 | C13: Maths | D13: T1_G2_Math_Scholars_TB B2B (27) | E13: 1:1 | F13: Book | G13: 2027-2028 | H13: Term 1 | I13: 4000011861 | J13: 40.09 | L13: =J13+K13 -> 40.09 | M13: 0 | N13: =M13*L13 -> 0 | O13: =L13+N13 -> 40.09 | P13: =IFERROR(O13/Q13,"") -> 0.12098624 | Q13: =SUMIFS(O:O,T:T,T13,B:B,B13,A:A,A13,G:G,G13,E:E,E13) -> 331.36 | R13: =V13-SUMIFS(Q:Q,A:A,A13,B:B,B13,G:G,G13,E:E,E13,T:T,"Fixed Price ( Base Price with GST)") -> 2387.2088 | S13: =IF(T13="Fixed Price ( Base Price with GST)",O13,P13*R13) -> 288.81941 | T13: Based on Base % | U13: 4499 | V13: =IFERROR(U13*(1-30%),0) -> 3149.3 | W13: 490110 | X13: Core | Y13: =IFERROR(S13,0) -> 288.81941 | Z13: =IF(ISNUMBER(S13),S13,0) -> 288.81941 | AA13: =IFERROR(Z13/(1+M13),Z13) -> 288.81941 | AB13: =IF(ISNUMBER(J13),J13,0) -> 40.09 | AC13: =AA13-AB13 -> 248.72941 | AD13: =IFERROR(AC13/AA13,0) -> 0.86119354 | AE13: =IFERROR(AC13/AB13,0) -> 6.2042757 | AF13: =IF(AD13>=Assumptions!$B$3,"OK","Review") -> OK | AG13: =IFERROR(IF(Assumptions!$B$13="Cost Price",AB13,AA13)*SUMIF(Assumptions!$A$6:$A$10,X13,Assumptions!$B$6:$B$10),0) -> 23.105553 | AH13: =IFERROR(IF(Assumptions!$B$13="Cost Price",AB13,AA13)*SUMIF(Assumptions!$A$6:$A$10,X13,Assumptions!$C$6:$C$10),0) -> 14.440971 | AI13: =IFERROR(IF(Assumptions!$B$13="Cost Price",AB13,AA13)*SUMIF(Assumptions!$A$6:$A$10,X13,Assumptions!$D$6:$D$10),0) -> 28.881941 | AJ13: 45.211454 | AK13: =SUM(AG13:AJ13) -> 111.63992 | AL13: 0.33 | AM13: =AC13-AK13 -> 137.08949 | AN13: =IFERROR(AM13/AA13,0) -> 0.47465471 | AO13: =IF(AN13>=Assumptions!$B$3,"OK","Review") -> OK
A14: Corekit AY 2027-2028 | B14: Grade 2 | C14: Maths | D14: T1_G2_Math_Scholars_WB B2B (27) | E14: 1:1 | F14: Book | G14: 2027-2028 | H14: Term 1 | I14: 4000011872 | J14: 21.01 | L14: =J14+K14 -> 21.01 | M14: 0 | N14: =M14*L14 -> 0 | O14: =L14+N14 -> 21.01 | P14: =IFERROR(O14/Q14,"") -> 0.06340536 | Q14: =SUMIFS(O:O,T:T,T14,B:B,B14,A:A,A14,G:G,G14,E:E,E14) -> 331.36 | R14: =V14-SUMIFS(Q:Q,A:A,A14,B:B,B14,G:G,G14,E:E,E14,T:T,"Fixed Price ( Base Price with GST)") -> 2387.2088 | S14: =IF(T14="Fixed Price ( Base Price with GST)",O14,P14*R14) -> 151.36183 | T14: Based on Base % | U14: 4499 | V14: =IFERROR(U14*(1-30%),0) -> 3149.3 | W14: 490110 | X14: Core | Y14: =IFERROR(S14,0) -> 151.36183 | Z14: =IF(ISNUMBER(S14),S14,0) -> 151.36183 | AA14: =IFERROR(Z14/(1+M14),Z14) -> 151.36183 | AB14: =IF(ISNUMBER(J14),J14,0) -> 21.01 | AC14: =AA14-AB14 -> 130.35183 | AD14: =IFERROR(AC14/AA14,0) -> 0.86119354 | AE14: =IFERROR(AC14/AB14,0) -> 6.2042757 | AF14: =IF(AD14>=Assumptions!$B$3,"OK","Review") -> OK | AG14: =IFERROR(IF(Assumptions!$B$13="Cost Price",AB14,AA14)*SUMIF(Assumptions!$A$6:$A$10,X14,Assumptions!$B$6:$B$10),0) -> 12.108947 | AH14: =IFERROR(IF(Assumptions!$B$13="Cost Price",AB14,AA14)*SUMIF(Assumptions!$A$6:$A$10,X14,Assumptions!$C$6:$C$10),0) -> 7.5680916 | AI14: =IFERROR(IF(Assumptions!$B$13="Cost Price",AB14,AA14)*SUMIF(Assumptions!$A$6:$A$10,X14,Assumptions!$D$6:$D$10),0) -> 15.136183 | AJ14: 23.694005 | AK14: =SUM(AG14:AJ14) -> 58.507226 | AL14: 0.33 | AM14: =AC14-AK14 -> 71.844607 | AN14: =IFERROR(AM14/AA14,0) -> 0.47465471 | AO14: =IF(AN14>=Assumptions!$B$3,"OK","Review") -> OK
A15: Corekit AY 2027-2028 | B15: Grade 2 | C15: English | D15: Annual_G2_English_RB B2B (27) | E15: 1:1 | F15: Book | G15: 2027-2028 | H15: Term 1 | I15: 4000011837 | J15: 20.1 | L15: =J15+K15 -> 20.1 | M15: 0 | N15: =M15*L15 -> 0 | O15: =L15+N15 -> 20.1 | P15: =IFERROR(O15/Q15,"") -> 0.060659102 | Q15: =SUMIFS(O:O,T:T,T15,B:B,B15,A:A,A15,G:G,G15,E:E,E15) -> 331.36 | R15: =V15-SUMIFS(Q:Q,A:A,A15,B:B,B15,G:G,G15,E:E,E15,T:T,"Fixed Price ( Base Price with GST)") -> 2387.2088 | S15: =IF(T15="Fixed Price ( Base Price with GST)",O15,P15*R15) -> 144.80594 | T15: Based on Base % | U15: 4499 | V15: =IFERROR(U15*(1-30%),0) -> 3149.3 | W15: 490110 | X15: Core | Y15: =IFERROR(S15,0) -> 144.80594 | Z15: =IF(ISNUMBER(S15),S15,0) -> 144.80594 | AA15: =IFERROR(Z15/(1+M15),Z15) -> 144.80594 | AB15: =IF(ISNUMBER(J15),J15,0) -> 20.1 | AC15: =AA15-AB15 -> 124.70594 | AD15: =IFERROR(AC15/AA15,0) -> 0.86119354 | AE15: =IFERROR(AC15/AB15,0) -> 6.2042757 | AF15: =IF(AD15>=Assumptions!$B$3,"OK","Review") -> OK | AG15: =IFERROR(IF(Assumptions!$B$13="Cost Price",AB15,AA15)*SUMIF(Assumptions!$A$6:$A$10,X15,Assumptions!$B$6:$B$10),0) -> 11.584475 | AH15: =IFERROR(IF(Assumptions!$B$13="Cost Price",AB15,AA15)*SUMIF(Assumptions!$A$6:$A$10,X15,Assumptions!$C$6:$C$10),0) -> 7.2402971 | AI15: =IFERROR(IF(Assumptions!$B$13="Cost Price",AB15,AA15)*SUMIF(Assumptions!$A$6:$A$10,X15,Assumptions!$D$6:$D$10),0) -> 14.480594 | AJ15: 22.667753 | AK15: =SUM(AG15:AJ15) -> 55.97312 | AL15: 0.33 | AM15: =AC15-AK15 -> 68.732822 | AN15: =IFERROR(AM15/AA15,0) -> 0.47465471 | AO15: =IF(AN15>=Assumptions!$B$3,"OK","Review") -> OK
A16: Corekit AY 2027-2028 | B16: Grade 2 | C16: English | D16: T1_G2_English_RC B2B (27) | E16: 1:1 | F16: Workbook | G16: 2027-2028 | H16: Term 1 | I16: 4000011826 | J16: 66.38 | L16: =J16+K16 -> 66.38 | M16: 0 | N16: =M16*L16 -> 0 | O16: =L16+N16 -> 66.38 | P16: =IFERROR(O16/Q16,"") -> 0.20032593 | Q16: =SUMIFS(O:O,T:T,T16,B:B,B16,A:A,A16,G:G,G16,E:E,E16) -> 331.36 | R16: =V16-SUMIFS(Q:Q,A:A,A16,B:B,B16,G:G,G16,E:E,E16,T:T,"Fixed Price ( Base Price with GST)") -> 2387.2088 | S16: =IF(T16="Fixed Price ( Base Price with GST)",O16,P16*R16) -> 478.21982 | T16: Based on Base % | U16: 4499 | V16: =IFERROR(U16*(1-30%),0) -> 3149.3 | W16: 490110 | X16: Core | Y16: =IFERROR(S16,0) -> 478.21982 | Z16: =IF(ISNUMBER(S16),S16,0) -> 478.21982 | AA16: =IFERROR(Z16/(1+M16),Z16) -> 478.21982 | AB16: =IF(ISNUMBER(J16),J16,0) -> 66.38 | AC16: =AA16-AB16 -> 411.83982 | AD16: =IFERROR(AC16/AA16,0) -> 0.86119354 | AE16: =IFERROR(AC16/AB16,0) -> 6.2042757 | AF16: =IF(AD16>=Assumptions!$B$3,"OK","Review") -> OK | AG16: =IFERROR(IF(Assumptions!$B$13="Cost Price",AB16,AA16)*SUMIF(Assumptions!$A$6:$A$10,X16,Assumptions!$B$6:$B$10),0) -> 38.257586 | AH16: =IFERROR(IF(Assumptions!$B$13="Cost Price",AB16,AA16)*SUMIF(Assumptions!$A$6:$A$10,X16,Assumptions!$C$6:$C$10),0) -> 23.910991 | AI16: =IFERROR(IF(Assumptions!$B$13="Cost Price",AB16,AA16)*SUMIF(Assumptions!$A$6:$A$10,X16,Assumptions!$D$6:$D$10),0) -> 47.821982 | AJ16: 74.859973 | AK16: =SUM(AG16:AJ16) -> 184.85053 | AL16: 0.33 | AM16: =AC16-AK16 -> 226.98929 | AN16: =IFERROR(AM16/AA16,0) -> 0.47465471 | AO16: =IF(AN16>=Assumptions!$B$3,"OK","Review") -> OK
A17: Corekit AY 2027-2028 | B17: Grade 2 | C17: English | D17: T1_G2_English_WB B2B (27) | E17: 1:1 | F17: Workbook | G17: 2027-2028 | H17: Term 1 | I17: 4000011846 | J17: 25.48 | L17: =J17+K17 -> 25.48 | M17: 0 | N17: =M17*L17 -> 0 | O17: =L17+N17 -> 25.48 | P17: =IFERROR(O17/Q17,"") -> 0.07689522 | Q17: =SUMIFS(O:O,T:T,T17,B:B,B17,A:A,A17,G:G,G17,E:E,E17) -> 331.36 | R17: =V17-SUMIFS(Q:Q,A:A,A17,B:B,B17,G:G,G17,E:E,E17,T:T,"Fixed Price ( Base Price with GST)") -> 2387.2088 | S17: =IF(T17="Fixed Price ( Base Price with GST)",O17,P17*R17) -> 183.56495 | T17: Based on Base % | U17: 4499 | V17: =IFERROR(U17*(1-30%),0) -> 3149.3 | W17: 490110 | X17: Core | Y17: =IFERROR(S17,0) -> 183.56495 | Z17: =IF(ISNUMBER(S17),S17,0) -> 183.56495 | AA17: =IFERROR(Z17/(1+M17),Z17) -> 183.56495 | AB17: =IF(ISNUMBER(J17),J17,0) -> 25.48 | AC17: =AA17-AB17 -> 158.08495 | AD17: =IFERROR(AC17/AA17,0) -> 0.86119354 | AE17: =IFERROR(AC17/AB17,0) -> 6.2042757 | AF17: =IF(AD17>=Assumptions!$B$3,"OK","Review") -> OK | AG17: =IFERROR(IF(Assumptions!$B$13="Cost Price",AB17,AA17)*SUMIF(Assumptions!$A$6:$A$10,X17,Assumptions!$B$6:$B$10),0) -> 14.685196 | AH17: =IFERROR(IF(Assumptions!$B$13="Cost Price",AB17,AA17)*SUMIF(Assumptions!$A$6:$A$10,X17,Assumptions!$C$6:$C$10),0) -> 9.1782473 | AI17: =IFERROR(IF(Assumptions!$B$13="Cost Price",AB17,AA17)*SUMIF(Assumptions!$A$6:$A$10,X17,Assumptions!$D$6:$D$10),0) -> 18.356495 | AJ17: 28.735042 | AK17: =SUM(AG17:AJ17) -> 70.95498 | AL17: 0.33 | AM17: =AC17-AK17 -> 87.129965 | AN17: =IFERROR(AM17/AA17,0) -> 0.47465471 | AO17: =IF(AN17>=Assumptions!$B$3,"OK","Review") -> OK
A18: Corekit AY 2027-2028 | B18: Grade 2 | C18: Maths | D18: T2_G2_Math_Scholars_TB B2B (27) | E18: 1:1 | F18: Book | G18: 2027-2028 | H18: Term 2 | I18: 4000011847 | J18: 50.5 | L18: =J18+K18 -> 50.5 | M18: 0 | N18: =M18*L18 -> 0 | O18: =L18+N18 -> 50.5 | P18: =IFERROR(O18/Q18,"") -> 0.15240222 | Q18: =SUMIFS(O:O,T:T,T18,B:B,B18,A:A,A18,G:G,G18,E:E,E18) -> 331.36 | R18: =V18-SUMIFS(Q:Q,A:A,A18,B:B,B18,G:G,G18,E:E,E18,T:T,"Fixed Price ( Base Price with GST)") -> 2387.2088 | S18: =IF(T18="Fixed Price ( Base Price with GST)",O18,P18*R18) -> 363.81592 | T18: Based on Base % | U18: 4499 | V18: =IFERROR(U18*(1-30%),0) -> 3149.3 | W18: 490110 | X18: Core | Y18: =IFERROR(S18,0) -> 363.81592 | Z18: =IF(ISNUMBER(S18),S18,0) -> 363.81592 | AA18: =IFERROR(Z18/(1+M18),Z18) -> 363.81592 | AB18: =IF(ISNUMBER(J18),J18,0) -> 50.5 | AC18: =AA18-AB18 -> 313.31592 | AD18: =IFERROR(AC18/AA18,0) -> 0.86119354 | AE18: =IFERROR(AC18/AB18,0) -> 6.2042757 | AF18: =IF(AD18>=Assumptions!$B$3,"OK","Review") -> OK | AG18: =IFERROR(IF(Assumptions!$B$13="Cost Price",AB18,AA18)*SUMIF(Assumptions!$A$6:$A$10,X18,Assumptions!$B$6:$B$10),0) -> 29.105274 | AH18: =IFERROR(IF(Assumptions!$B$13="Cost Price",AB18,AA18)*SUMIF(Assumptions!$A$6:$A$10,X18,Assumptions!$C$6:$C$10),0) -> 18.190796 | AI18: =IFERROR(IF(Assumptions!$B$13="Cost Price",AB18,AA18)*SUMIF(Assumptions!$A$6:$A$10,X18,Assumptions!$D$6:$D$10),0) -> 36.381592 | AJ18: 56.95132 | AK18: =SUM(AG18:AJ18) -> 140.62898 | AL18: 0.33 | AM18: =AC18-AK18 -> 172.68694 | AN18: =IFERROR(AM18/AA18,0) -> 0.47465471 | AO18: =IF(AN18>=Assumptions!$B$3,"OK","Review") -> OK
A19: Corekit AY 2027-2028 | B19: Grade 2 | C19: Maths | D19: T2_G2_Math_Scholars_WB B2B (27) | E19: 1:1 | F19: Book | G19: 2027-2028 | H19: Term 2 | I19: 4000011848 | J19: 21.01 | L19: =J19+K19 -> 21.01 | M19: 0 | N19: =M19*L19 -> 0 | O19: =L19+N19 -> 21.01 | P19: =IFERROR(O19/Q19,"") -> 0.06340536 | Q19: =SUMIFS(O:O,T:T,T19,B:B,B19,A:A,A19,G:G,G19,E:E,E19) -> 331.36 | R19: =V19-SUMIFS(Q:Q,A:A,A19,B:B,B19,G:G,G19,E:E,E19,T:T,"Fixed Price ( Base Price with GST)") -> 2387.2088 | S19: =IF(T19="Fixed Price ( Base Price with GST)",O19,P19*R19) -> 151.36183 | T19: Based on Base % | U19: 4499 | V19: =IFERROR(U19*(1-30%),0) -> 3149.3 | W19: 490110 | X19: Core | Y19: =IFERROR(S19,0) -> 151.36183 | Z19: =IF(ISNUMBER(S19),S19,0) -> 151.36183 | AA19: =IFERROR(Z19/(1+M19),Z19) -> 151.36183 | AB19: =IF(ISNUMBER(J19),J19,0) -> 21.01 | AC19: =AA19-AB19 -> 130.35183 | AD19: =IFERROR(AC19/AA19,0) -> 0.86119354 | AE19: =IFERROR(AC19/AB19,0) -> 6.2042757 | AF19: =IF(AD19>=Assumptions!$B$3,"OK","Review") -> OK | AG19: =IFERROR(IF(Assumptions!$B$13="Cost Price",AB19,AA19)*SUMIF(Assumptions!$A$6:$A$10,X19,Assumptions!$B$6:$B$10),0) -> 12.108947 | AH19: =IFERROR(IF(Assumptions!$B$13="Cost Price",AB19,AA19)*SUMIF(Assumptions!$A$6:$A$10,X19,Assumptions!$C$6:$C$10),0) -> 7.5680916 | AI19: =IFERROR(IF(Assumptions!$B$13="Cost Price",AB19,AA19)*SUMIF(Assumptions!$A$6:$A$10,X19,Assumptions!$D$6:$D$10),0) -> 15.136183 | AJ19: 23.694005 | AK19: =SUM(AG19:AJ19) -> 58.507226 | AL19: 0.33 | AM19: =AC19-AK19 -> 71.844607 | AN19: =IFERROR(AM19/AA19,0) -> 0.47465471 | AO19: =IF(AN19>=Assumptions!$B$3,"OK","Review") -> OK
A20: Corekit AY 2027-2028 | B20: Grade 2 | C20: English | D20: T2_G2_English_RC B2B (27) | E20: 1:1 | F20: Workbook | G20: 2027-2028 | H20: Term 2 | I20: 4000011849 | J20: 62.84 | L20: =J20+K20 -> 62.84 | M20: 0 | N20: =M20*L20 -> 0 | O20: =L20+N20 -> 62.84 | P20: =IFERROR(O20/Q20,"") -> 0.18964268 | Q20: =SUMIFS(O:O,T:T,T20,B:B,B20,A:A,A20,G:G,G20,E:E,E20) -> 331.36 | R20: =V20-SUMIFS(Q:Q,A:A,A20,B:B,B20,G:G,G20,E:E,E20,T:T,"Fixed Price ( Base Price with GST)") -> 2387.2088 | S20: =IF(T20="Fixed Price ( Base Price with GST)",O20,P20*R20) -> 452.71669 | T20: Based on Base % | U20: 4499 | V20: =IFERROR(U20*(1-30%),0) -> 3149.3 | W20: 490110 | X20: Core | Y20: =IFERROR(S20,0) -> 452.71669 | Z20: =IF(ISNUMBER(S20),S20,0) -> 452.71669 | AA20: =IFERROR(Z20/(1+M20),Z20) -> 452.71669 | AB20: =IF(ISNUMBER(J20),J20,0) -> 62.84 | AC20: =AA20-AB20 -> 389.87669 | AD20: =IFERROR(AC20/AA20,0) -> 0.86119354 | AE20: =IFERROR(AC20/AB20,0) -> 6.2042757 | AF20: =IF(AD20>=Assumptions!$B$3,"OK","Review") -> OK | AG20: =IFERROR(IF(Assumptions!$B$13="Cost Price",AB20,AA20)*SUMIF(Assumptions!$A$6:$A$10,X20,Assumptions!$B$6:$B$10),0) -> 36.217335 | AH20: =IFERROR(IF(Assumptions!$B$13="Cost Price",AB20,AA20)*SUMIF(Assumptions!$A$6:$A$10,X20,Assumptions!$C$6:$C$10),0) -> 22.635834 | AI20: =IFERROR(IF(Assumptions!$B$13="Cost Price",AB20,AA20)*SUMIF(Assumptions!$A$6:$A$10,X20,Assumptions!$D$6:$D$10),0) -> 45.271669 | AJ20: 70.867742 | AK20: =SUM(AG20:AJ20) -> 174.99258 | AL20: 0.33 | AM20: =AC20-AK20 -> 214.88411 | AN20: =IFERROR(AM20/AA20,0) -> 0.47465471 | AO20: =IF(AN20>=Assumptions!$B$3,"OK","Review") -> OK
A21: Corekit AY 2027-2028 | B21: Grade 2 | C21: English | D21: T2_G2_English_WB B2B (27) | E21: 1:1 | F21: Workbook | G21: 2027-2028 | H21: Term 2 | I21: 4000011850 | J21: 23.95 | L21: =J21+K21 -> 23.95 | M21: 0 | N21: =M21*L21 -> 0 | O21: =L21+N21 -> 23.95 | P21: =IFERROR(O21/Q21,"") -> 0.072277885 | Q21: =SUMIFS(O:O,T:T,T21,B:B,B21,A:A,A21,G:G,G21,E:E,E21) -> 331.36 | R21: =V21-SUMIFS(Q:Q,A:A,A21,B:B,B21,G:G,G21,E:E,E21,T:T,"Fixed Price ( Base Price with GST)") -> 2387.2088 | S21: =IF(T21="Fixed Price ( Base Price with GST)",O21,P21*R21) -> 172.5424 | T21: Based on Base % | U21: 4499 | V21: =IFERROR(U21*(1-30%),0) -> 3149.3 | W21: 490110 | X21: Core | Y21: =IFERROR(S21,0) -> 172.5424 | Z21: =IF(ISNUMBER(S21),S21,0) -> 172.5424 | AA21: =IFERROR(Z21/(1+M21),Z21) -> 172.5424 | AB21: =IF(ISNUMBER(J21),J21,0) -> 23.95 | AC21: =AA21-AB21 -> 148.5924 | AD21: =IFERROR(AC21/AA21,0) -> 0.86119354 | AE21: =IFERROR(AC21/AB21,0) -> 6.2042757 | AF21: =IF(AD21>=Assumptions!$B$3,"OK","Review") -> OK | AG21: =IFERROR(IF(Assumptions!$B$13="Cost Price",AB21,AA21)*SUMIF(Assumptions!$A$6:$A$10,X21,Assumptions!$B$6:$B$10),0) -> 13.803392 | AH21: =IFERROR(IF(Assumptions!$B$13="Cost Price",AB21,AA21)*SUMIF(Assumptions!$A$6:$A$10,X21,Assumptions!$C$6:$C$10),0) -> 8.6271202 | AI21: =IFERROR(IF(Assumptions!$B$13="Cost Price",AB21,AA21)*SUMIF(Assumptions!$A$6:$A$10,X21,Assumptions!$D$6:$D$10),0) -> 17.25424 | AJ21: 27.009586 | AK21: =SUM(AG21:AJ21) -> 66.694339 | AL21: 0.33 | AM21: =AC21-AK21 -> 81.898064 | AN21: =IFERROR(AM21/AA21,0) -> 0.47465471 | AO21: =IF(AN21>=Assumptions!$B$3,"OK","Review") -> OK
A22: Corekit AY 2027-2028 | B22: Grade 2 | C22: Combo Kit | D22: B2B Sci-Pi Visual Maths Kit G2 27-28 | E22: 1:1 | F22: Kit | G22: 2027-2028 | H22: Term 1 | I22: 7000000223 | J22: 216.92 | K22: 10 | L22: =J22+K22 -> 226.92 | M22: 0.18 | N22: =M22*L22 -> 40.8456 | O22: =L22+N22 -> 267.7656 | P22: =IFERROR(O22/Q22,"") -> 0.70271275 | Q22: =SUMIFS(O:O,T:T,T22,B:B,B22,A:A,A22,G:G,G22,E:E,E22) -> 381.0456 | R22: =V22-SUMIFS(Q:Q,A:A,A22,B:B,B22,G:G,G22,E:E,E22,T:T,"Fixed Price ( Base Price with GST)") -> 2387.2088 | S22: =IF(T22="Fixed Price ( Base Price with GST)",O22,P22*R22) -> 267.7656 | T22: Fixed Price ( Base Price with GST) | U22: 4499 | V22: =IFERROR(U22*(1-30%),0) -> 3149.3 | W22: 49119990 | X22: Core | Y22: =IFERROR(S22,0) -> 267.7656 | Z22: =IF(ISNUMBER(S22),S22,0) -> 267.7656 | AA22: =IFERROR(Z22/(1+M22),Z22) -> 226.92 | AB22: =IF(ISNUMBER(J22),J22,0) -> 216.92 | AC22: =AA22-AB22 -> 10 | AD22: =IFERROR(AC22/AA22,0) -> 0.044068394 | AE22: =IFERROR(AC22/AB22,0) -> 0.046099945 | AF22: =IF(AD22>=Assumptions!$B$3,"OK","Review") -> Review | AG22: =IFERROR(IF(Assumptions!$B$13="Cost Price",AB22,AA22)*SUMIF(Assumptions!$A$6:$A$10,X22,Assumptions!$B$6:$B$10),0) -> 18.1536 | AH22: =IFERROR(IF(Assumptions!$B$13="Cost Price",AB22,AA22)*SUMIF(Assumptions!$A$6:$A$10,X22,Assumptions!$C$6:$C$10),0) -> 11.346 | AI22: =IFERROR(IF(Assumptions!$B$13="Cost Price",AB22,AA22)*SUMIF(Assumptions!$A$6:$A$10,X22,Assumptions!$D$6:$D$10),0) -> 22.692 | AJ22: 22.692 | AK22: =SUM(AG22:AJ22) -> 74.8836 | AL22: 0.33 | AM22: =AC22-AK22 -> -64.8836 | AN22: =IFERROR(AM22/AA22,0) -> -0.28593161 | AO22: =IF(AN22>=Assumptions!$B$3,"OK","Review") -> Review
A23: Corekit AY 2027-2028 | B23: Grade 2 | C23: Service | D23: Services Charges_25_26 | E23: 1:1 | F23: Services Charges | G23: 2027-2028 | H23: Term 1 | I23: 8400007 | J23: 96 | L23: =J23+K23 -> 96 | M23: 0.18 | N23: =M23*L23 -> 17.28 | O23: =L23+N23 -> 113.28 | P23: =IFERROR(O23/Q23,"") -> 0.29728725 | Q23: =SUMIFS(O:O,T:T,T23,B:B,B23,A:A,A23,G:G,G23,E:E,E23) -> 381.0456 | R23: =V23-SUMIFS(Q:Q,A:A,A23,B:B,B23,G:G,G23,E:E,E23,T:T,"Fixed Price ( Base Price with GST)") -> 2387.2088 | S23: =IF(T23="Fixed Price ( Base Price with GST)",O23,P23*R23) -> 113.28 | T23: Fixed Price ( Base Price with GST) | U23: 4499 | V23: =IFERROR(U23*(1-30%),0) -> 3149.3 | W23: 999299 | X23: Core | Y23: =IFERROR(S23,0) -> 113.28 | Z23: =IF(ISNUMBER(S23),S23,0) -> 113.28 | AA23: =IFERROR(Z23/(1+M23),Z23) -> 96 | AB23: =IF(ISNUMBER(J23),J23,0) -> 96 | AC23: =AA23-AB23 -> 0 | AD23: =IFERROR(AC23/AA23,0) -> 0 | AE23: =IFERROR(AC23/AB23,0) -> 0 | AF23: =IF(AD23>=Assumptions!$B$3,"OK","Review") -> Review | AG23: =IFERROR(IF(Assumptions!$B$13="Cost Price",AB23,AA23)*SUMIF(Assumptions!$A$6:$A$10,X23,Assumptions!$B$6:$B$10),0) -> 7.68 | AH23: =IFERROR(IF(Assumptions!$B$13="Cost Price",AB23,AA23)*SUMIF(Assumptions!$A$6:$A$10,X23,Assumptions!$C$6:$C$10),0) -> 4.8 | AI23: =IFERROR(IF(Assumptions!$B$13="Cost Price",AB23,AA23)*SUMIF(Assumptions!$A$6:$A$10,X23,Assumptions!$D$6:$D$10),0) -> 9.6 | AJ23: 9.6 | AK23: =SUM(AG23:AJ23) -> 31.68 | AL23: 0.33 | AM23: =AC23-AK23 -> -31.68 | AN23: =IFERROR(AM23/AA23,0) -> -0.33 | AO23: =IF(AN23>=Assumptions!$B$3,"OK","Review") -> Review
A24: Corekit AY 2027-2028 | B24: Grade 3 | C24: Science | D24: T1_G3_Science Explorers_TB B2B (27) | E24: 1:1 | F24: Book | G24: 2027-2028 | H24: Term 1 | I24: 4000011851 | J24: 30 | L24: =J24+K24 -> 30 | M24: 0 | N24: =M24*L24 -> 0 | O24: =L24+N24 -> 30 | P24: =IFERROR(O24/Q24,"") -> 0.060504608 | Q24: =SUMIFS(O:O,T:T,T24,B:B,B24,A:A,A24,G:G,G24,E:E,E24) -> 495.83 | R24: =V24-SUMIFS(Q:Q,A:A,A24,B:B,B24,G:G,G24,E:E,E24,T:T,"Fixed Price ( Base Price with GST)") -> 2992.764 | S24: =IF(T24="Fixed Price ( Base Price with GST)",O24,P24*R24) -> 181.07601 | T24: Based on Base % | U24: 5599 | V24: =IFERROR(U24*(1-30%),0) -> 3919.3 | W24: 490110 | X24: Core | Y24: =IFERROR(S24,0) -> 181.07601 | Z24: =IF(ISNUMBER(S24),S24,0) -> 181.07601 | AA24: =IFERROR(Z24/(1+M24),Z24) -> 181.07601 | AB24: =IF(ISNUMBER(J24),J24,0) -> 30 | AC24: =AA24-AB24 -> 151.07601 | AD24: =IFERROR(AC24/AA24,0) -> 0.83432372 | AE24: =IFERROR(AC24/AB24,0) -> 5.0358671 | AF24: =IF(AD24>=Assumptions!$B$3,"OK","Review") -> OK | AG24: =IFERROR(IF(Assumptions!$B$13="Cost Price",AB24,AA24)*SUMIF(Assumptions!$A$6:$A$10,X24,Assumptions!$B$6:$B$10),0) -> 14.486081 | AH24: =IFERROR(IF(Assumptions!$B$13="Cost Price",AB24,AA24)*SUMIF(Assumptions!$A$6:$A$10,X24,Assumptions!$C$6:$C$10),0) -> 9.0538007 | AI24: =IFERROR(IF(Assumptions!$B$13="Cost Price",AB24,AA24)*SUMIF(Assumptions!$A$6:$A$10,X24,Assumptions!$D$6:$D$10),0) -> 18.107601 | AJ24: 28.27056 | AK24: =SUM(AG24:AJ24) -> 69.918044 | AL24: 0.33 | AM24: =AC24-AK24 -> 81.15797 | AN24: =IFERROR(AM24/AA24,0) -> 0.44819835 | AO24: =IF(AN24>=Assumptions!$B$3,"OK","Review") -> OK
A25: Corekit AY 2027-2028 | B25: Grade 3 | C25: Science | D25: T1_G3_Science Explorers_WB B2B (27) | E25: 1:1 | F25: Book | G25: 2027-2028 | H25: Term 1 | I25: 4000011853 | J25: 16.29 | L25: =J25+K25 -> 16.29 | M25: 0 | N25: =M25*L25 -> 0 | O25: =L25+N25 -> 16.29 | P25: =IFERROR(O25/Q25,"") -> 0.032854002 | Q25: =SUMIFS(O:O,T:T,T25,B:B,B25,A:A,A25,G:G,G25,E:E,E25) -> 495.83 | R25: =V25-SUMIFS(Q:Q,A:A,A25,B:B,B25,G:G,G25,E:E,E25,T:T,"Fixed Price ( Base Price with GST)") -> 2992.764 | S25: =IF(T25="Fixed Price ( Base Price with GST)",O25,P25*R25) -> 98.324276 | T25: Based on Base % | U25: 5599 | V25: =IFERROR(U25*(1-30%),0) -> 3919.3 | W25: 490110 | X25: Core | Y25: =IFERROR(S25,0) -> 98.324276 | Z25: =IF(ISNUMBER(S25),S25,0) -> 98.324276 | AA25: =IFERROR(Z25/(1+M25),Z25) -> 98.324276 | AB25: =IF(ISNUMBER(J25),J25,0) -> 16.29 | AC25: =AA25-AB25 -> 82.034276 | AD25: =IFERROR(AC25/AA25,0) -> 0.83432372 | AE25: =IFERROR(AC25/AB25,0) -> 5.0358671 | AF25: =IF(AD25>=Assumptions!$B$3,"OK","Review") -> OK | AG25: =IFERROR(IF(Assumptions!$B$13="Cost Price",AB25,AA25)*SUMIF(Assumptions!$A$6:$A$10,X25,Assumptions!$B$6:$B$10),0) -> 7.865942 | AH25: =IFERROR(IF(Assumptions!$B$13="Cost Price",AB25,AA25)*SUMIF(Assumptions!$A$6:$A$10,X25,Assumptions!$C$6:$C$10),0) -> 4.9162138 | AI25: =IFERROR(IF(Assumptions!$B$13="Cost Price",AB25,AA25)*SUMIF(Assumptions!$A$6:$A$10,X25,Assumptions!$D$6:$D$10),0) -> 9.8324276 | AJ25: 15.350914 | AK25: =SUM(AG25:AJ25) -> 37.965498 | AL25: 0.33 | AM25: =AC25-AK25 -> 44.068778 | AN25: =IFERROR(AM25/AA25,0) -> 0.44819835 | AO25: =IF(AN25>=Assumptions!$B$3,"OK","Review") -> OK
A26: Corekit AY 2027-2028 | B26: Grade 3 | C26: Maths | D26: T1_G3_Math_Scholars_TB B2B (27) | E26: 1:1 | F26: Book | G26: 2027-2028 | H26: Term 1 | I26: 4000011854 | J26: 43.03 | L26: =J26+K26 -> 43.03 | M26: 0 | N26: =M26*L26 -> 0 | O26: =L26+N26 -> 43.03 | P26: =IFERROR(O26/Q26,"") -> 0.086783777 | Q26: =SUMIFS(O:O,T:T,T26,B:B,B26,A:A,A26,G:G,G26,E:E,E26) -> 495.83 | R26: =V26-SUMIFS(Q:Q,A:A,A26,B:B,B26,G:G,G26,E:E,E26,T:T,"Fixed Price ( Base Price with GST)") -> 2992.764 | S26: =IF(T26="Fixed Price ( Base Price with GST)",O26,P26*R26) -> 259.72336 | T26: Based on Base % | U26: 5599 | V26: =IFERROR(U26*(1-30%),0) -> 3919.3 | W26: 490110 | X26: Core | Y26: =IFERROR(S26,0) -> 259.72336 | Z26: =IF(ISNUMBER(S26),S26,0) -> 259.72336 | AA26: =IFERROR(Z26/(1+M26),Z26) -> 259.72336 | AB26: =IF(ISNUMBER(J26),J26,0) -> 43.03 | AC26: =AA26-AB26 -> 216.69336 | AD26: =IFERROR(AC26/AA26,0) -> 0.83432372 | AE26: =IFERROR(AC26/AB26,0) -> 5.0358671 | AF26: =IF(AD26>=Assumptions!$B$3,"OK","Review") -> OK | AG26: =IFERROR(IF(Assumptions!$B$13="Cost Price",AB26,AA26)*SUMIF(Assumptions!$A$6:$A$10,X26,Assumptions!$B$6:$B$10),0) -> 20.777869 | AH26: =IFERROR(IF(Assumptions!$B$13="Cost Price",AB26,AA26)*SUMIF(Assumptions!$A$6:$A$10,X26,Assumptions!$C$6:$C$10),0) -> 12.986168 | AI26: =IFERROR(IF(Assumptions!$B$13="Cost Price",AB26,AA26)*SUMIF(Assumptions!$A$6:$A$10,X26,Assumptions!$D$6:$D$10),0) -> 25.972336 | AJ26: 40.549407 | AK26: =SUM(AG26:AJ26) -> 100.28578 | AL26: 0.33 | AM26: =AC26-AK26 -> 116.40758 | AN26: =IFERROR(AM26/AA26,0) -> 0.44819835 | AO26: =IF(AN26>=Assumptions!$B$3,"OK","Review") -> OK
A27: Corekit AY 2027-2028 | B27: Grade 3 | C27: Maths | D27: T1_G3_Math_Scholars_WB B2B (27) | E27: 1:1 | F27: Book | G27: 2027-2028 | H27: Term 1 | I27: 4000011855 | J27: 20.67 | L27: =J27+K27 -> 20.67 | M27: 0 | N27: =M27*L27 -> 0 | O27: =L27+N27 -> 20.67 | P27: =IFERROR(O27/Q27,"") -> 0.041687675 | Q27: =SUMIFS(O:O,T:T,T27,B:B,B27,A:A,A27,G:G,G27,E:E,E27) -> 495.83 | R27: =V27-SUMIFS(Q:Q,A:A,A27,B:B,B27,G:G,G27,E:E,E27,T:T,"Fixed Price ( Base Price with GST)") -> 2992.764 | S27: =IF(T27="Fixed Price ( Base Price with GST)",O27,P27*R27) -> 124.76137 | T27: Based on Base % | U27: 5599 | V27: =IFERROR(U27*(1-30%),0) -> 3919.3 | W27: 490110 | X27: Core | Y27: =IFERROR(S27,0) -> 124.76137 | Z27: =IF(ISNUMBER(S27),S27,0) -> 124.76137 | AA27: =IFERROR(Z27/(1+M27),Z27) -> 124.76137 | AB27: =IF(ISNUMBER(J27),J27,0) -> 20.67 | AC27: =AA27-AB27 -> 104.09137 | AD27: =IFERROR(AC27/AA27,0) -> 0.83432372 | AE27: =IFERROR(AC27/AB27,0) -> 5.0358671 | AF27: =IF(AD27>=Assumptions!$B$3,"OK","Review") -> OK | AG27: =IFERROR(IF(Assumptions!$B$13="Cost Price",AB27,AA27)*SUMIF(Assumptions!$A$6:$A$10,X27,Assumptions!$B$6:$B$10),0) -> 9.9809099 | AH27: =IFERROR(IF(Assumptions!$B$13="Cost Price",AB27,AA27)*SUMIF(Assumptions!$A$6:$A$10,X27,Assumptions!$C$6:$C$10),0) -> 6.2380687 | AI27: =IFERROR(IF(Assumptions!$B$13="Cost Price",AB27,AA27)*SUMIF(Assumptions!$A$6:$A$10,X27,Assumptions!$D$6:$D$10),0) -> 12.476137 | AJ27: 19.478416 | AK27: =SUM(AG27:AJ27) -> 48.173532 | AL27: 0.33 | AM27: =AC27-AK27 -> 55.917842 | AN27: =IFERROR(AM27/AA27,0) -> 0.44819835 | AO27: =IF(AN27>=Assumptions!$B$3,"OK","Review") -> OK
A28: Corekit AY 2027-2028 | B28: Grade 3 | C28: English | D28: Annual_G3_English_Comp B2B (27) | E28: 1:1 | F28: Book | G28: 2027-2028 | H28: Term 1 | I28: 4000011857 | J28: 28.34 | L28: =J28+K28 -> 28.34 | M28: 0 | N28: =M28*L28 -> 0 | O28: =L28+N28 -> 28.34 | P28: =IFERROR(O28/Q28,"") -> 0.057156687 | Q28: =SUMIFS(O:O,T:T,T28,B:B,B28,A:A,A28,G:G,G28,E:E,E28) -> 495.83 | R28: =V28-SUMIFS(Q:Q,A:A,A28,B:B,B28,G:G,G28,E:E,E28,T:T,"Fixed Price ( Base Price with GST)") -> 2992.764 | S28: =IF(T28="Fixed Price ( Base Price with GST)",O28,P28*R28) -> 171.05647 | T28: Based on Base % | U28: 5599 | V28: =IFERROR(U28*(1-30%),0) -> 3919.3 | W28: 490110 | X28: Core | Y28: =IFERROR(S28,0) -> 171.05647 | Z28: =IF(ISNUMBER(S28),S28,0) -> 171.05647 | AA28: =IFERROR(Z28/(1+M28),Z28) -> 171.05647 | AB28: =IF(ISNUMBER(J28),J28,0) -> 28.34 | AC28: =AA28-AB28 -> 142.71647 | AD28: =IFERROR(AC28/AA28,0) -> 0.83432372 | AE28: =IFERROR(AC28/AB28,0) -> 5.0358671 | AF28: =IF(AD28>=Assumptions!$B$3,"OK","Review") -> OK | AG28: =IFERROR(IF(Assumptions!$B$13="Cost Price",AB28,AA28)*SUMIF(Assumptions!$A$6:$A$10,X28,Assumptions!$B$6:$B$10),0) -> 13.684518 | AH28: =IFERROR(IF(Assumptions!$B$13="Cost Price",AB28,AA28)*SUMIF(Assumptions!$A$6:$A$10,X28,Assumptions!$C$6:$C$10),0) -> 8.5528237 | AI28: =IFERROR(IF(Assumptions!$B$13="Cost Price",AB28,AA28)*SUMIF(Assumptions!$A$6:$A$10,X28,Assumptions!$D$6:$D$10),0) -> 17.105647 | AJ28: 26.706256 | AK28: =SUM(AG28:AJ28) -> 66.049245 | AL28: 0.33 | AM28: =AC28-AK28 -> 76.667229 | AN28: =IFERROR(AM28/AA28,0) -> 0.44819835 | AO28: =IF(AN28>=Assumptions!$B$3,"OK","Review") -> OK
A29: Corekit AY 2027-2028 | B29: Grade 3 | C29: English | D29: T1_G3_English_RC B2B (27) | E29: 1:1 | F29: Workbook | G29: 2027-2028 | H29: Term 1 | I29: 4000011856 | J29: 65.83 | L29: =J29+K29 -> 65.83 | M29: 0 | N29: =M29*L29 -> 0 | O29: =L29+N29 -> 65.83 | P29: =IFERROR(O29/Q29,"") -> 0.13276728 | Q29: =SUMIFS(O:O,T:T,T29,B:B,B29,A:A,A29,G:G,G29,E:E,E29) -> 495.83 | R29: =V29-SUMIFS(Q:Q,A:A,A29,B:B,B29,G:G,G29,E:E,E29,T:T,"Fixed Price ( Base Price with GST)") -> 2992.764 | S29: =IF(T29="Fixed Price ( Base Price with GST)",O29,P29*R29) -> 397.34113 | T29: Based on Base % | U29: 5599 | V29: =IFERROR(U29*(1-30%),0) -> 3919.3 | W29: 490110 | X29: Core | Y29: =IFERROR(S29,0) -> 397.34113 | Z29: =IF(ISNUMBER(S29),S29,0) -> 397.34113 | AA29: =IFERROR(Z29/(1+M29),Z29) -> 397.34113 | AB29: =IF(ISNUMBER(J29),J29,0) -> 65.83 | AC29: =AA29-AB29 -> 331.51113 | AD29: =IFERROR(AC29/AA29,0) -> 0.83432372 | AE29: =IFERROR(AC29/AB29,0) -> 5.0358671 | AF29: =IF(AD29>=Assumptions!$B$3,"OK","Review") -> OK | AG29: =IFERROR(IF(Assumptions!$B$13="Cost Price",AB29,AA29)*SUMIF(Assumptions!$A$6:$A$10,X29,Assumptions!$B$6:$B$10),0) -> 31.787291 | AH29: =IFERROR(IF(Assumptions!$B$13="Cost Price",AB29,AA29)*SUMIF(Assumptions!$A$6:$A$10,X29,Assumptions!$C$6:$C$10),0) -> 19.867057 | AI29: =IFERROR(IF(Assumptions!$B$13="Cost Price",AB29,AA29)*SUMIF(Assumptions!$A$6:$A$10,X29,Assumptions!$D$6:$D$10),0) -> 39.734113 | AJ29: 62.035033 | AK29: =SUM(AG29:AJ29) -> 153.42349 | AL29: 0.33 | AM29: =AC29-AK29 -> 178.08764 | AN29: =IFERROR(AM29/AA29,0) -> 0.44819835 | AO29: =IF(AN29>=Assumptions!$B$3,"OK","Review") -> OK
A30: Corekit AY 2027-2028 | B30: Grade 3 | C30: English | D30: T1_G3_English_WB B2B (27) | E30: 1:1 | F30: Workbook | G30: 2027-2028 | H30: Term 1 | I30: 4000011858 | J30: 16.29 | L30: =J30+K30 -> 16.29 | M30: 0 | N30: =M30*L30 -> 0 | O30: =L30+N30 -> 16.29 | P30: =IFERROR(O30/Q30,"") -> 0.032854002 | Q30: =SUMIFS(O:O,T:T,T30,B:B,B30,A:A,A30,G:G,G30,E:E,E30) -> 495.83 | R30: =V30-SUMIFS(Q:Q,A:A,A30,B:B,B30,G:G,G30,E:E,E30,T:T,"Fixed Price ( Base Price with GST)") -> 2992.764 | S30: =IF(T30="Fixed Price ( Base Price with GST)",O30,P30*R30) -> 98.324276 | T30: Based on Base % | U30: 5599 | V30: =IFERROR(U30*(1-30%),0) -> 3919.3 | W30: 490110 | X30: Core | Y30: =IFERROR(S30,0) -> 98.324276 | Z30: =IF(ISNUMBER(S30),S30,0) -> 98.324276 | AA30: =IFERROR(Z30/(1+M30),Z30) -> 98.324276 | AB30: =IF(ISNUMBER(J30),J30,0) -> 16.29 | AC30: =AA30-AB30 -> 82.034276 | AD30: =IFERROR(AC30/AA30,0) -> 0.83432372 | AE30: =IFERROR(AC30/AB30,0) -> 5.0358671 | AF30: =IF(AD30>=Assumptions!$B$3,"OK","Review") -> OK | AG30: =IFERROR(IF(Assumptions!$B$13="Cost Price",AB30,AA30)*SUMIF(Assumptions!$A$6:$A$10,X30,Assumptions!$B$6:$B$10),0) -> 7.865942 | AH30: =IFERROR(IF(Assumptions!$B$13="Cost Price",AB30,AA30)*SUMIF(Assumptions!$A$6:$A$10,X30,Assumptions!$C$6:$C$10),0) -> 4.9162138 | AI30: =IFERROR(IF(Assumptions!$B$13="Cost Price",AB30,AA30)*SUMIF(Assumptions!$A$6:$A$10,X30,Assumptions!$D$6:$D$10),0) -> 9.8324276 | AJ30: 15.350914 | AK30: =SUM(AG30:AJ30) -> 37.965498 | AL30: 0.33 | AM30: =AC30-AK30 -> 44.068778 | AN30: =IFERROR(AM30/AA30,0) -> 0.44819835 | AO30: =IF(AN30>=Assumptions!$B$3,"OK","Review") -> OK
A31: Corekit AY 2027-2028 | B31: Grade 3 | C31: IDP | D31: T1_G3_IDP_TB B2B (27) | E31: 1:1 | F31: Workbook | G31: 2027-2028 | H31: Term 1 | I31: 4000011859 | J31: 54.55 | L31: =J31+K31 -> 54.55 | M31: 0 | N31: =M31*L31 -> 0 | O31: =L31+N31 -> 54.55 | P31: =IFERROR(O31/Q31,"") -> 0.11001755 | Q31: =SUMIFS(O:O,T:T,T31,B:B,B31,A:A,A31,G:G,G31,E:E,E31) -> 495.83 | R31: =V31-SUMIFS(Q:Q,A:A,A31,B:B,B31,G:G,G31,E:E,E31,T:T,"Fixed Price ( Base Price with GST)") -> 2992.764 | S31: =IF(T31="Fixed Price ( Base Price with GST)",O31,P31*R31) -> 329.25655 | T31: Based on Base % | U31: 5599 | V31: =IFERROR(U31*(1-30%),0) -> 3919.3 | W31: 490110 | X31: Core | Y31: =IFERROR(S31,0) -> 329.25655 | Z31: =IF(ISNUMBER(S31),S31,0) -> 329.25655 | AA31: =IFERROR(Z31/(1+M31),Z31) -> 329.25655 | AB31: =IF(ISNUMBER(J31),J31,0) -> 54.55 | AC31: =AA31-AB31 -> 274.70655 | AD31: =IFERROR(AC31/AA31,0) -> 0.83432372 | AE31: =IFERROR(AC31/AB31,0) -> 5.0358671 | AF31: =IF(AD31>=Assumptions!$B$3,"OK","Review") -> OK | AG31: =IFERROR(IF(Assumptions!$B$13="Cost Price",AB31,AA31)*SUMIF(Assumptions!$A$6:$A$10,X31,Assumptions!$B$6:$B$10),0) -> 26.340524 | AH31: =IFERROR(IF(Assumptions!$B$13="Cost Price",AB31,AA31)*SUMIF(Assumptions!$A$6:$A$10,X31,Assumptions!$C$6:$C$10),0) -> 16.462828 | AI31: =IFERROR(IF(Assumptions!$B$13="Cost Price",AB31,AA31)*SUMIF(Assumptions!$A$6:$A$10,X31,Assumptions!$D$6:$D$10),0) -> 32.925655 | AJ31: 51.405302 | AK31: =SUM(AG31:AJ31) -> 127.13431 | AL31: 0.33 | AM31: =AC31-AK31 -> 147.57224 | AN31: =IFERROR(AM31/AA31,0) -> 0.44819835 | AO31: =IF(AN31>=Assumptions!$B$3,"OK","Review") -> OK
A32: Corekit AY 2027-2028 | B32: Grade 3 | C32: Science | D32: T2_G3_Science Explorers_TB B2B (27) | E32: 1:1 | F32: Book | G32: 2027-2028 | H32: Term 2 | I32: 4000011780 | J32: 32.14 | L32: =J32+K32 -> 32.14 | M32: 0 | N32: =M32*L32 -> 0 | O32: =L32+N32 -> 32.14 | P32: =IFERROR(O32/Q32,"") -> 0.064820604 | Q32: =SUMIFS(O:O,T:T,T32,B:B,B32,A:A,A32,G:G,G32,E:E,E32) -> 495.83 | R32: =V32-SUMIFS(Q:Q,A:A,A32,B:B,B32,G:G,G32,E:E,E32,T:T,"Fixed Price ( Base Price with GST)") -> 2992.764 | S32: =IF(T32="Fixed Price ( Base Price with GST)",O32,P32*R32) -> 193.99277 | T32: Based on Base % | U32: 5599 | V32: =IFERROR(U32*(1-30%),0) -> 3919.3 | W32: 490110 | X32: Core | Y32: =IFERROR(S32,0) -> 193.99277 | Z32: =IF(ISNUMBER(S32),S32,0) -> 193.99277 | AA32: =IFERROR(Z32/(1+M32),Z32) -> 193.99277 | AB32: =IF(ISNUMBER(J32),J32,0) -> 32.14 | AC32: =AA32-AB32 -> 161.85277 | AD32: =IFERROR(AC32/AA32,0) -> 0.83432372 | AE32: =IFERROR(AC32/AB32,0) -> 5.0358671 | AF32: =IF(AD32>=Assumptions!$B$3,"OK","Review") -> OK | AG32: =IFERROR(IF(Assumptions!$B$13="Cost Price",AB32,AA32)*SUMIF(Assumptions!$A$6:$A$10,X32,Assumptions!$B$6:$B$10),0) -> 15.519422 | AH32: =IFERROR(IF(Assumptions!$B$13="Cost Price",AB32,AA32)*SUMIF(Assumptions!$A$6:$A$10,X32,Assumptions!$C$6:$C$10),0) -> 9.6996385 | AI32: =IFERROR(IF(Assumptions!$B$13="Cost Price",AB32,AA32)*SUMIF(Assumptions!$A$6:$A$10,X32,Assumptions!$D$6:$D$10),0) -> 19.399277 | AJ32: 30.287194 | AK32: =SUM(AG32:AJ32) -> 74.905531 | AL32: 0.33 | AM32: =AC32-AK32 -> 86.947239 | AN32: =IFERROR(AM32/AA32,0) -> 0.44819835 | AO32: =IF(AN32>=Assumptions!$B$3,"OK","Review") -> OK
A33: Corekit AY 2027-2028 | B33: Grade 3 | C33: Science | D33: T2_G3_Science Explorers_WB B2B (27) | E33: 1:1 | F33: Book | G33: 2027-2028 | H33: Term 2 | I33: 4000011781 | J33: 17.72 | L33: =J33+K33 -> 17.72 | M33: 0 | N33: =M33*L33 -> 0 | O33: =L33+N33 -> 17.72 | P33: =IFERROR(O33/Q33,"") -> 0.035738055 | Q33: =SUMIFS(O:O,T:T,T33,B:B,B33,A:A,A33,G:G,G33,E:E,E33) -> 495.83 | R33: =V33-SUMIFS(Q:Q,A:A,A33,B:B,B33,G:G,G33,E:E,E33,T:T,"Fixed Price ( Base Price with GST)") -> 2992.764 | S33: =IF(T33="Fixed Price ( Base Price with GST)",O33,P33*R33) -> 106.95557 | T33: Based on Base % | U33: 5599 | V33: =IFERROR(U33*(1-30%),0) -> 3919.3 | W33: 490110 | X33: Core | Y33: =IFERROR(S33,0) -> 106.95557 | Z33: =IF(ISNUMBER(S33),S33,0) -> 106.95557 | AA33: =IFERROR(Z33/(1+M33),Z33) -> 106.95557 | AB33: =IF(ISNUMBER(J33),J33,0) -> 17.72 | AC33: =AA33-AB33 -> 89.235566 | AD33: =IFERROR(AC33/AA33,0) -> 0.83432372 | AE33: =IFERROR(AC33/AB33,0) -> 5.0358671 | AF33: =IF(AD33>=Assumptions!$B$3,"OK","Review") -> OK | AG33: =IFERROR(IF(Assumptions!$B$13="Cost Price",AB33,AA33)*SUMIF(Assumptions!$A$6:$A$10,X33,Assumptions!$B$6:$B$10),0) -> 8.5564452 | AH33: =IFERROR(IF(Assumptions!$B$13="Cost Price",AB33,AA33)*SUMIF(Assumptions!$A$6:$A$10,X33,Assumptions!$C$6:$C$10),0) -> 5.3477783 | AI33: =IFERROR(IF(Assumptions!$B$13="Cost Price",AB33,AA33)*SUMIF(Assumptions!$A$6:$A$10,X33,Assumptions!$D$6:$D$10),0) -> 10.695557 | AJ33: 16.698478 | AK33: =SUM(AG33:AJ33) -> 41.298258 | AL33: 0.33 | AM33: =AC33-AK33 -> 47.937308 | AN33: =IFERROR(AM33/AA33,0) -> 0.44819835 | AO33: =IF(AN33>=Assumptions!$B$3,"OK","Review") -> OK
A34: Corekit AY 2027-2028 | B34: Grade 3 | C34: Maths | D34: T2_G3_Math_Scholars_TB B2B (27) | E34: 1:1 | F34: Book | G34: 2027-2028 | H34: Term 2 | I34: 4000011782 | J34: 43.03 | L34: =J34+K34 -> 43.03 | M34: 0 | N34: =M34*L34 -> 0 | O34: =L34+N34 -> 43.03 | P34: =IFERROR(O34/Q34,"") -> 0.086783777 | Q34: =SUMIFS(O:O,T:T,T34,B:B,B34,A:A,A34,G:G,G34,E:E,E34) -> 495.83 | R34: =V34-SUMIFS(Q:Q,A:A,A34,B:B,B34,G:G,G34,E:E,E34,T:T,"Fixed Price ( Base Price with GST)") -> 2992.764 | S34: =IF(T34="Fixed Price ( Base Price with GST)",O34,P34*R34) -> 259.72336 | T34: Based on Base % | U34: 5599 | V34: =IFERROR(U34*(1-30%),0) -> 3919.3 | W34: 490110 | X34: Core | Y34: =IFERROR(S34,0) -> 259.72336 | Z34: =IF(ISNUMBER(S34),S34,0) -> 259.72336 | AA34: =IFERROR(Z34/(1+M34),Z34) -> 259.72336 | AB34: =IF(ISNUMBER(J34),J34,0) -> 43.03 | AC34: =AA34-AB34 -> 216.69336 | AD34: =IFERROR(AC34/AA34,0) -> 0.83432372 | AE34: =IFERROR(AC34/AB34,0) -> 5.0358671 | AF34: =IF(AD34>=Assumptions!$B$3,"OK","Review") -> OK | AG34: =IFERROR(IF(Assumptions!$B$13="Cost Price",AB34,AA34)*SUMIF(Assumptions!$A$6:$A$10,X34,Assumptions!$B$6:$B$10),0) -> 20.777869 | AH34: =IFERROR(IF(Assumptions!$B$13="Cost Price",AB34,AA34)*SUMIF(Assumptions!$A$6:$A$10,X34,Assumptions!$C$6:$C$10),0) -> 12.986168 | AI34: =IFERROR(IF(Assumptions!$B$13="Cost Price",AB34,AA34)*SUMIF(Assumptions!$A$6:$A$10,X34,Assumptions!$D$6:$D$10),0) -> 25.972336 | AJ34: 40.549407 | AK34: =SUM(AG34:AJ34) -> 100.28578 | AL34: 0.33 | AM34: =AC34-AK34 -> 116.40758 | AN34: =IFERROR(AM34/AA34,0) -> 0.44819835 | AO34: =IF(AN34>=Assumptions!$B$3,"OK","Review") -> OK
... A38: Corekit AY 2027-2028 | B38: Grade 3 | C38: IDP | D38: T2_G3_IDP_TB B2B (27) | E38: 1:1 | F38: Workbook | G38: 2027-2028 | H38: Term 2 | I38: 4000011787 | J38: 37.66 | L38: =J38+K38 -> 37.66 | M38: 0 | N38: =M38*L38 -> 0 | O38: =L38+N38 -> 37.66 | P38: =IFERROR(O38/Q38,"") -> 0.075953452 | Q38: =SUMIFS(O:O,T:T,T38,B:B,B38,A:A,A38,G:G,G38,E:E,E38) -> 495.83 | R38: =V38-SUMIFS(Q:Q,A:A,A38,B:B,B38,G:G,G38,E:E,E38,T:T,"Fixed Price ( Base Price with GST)") -> 2992.764 | S38: =IF(T38="Fixed Price ( Base Price with GST)",O38,P38*R38) -> 227.31076 | T38: Based on Base % | U38: 5599 | V38: =IFERROR(U38*(1-30%),0) -> 3919.3 | W38: 490110 | X38: Core | Y38: =IFERROR(S38,0) -> 227.31076 | Z38: =IF(ISNUMBER(S38),S38,0) -> 227.31076 | AA38: =IFERROR(Z38/(1+M38),Z38) -> 227.31076 | AB38: =IF(ISNUMBER(J38),J38,0) -> 37.66 | AC38: =AA38-AB38 -> 189.65076 | AD38: =IFERROR(AC38/AA38,0) -> 0.83432372 | AE38: =IFERROR(AC38/AB38,0) -> 5.0358671 | AF38: =IF(AD38>=Assumptions!$B$3,"OK","Review") -> OK | AG38: =IFERROR(IF(Assumptions!$B$13="Cost Price",AB38,AA38)*SUMIF(Assumptions!$A$6:$A$10,X38,Assumptions!$B$6:$B$10),0) -> 18.18486 | AH38: =IFERROR(IF(Assumptions!$B$13="Cost Price",AB38,AA38)*SUMIF(Assumptions!$A$6:$A$10,X38,Assumptions!$C$6:$C$10),0) -> 11.365538 | AI38: =IFERROR(IF(Assumptions!$B$13="Cost Price",AB38,AA38)*SUMIF(Assumptions!$A$6:$A$10,X38,Assumptions!$D$6:$D$10),0) -> 22.731076 | AJ38: 35.488977 | AK38: =SUM(AG38:AJ38) -> 87.770451 | AL38: 0.33 | AM38: =AC38-AK38 -> 101.88031 | AN38: =IFERROR(AM38/AA38,0) -> 0.44819835 | AO38: =IF(AN38>=Assumptions!$B$3,"OK","Review") -> OK
A39: Corekit AY 2027-2028 | B39: Grade 3 | C39: Combo Kit | D39: B2B Sci-Pi Combined Kit G3 27-28 | E39: 1:1 | F39: Kit | G39: 2027-2028 | H39: Term 1 | I39: 7000000217 | J39: 286.6 | K39: 10 | L39: =J39+K39 -> 296.6 | M39: 0.18 | N39: =M39*L39 -> 53.388 | O39: =L39+N39 -> 349.988 | P39: =IFERROR(O39/Q39,"") -> 0.75547631 | Q39: =SUMIFS(O:O,T:T,T39,B:B,B39,A:A,A39,G:G,G39,E:E,E39) -> 463.268 | R39: =V39-SUMIFS(Q:Q,A:A,A39,B:B,B39,G:G,G39,E:E,E39,T:T,"Fixed Price ( Base Price with GST)") -> 2992.764 | S39: =IF(T39="Fixed Price ( Base Price with GST)",O39,P39*R39) -> 349.988 | T39: Fixed Price ( Base Price with GST) | U39: 5599 | V39: =IFERROR(U39*(1-30%),0) -> 3919.3 | W39: 49119990 | X39: Core | Y39: =IFERROR(S39,0) -> 349.988 | Z39: =IF(ISNUMBER(S39),S39,0) -> 349.988 | AA39: =IFERROR(Z39/(1+M39),Z39) -> 296.6 | AB39: =IF(ISNUMBER(J39),J39,0) -> 286.6 | AC39: =AA39-AB39 -> 10 | AD39: =IFERROR(AC39/AA39,0) -> 0.033715442 | AE39: =IFERROR(AC39/AB39,0) -> 0.034891835 | AF39: =IF(AD39>=Assumptions!$B$3,"OK","Review") -> Review | AG39: =IFERROR(IF(Assumptions!$B$13="Cost Price",AB39,AA39)*SUMIF(Assumptions!$A$6:$A$10,X39,Assumptions!$B$6:$B$10),0) -> 23.728 | AH39: =IFERROR(IF(Assumptions!$B$13="Cost Price",AB39,AA39)*SUMIF(Assumptions!$A$6:$A$10,X39,Assumptions!$C$6:$C$10),0) -> 14.83 | AI39: =IFERROR(IF(Assumptions!$B$13="Cost Price",AB39,AA39)*SUMIF(Assumptions!$A$6:$A$10,X39,Assumptions!$D$6:$D$10),0) -> 29.66 | AJ39: 29.66 | AK39: =SUM(AG39:AJ39) -> 97.878 | AL39: 0.33 | AM39: =AC39-AK39 -> -87.878 | AN39: =IFERROR(AM39/AA39,0) -> -0.29628456 | AO39: =IF(AN39>=Assumptions!$B$3,"OK","Review") -> Review
A40: Corekit AY 2027-2028 | B40: Grade 3 | C40: Service | D40: Services Charges_25_26 | E40: 1:1 | F40: Services Charges | G40: 2027-2028 | H40: Term 1 | I40: 8400007 | J40: 96 | L40: =J40+K40 -> 96 | M40: 0.18 | N40: =M40*L40 -> 17.28 | O40: =L40+N40 -> 113.28 | P40: =IFERROR(O40/Q40,"") -> 0.24452369 | Q40: =SUMIFS(O:O,T:T,T40,B:B,B40,A:A,A40,G:G,G40,E:E,E40) -> 463.268 | R40: =V40-SUMIFS(Q:Q,A:A,A40,B:B,B40,G:G,G40,E:E,E40,T:T,"Fixed Price ( Base Price with GST)") -> 2992.764 | S40: =IF(T40="Fixed Price ( Base Price with GST)",O40,P40*R40) -> 113.28 | T40: Fixed Price ( Base Price with GST) | U40: 5599 | V40: =IFERROR(U40*(1-30%),0) -> 3919.3 | W40: 999299 | X40: Core | Y40: =IFERROR(S40,0) -> 113.28 | Z40: =IF(ISNUMBER(S40),S40,0) -> 113.28 | AA40: =IFERROR(Z40/(1+M40),Z40) -> 96 | AB40: =IF(ISNUMBER(J40),J40,0) -> 96 | AC40: =AA40-AB40 -> 0 | AD40: =IFERROR(AC40/AA40,0) -> 0 | AE40: =IFERROR(AC40/AB40,0) -> 0 | AF40: =IF(AD40>=Assumptions!$B$3,"OK","Review") -> Review | AG40: =IFERROR(IF(Assumptions!$B$13="Cost Price",AB40,AA40)*SUMIF(Assumptions!$A$6:$A$10,X40,Assumptions!$B$6:$B$10),0) -> 7.68 | AH40: =IFERROR(IF(Assumptions!$B$13="Cost Price",AB40,AA40)*SUMIF(Assumptions!$A$6:$A$10,X40,Assumptions!$C$6:$C$10),0) -> 4.8 | AI40: =IFERROR(IF(Assumptions!$B$13="Cost Price",AB40,AA40)*SUMIF(Assumptions!$A$6:$A$10,X40,Assumptions!$D$6:$D$10),0) -> 9.6 | AJ40: 9.6 | AK40: =SUM(AG40:AJ40) -> 31.68 | AL40: 0.33 | AM40: =AC40-AK40 -> -31.68 | AN40: =IFERROR(AM40/AA40,0) -> -0.33 | AO40: =IF(AN40>=Assumptions!$B$3,"OK","Review") -> Review
A41: Corekit AY 2027-2028 | B41: Grade 4 | C41: Science | D41: T1_G4_Science Explorers_TB B2B (27) | E41: 1:1 | F41: Book | G41: 2027-2028 | H41: Term 1 | I41: 4000011788 | J41: 34.78 | L41: =J41+K41 -> 34.78 | M41: 0 | N41: =M41*L41 -> 0 | O41: =L41+N41 -> 34.78 | P41: =IFERROR(O41/Q41,"") -> 0.063885674 | Q41: =SUMIFS(O:O,T:T,T41,B:B,B41,A:A,A41,G:G,G41,E:E,E41) -> 544.41 | R41: =V41-SUMIFS(Q:Q,A:A,A41,B:B,B41,G:G,G41,E:E,E41,T:T,"Fixed Price ( Base Price with GST)") -> 3165.752 | S41: =IF(T41="Fixed Price ( Base Price with GST)",O41,P41*R41) -> 202.2462 | T41: Based on Base % | U41: 5599 | V41: =IFERROR(U41*(1-30%),0) -> 3919.3 | W41: 490110 | X41: Core | Y41: =IFERROR(S41,0) -> 202.2462 | Z41: =IF(ISNUMBER(S41),S41,0) -> 202.2462 | AA41: =IFERROR(Z41/(1+M41),Z41) -> 202.2462 | AB41: =IF(ISNUMBER(J41),J41,0) -> 34.78 | AC41: =AA41-AB41 -> 167.4662 | AD41: =IFERROR(AC41/AA41,0) -> 0.82803138 | AE41: =IFERROR(AC41/AB41,0) -> 4.8150144 | AF41: =IF(AD41>=Assumptions!$B$3,"OK","Review") -> OK | AG41: =IFERROR(IF(Assumptions!$B$13="Cost Price",AB41,AA41)*SUMIF(Assumptions!$A$6:$A$10,X41,Assumptions!$B$6:$B$10),0) -> 16.179696 | AH41: =IFERROR(IF(Assumptions!$B$13="Cost Price",AB41,AA41)*SUMIF(Assumptions!$A$6:$A$10,X41,Assumptions!$C$6:$C$10),0) -> 10.11231 | AI41: =IFERROR(IF(Assumptions!$B$13="Cost Price",AB41,AA41)*SUMIF(Assumptions!$A$6:$A$10,X41,Assumptions!$D$6:$D$10),0) -> 20.22462 | AJ41: 30.955497 | AK41: =SUM(AG41:AJ41) -> 77.472123 | AL41: 0.33 | AM41: =AC41-AK41 -> 89.994078 | AN41: =IFERROR(AM41/AA41,0) -> 0.4449729 | AO41: =IF(AN41>=Assumptions!$B$3,"OK","Review") -> OK
A42: Corekit AY 2027-2028 | B42: Grade 4 | C42: Science | D42: T1_G4_Science Explorers_WB B2B (27) | E42: 1:1 | F42: Book | G42: 2027-2028 | H42: Term 1 | I42: 4000011789 | J42: 19.34 | L42: =J42+K42 -> 19.34 | M42: 0 | N42: =M42*L42 -> 0 | O42: =L42+N42 -> 19.34 | P42: =IFERROR(O42/Q42,"") -> 0.035524696 | Q42: =SUMIFS(O:O,T:T,T42,B:B,B42,A:A,A42,G:G,G42,E:E,E42) -> 544.41 | R42: =V42-SUMIFS(Q:Q,A:A,A42,B:B,B42,G:G,G42,E:E,E42,T:T,"Fixed Price ( Base Price with GST)") -> 3165.752 | S42: =IF(T42="Fixed Price ( Base Price with GST)",O42,P42*R42) -> 112.46238 | T42: Based on Base % | U42: 5599 | V42: =IFERROR(U42*(1-30%),0) -> 3919.3 | W42: 490110 | X42: Core | Y42: =IFERROR(S42,0) -> 112.46238 | Z42: =IF(ISNUMBER(S42),S42,0) -> 112.46238 | AA42: =IFERROR(Z42/(1+M42),Z42) -> 112.46238 | AB42: =IF(ISNUMBER(J42),J42,0) -> 19.34 | AC42: =AA42-AB42 -> 93.122379 | AD42: =IFERROR(AC42/AA42,0) -> 0.82803138 | AE42: =IFERROR(AC42/AB42,0) -> 4.8150144 | AF42: =IF(AD42>=Assumptions!$B$3,"OK","Review") -> OK | AG42: =IFERROR(IF(Assumptions!$B$13="Cost Price",AB42,AA42)*SUMIF(Assumptions!$A$6:$A$10,X42,Assumptions!$B$6:$B$10),0) -> 8.9969903 | AH42: =IFERROR(IF(Assumptions!$B$13="Cost Price",AB42,AA42)*SUMIF(Assumptions!$A$6:$A$10,X42,Assumptions!$C$6:$C$10),0) -> 5.6231189 | AI42: =IFERROR(IF(Assumptions!$B$13="Cost Price",AB42,AA42)*SUMIF(Assumptions!$A$6:$A$10,X42,Assumptions!$D$6:$D$10),0) -> 11.246238 | AJ42: 17.213321 | AK42: =SUM(AG42:AJ42) -> 43.079668 | AL42: 0.33 | AM42: =AC42-AK42 -> 50.042711 | AN42: =IFERROR(AM42/AA42,0) -> 0.4449729 | AO42: =IF(AN42>=Assumptions!$B$3,"OK","Review") -> OK
A43: Corekit AY 2027-2028 | B43: Grade 4 | C43: Maths | D43: T1_G4_Math_Scholars_TB B2B (27) | E43: 1:1 | F43: Book | G43: 2027-2028 | H43: Term 1 | I43: 4000011790 | J43: 45.67 | L43: =J43+K43 -> 45.67 | M43: 0 | N43: =M43*L43 -> 0 | O43: =L43+N43 -> 45.67 | P43: =IFERROR(O43/Q43,"") -> 0.083888981 | Q43: =SUMIFS(O:O,T:T,T43,B:B,B43,A:A,A43,G:G,G43,E:E,E43) -> 544.41 | R43: =V43-SUMIFS(Q:Q,A:A,A43,B:B,B43,G:G,G43,E:E,E43,T:T,"Fixed Price ( Base Price with GST)") -> 3165.752 | S43: =IF(T43="Fixed Price ( Base Price with GST)",O43,P43*R43) -> 265.57171 | T43: Based on Base % | U43: 5599 | V43: =IFERROR(U43*(1-30%),0) -> 3919.3 | W43: 490110 | X43: Core | Y43: =IFERROR(S43,0) -> 265.57171 | Z43: =IF(ISNUMBER(S43),S43,0) -> 265.57171 | AA43: =IFERROR(Z43/(1+M43),Z43) -> 265.57171 | AB43: =IF(ISNUMBER(J43),J43,0) -> 45.67 | AC43: =AA43-AB43 -> 219.90171 | AD43: =IFERROR(AC43/AA43,0) -> 0.82803138 | AE43: =IFERROR(AC43/AB43,0) -> 4.8150144 | AF43: =IF(AD43>=Assumptions!$B$3,"OK","Review") -> OK | AG43: =IFERROR(IF(Assumptions!$B$13="Cost Price",AB43,AA43)*SUMIF(Assumptions!$A$6:$A$10,X43,Assumptions!$B$6:$B$10),0) -> 21.245737 | AH43: =IFERROR(IF(Assumptions!$B$13="Cost Price",AB43,AA43)*SUMIF(Assumptions!$A$6:$A$10,X43,Assumptions!$C$6:$C$10),0) -> 13.278585 | AI43: =IFERROR(IF(Assumptions!$B$13="Cost Price",AB43,AA43)*SUMIF(Assumptions!$A$6:$A$10,X43,Assumptions!$D$6:$D$10),0) -> 26.557171 | AJ43: 40.648003 | AK43: =SUM(AG43:AJ43) -> 101.7295 | AL43: 0.33 | AM43: =AC43-AK43 -> 118.17221 | AN43: =IFERROR(AM43/AA43,0) -> 0.4449729 | AO43: =IF(AN43>=Assumptions!$B$3,"OK","Review") -> OK
A44: Corekit AY 2027-2028 | B44: Grade 4 | C44: Maths | D44: T1_G4_Math_Scholars_WB B2B (27) | E44: 1:1 | F44: Book | G44: 2027-2028 | H44: Term 1 | I44: 4000011791 | J44: 20.8 | L44: =J44+K44 -> 20.8 | M44: 0 | N44: =M44*L44 -> 0 | O44: =L44+N44 -> 20.8 | P44: =IFERROR(O44/Q44,"") -> 0.038206499 | Q44: =SUMIFS(O:O,T:T,T44,B:B,B44,A:A,A44,G:G,G44,E:E,E44) -> 544.41 | R44: =V44-SUMIFS(Q:Q,A:A,A44,B:B,B44,G:G,G44,E:E,E44,T:T,"Fixed Price ( Base Price with GST)") -> 3165.752 | S44: =IF(T44="Fixed Price ( Base Price with GST)",O44,P44*R44) -> 120.9523 | T44: Based on Base % | U44: 5599 | V44: =IFERROR(U44*(1-30%),0) -> 3919.3 | W44: 490110 | X44: Core | Y44: =IFERROR(S44,0) -> 120.9523 | Z44: =IF(ISNUMBER(S44),S44,0) -> 120.9523 | AA44: =IFERROR(Z44/(1+M44),Z44) -> 120.9523 | AB44: =IF(ISNUMBER(J44),J44,0) -> 20.8 | AC44: =AA44-AB44 -> 100.1523 | AD44: =IFERROR(AC44/AA44,0) -> 0.82803138 | AE44: =IFERROR(AC44/AB44,0) -> 4.8150144 | AF44: =IF(AD44>=Assumptions!$B$3,"OK","Review") -> OK | AG44: =IFERROR(IF(Assumptions!$B$13="Cost Price",AB44,AA44)*SUMIF(Assumptions!$A$6:$A$10,X44,Assumptions!$B$6:$B$10),0) -> 9.676184 | AH44: =IFERROR(IF(Assumptions!$B$13="Cost Price",AB44,AA44)*SUMIF(Assumptions!$A$6:$A$10,X44,Assumptions!$C$6:$C$10),0) -> 6.047615 | AI44: =IFERROR(IF(Assumptions!$B$13="Cost Price",AB44,AA44)*SUMIF(Assumptions!$A$6:$A$10,X44,Assumptions!$D$6:$D$10),0) -> 12.09523 | AJ44: 18.512776 | AK44: =SUM(AG44:AJ44) -> 46.331805 | AL44: 0.33 | AM44: =AC44-AK44 -> 53.820495 | AN44: =IFERROR(AM44/AA44,0) -> 0.4449729 | AO44: =IF(AN44>=Assumptions!$B$3,"OK","Review") -> OK
A45: Corekit AY 2027-2028 | B45: Grade 4 | C45: English | D45: Annual_G4_English_Comp B2B (27) | E45: 1:1 | F45: Book | G45: 2027-2028 | H45: Term 1 | I45: 4000011793 | J45: 30.65 | L45: =J45+K45 -> 30.65 | M45: 0 | N45: =M45*L45 -> 0 | O45: =L45+N45 -> 30.65 | P45: =IFERROR(O45/Q45,"") -> 0.05629948 | Q45: =SUMIFS(O:O,T:T,T45,B:B,B45,A:A,A45,G:G,G45,E:E,E45) -> 544.41 | R45: =V45-SUMIFS(Q:Q,A:A,A45,B:B,B45,G:G,G45,E:E,E45,T:T,"Fixed Price ( Base Price with GST)") -> 3165.752 | S45: =IF(T45="Fixed Price ( Base Price with GST)",O45,P45*R45) -> 178.23019 | T45: Based on Base % | U45: 5599 | V45: =IFERROR(U45*(1-30%),0) -> 3919.3 | W45: 490110 | X45: Core | Y45: =IFERROR(S45,0) -> 178.23019 | Z45: =IF(ISNUMBER(S45),S45,0) -> 178.23019 | AA45: =IFERROR(Z45/(1+M45),Z45) -> 178.23019 | AB45: =IF(ISNUMBER(J45),J45,0) -> 30.65 | AC45: =AA45-AB45 -> 147.58019 | AD45: =IFERROR(AC45/AA45,0) -> 0.82803138 | AE45: =IFERROR(AC45/AB45,0) -> 4.8150144 | AF45: =IF(AD45>=Assumptions!$B$3,"OK","Review") -> OK | AG45: =IFERROR(IF(Assumptions!$B$13="Cost Price",AB45,AA45)*SUMIF(Assumptions!$A$6:$A$10,X45,Assumptions!$B$6:$B$10),0) -> 14.258415 | AH45: =IFERROR(IF(Assumptions!$B$13="Cost Price",AB45,AA45)*SUMIF(Assumptions!$A$6:$A$10,X45,Assumptions!$C$6:$C$10),0) -> 8.9115096 | AI45: =IFERROR(IF(Assumptions!$B$13="Cost Price",AB45,AA45)*SUMIF(Assumptions!$A$6:$A$10,X45,Assumptions!$D$6:$D$10),0) -> 17.823019 | AJ45: 27.279643 | AK45: =SUM(AG45:AJ45) -> 68.272587 | AL45: 0.33 | AM45: =AC45-AK45 -> 79.307605 | AN45: =IFERROR(AM45/AA45,0) -> 0.4449729 | AO45: =IF(AN45>=Assumptions!$B$3,"OK","Review") -> OK
A46: Corekit AY 2027-2028 | B46: Grade 4 | C46: English | D46: T1_G4_English_RC B2B (27) | E46: 1:1 | F46: Workbook | G46: 2027-2028 | H46: Term 1 | I46: 4000011792 | J46: 60.27 | L46: =J46+K46 -> 60.27 | M46: 0 | N46: =M46*L46 -> 0 | O46: =L46+N46 -> 60.27 | P46: =IFERROR(O46/Q46,"") -> 0.110707 | Q46: =SUMIFS(O:O,T:T,T46,B:B,B46,A:A,A46,G:G,G46,E:E,E46) -> 544.41 | R46: =V46-SUMIFS(Q:Q,A:A,A46,B:B,B46,G:G,G46,E:E,E46,T:T,"Fixed Price ( Base Price with GST)") -> 3165.752 | S46: =IF(T46="Fixed Price ( Base Price with GST)",O46,P46*R46) -> 350.47092 | T46: Based on Base % | U46: 5599 | V46: =IFERROR(U46*(1-30%),0) -> 3919.3 | W46: 490110 | X46: Core | Y46: =IFERROR(S46,0) -> 350.47092 | Z46: =IF(ISNUMBER(S46),S46,0) -> 350.47092 | AA46: =IFERROR(Z46/(1+M46),Z46) -> 350.47092 | AB46: =IF(ISNUMBER(J46),J46,0) -> 60.27 | AC46: =AA46-AB46 -> 290.20092 | AD46: =IFERROR(AC46/AA46,0) -> 0.82803138 | AE46: =IFERROR(AC46/AB46,0) -> 4.8150144 | AF46: =IF(AD46>=Assumptions!$B$3,"OK","Review") -> OK | AG46: =IFERROR(IF(Assumptions!$B$13="Cost Price",AB46,AA46)*SUMIF(Assumptions!$A$6:$A$10,X46,Assumptions!$B$6:$B$10),0) -> 28.037674 | AH46: =IFERROR(IF(Assumptions!$B$13="Cost Price",AB46,AA46)*SUMIF(Assumptions!$A$6:$A$10,X46,Assumptions!$C$6:$C$10),0) -> 17.523546 | AI46: =IFERROR(IF(Assumptions!$B$13="Cost Price",AB46,AA46)*SUMIF(Assumptions!$A$6:$A$10,X46,Assumptions!$D$6:$D$10),0) -> 35.047092 | AJ46: 53.642547 | AK46: =SUM(AG46:AJ46) -> 134.25086 | AL46: 0.33 | AM46: =AC46-AK46 -> 155.95006 | AN46: =IFERROR(AM46/AA46,0) -> 0.4449729 | AO46: =IF(AN46>=Assumptions!$B$3,"OK","Review") -> OK
A47: Corekit AY 2027-2028 | B47: Grade 4 | C47: English | D47: T1_G4_English_WB B2B (27) | E47: 1:1 | F47: Workbook | G47: 2027-2028 | H47: Term 1 | I47: 4000011795 | J47: 17.84 | L47: =J47+K47 -> 17.84 | M47: 0 | N47: =M47*L47 -> 0 | O47: =L47+N47 -> 17.84 | P47: =IFERROR(O47/Q47,"") -> 0.03276942 | Q47: =SUMIFS(O:O,T:T,T47,B:B,B47,A:A,A47,G:G,G47,E:E,E47) -> 544.41 | R47: =V47-SUMIFS(Q:Q,A:A,A47,B:B,B47,G:G,G47,E:E,E47,T:T,"Fixed Price ( Base Price with GST)") -> 3165.752 | S47: =IF(T47="Fixed Price ( Base Price with GST)",O47,P47*R47) -> 103.73986 | T47: Based on Base % | U47: 5599 | V47: =IFERROR(U47*(1-30%),0) -> 3919.3 | W47: 490110 | X47: Core | Y47: =IFERROR(S47,0) -> 103.73986 | Z47: =IF(ISNUMBER(S47),S47,0) -> 103.73986 | AA47: =IFERROR(Z47/(1+M47),Z47) -> 103.73986 | AB47: =IF(ISNUMBER(J47),J47,0) -> 17.84 | AC47: =AA47-AB47 -> 85.899857 | AD47: =IFERROR(AC47/AA47,0) -> 0.82803138 | AE47: =IFERROR(AC47/AB47,0) -> 4.8150144 | AF47: =IF(AD47>=Assumptions!$B$3,"OK","Review") -> OK | AG47: =IFERROR(IF(Assumptions!$B$13="Cost Price",AB47,AA47)*SUMIF(Assumptions!$A$6:$A$10,X47,Assumptions!$B$6:$B$10),0) -> 8.2991886 | AH47: =IFERROR(IF(Assumptions!$B$13="Cost Price",AB47,AA47)*SUMIF(Assumptions!$A$6:$A$10,X47,Assumptions!$C$6:$C$10),0) -> 5.1869929 | AI47: =IFERROR(IF(Assumptions!$B$13="Cost Price",AB47,AA47)*SUMIF(Assumptions!$A$6:$A$10,X47,Assumptions!$D$6:$D$10),0) -> 10.373986 | AJ47: 15.878265 | AK47: =SUM(AG47:AJ47) -> 39.738432 | AL47: 0.33 | AM47: =AC47-AK47 -> 46.161425 | AN47: =IFERROR(AM47/AA47,0) -> 0.4449729 | AO47: =IF(AN47>=Assumptions!$B$3,"OK","Review") -> OK
A48: Corekit AY 2027-2028 | B48: Grade 4 | C48: IDP | D48: T1_G4_IDP_TB B2B (27) | E48: 1:1 | F48: Workbook | G48: 2027-2028 | H48: Term 1 | I48: 4000011796 | J48: 57.61 | L48: =J48+K48 -> 57.61 | M48: 0 | N48: =M48*L48 -> 0 | O48: =L48+N48 -> 57.61 | P48: =IFERROR(O48/Q48,"") -> 0.10582098 | Q48: =SUMIFS(O:O,T:T,T48,B:B,B48,A:A,A48,G:G,G48,E:E,E48) -> 544.41 | R48: =V48-SUMIFS(Q:Q,A:A,A48,B:B,B48,G:G,G48,E:E,E48,T:T,"Fixed Price ( Base Price with GST)") -> 3165.752 | S48: =IF(T48="Fixed Price ( Base Price with GST)",O48,P48*R48) -> 335.00298 | T48: Based on Base % | U48: 5599 | V48: =IFERROR(U48*(1-30%),0) -> 3919.3 | W48: 490110 | X48: Core | Y48: =IFERROR(S48,0) -> 335.00298 | Z48: =IF(ISNUMBER(S48),S48,0) -> 335.00298 | AA48: =IFERROR(Z48/(1+M48),Z48) -> 335.00298 | AB48: =IF(ISNUMBER(J48),J48,0) -> 57.61 | AC48: =AA48-AB48 -> 277.39298 | AD48: =IFERROR(AC48/AA48,0) -> 0.82803138 | AE48: =IFERROR(AC48/AB48,0) -> 4.8150144 | AF48: =IF(AD48>=Assumptions!$B$3,"OK","Review") -> OK | AG48: =IFERROR(IF(Assumptions!$B$13="Cost Price",AB48,AA48)*SUMIF(Assumptions!$A$6:$A$10,X48,Assumptions!$B$6:$B$10),0) -> 26.800238 | AH48: =IFERROR(IF(Assumptions!$B$13="Cost Price",AB48,AA48)*SUMIF(Assumptions!$A$6:$A$10,X48,Assumptions!$C$6:$C$10),0) -> 16.750149 | AI48: =IFERROR(IF(Assumptions!$B$13="Cost Price",AB48,AA48)*SUMIF(Assumptions!$A$6:$A$10,X48,Assumptions!$D$6:$D$10),0) -> 33.500298 | AJ48: 51.275048 | AK48: =SUM(AG48:AJ48) -> 128.32573 | AL48: 0.33 | AM48: =AC48-AK48 -> 149.06725 | AN48: =IFERROR(AM48/AA48,0) -> 0.4449729 | AO48: =IF(AN48>=Assumptions!$B$3,"OK","Review") -> OK
A49: Corekit AY 2027-2028 | B49: Grade 4 | C49: Science | D49: T2_G4_Science Explorers_TB B2B (27) | E49: 1:1 | F49: Book | G49: 2027-2028 | H49: Term 2 | I49: 4000011797 | J49: 39.18 | L49: =J49+K49 -> 39.18 | M49: 0 | N49: =M49*L49 -> 0 | O49: =L49+N49 -> 39.18 | P49: =IFERROR(O49/Q49,"") -> 0.071967818 | Q49: =SUMIFS(O:O,T:T,T49,B:B,B49,A:A,A49,G:G,G49,E:E,E49) -> 544.41 | R49: =V49-SUMIFS(Q:Q,A:A,A49,B:B,B49,G:G,G49,E:E,E49,T:T,"Fixed Price ( Base Price with GST)") -> 3165.752 | S49: =IF(T49="Fixed Price ( Base Price with GST)",O49,P49*R49) -> 227.83226 | T49: Based on Base % | U49: 5599 | V49: =IFERROR(U49*(1-30%),0) -> 3919.3 | W49: 490110 | X49: Core | Y49: =IFERROR(S49,0) -> 227.83226 | Z49: =IF(ISNUMBER(S49),S49,0) -> 227.83226 | AA49: =IFERROR(Z49/(1+M49),Z49) -> 227.83226 | AB49: =IF(ISNUMBER(J49),J49,0) -> 39.18 | AC49: =AA49-AB49 -> 188.65226 | AD49: =IFERROR(AC49/AA49,0) -> 0.82803138 | AE49: =IFERROR(AC49/AB49,0) -> 4.8150144 | AF49: =IF(AD49>=Assumptions!$B$3,"OK","Review") -> OK | AG49: =IFERROR(IF(Assumptions!$B$13="Cost Price",AB49,AA49)*SUMIF(Assumptions!$A$6:$A$10,X49,Assumptions!$B$6:$B$10),0) -> 18.226581 | AH49: =IFERROR(IF(Assumptions!$B$13="Cost Price",AB49,AA49)*SUMIF(Assumptions!$A$6:$A$10,X49,Assumptions!$C$6:$C$10),0) -> 11.391613 | AI49: =IFERROR(IF(Assumptions!$B$13="Cost Price",AB49,AA49)*SUMIF(Assumptions!$A$6:$A$10,X49,Assumptions!$D$6:$D$10),0) -> 22.783226 | AJ49: 34.871661 | AK49: =SUM(AG49:AJ49) -> 87.273082 | AL49: 0.33 | AM49: =AC49-AK49 -> 101.37918 | AN49: =IFERROR(AM49/AA49,0) -> 0.4449729 | AO49: =IF(AN49>=Assumptions!$B$3,"OK","Review") -> OK
A50: Corekit AY 2027-2028 | B50: Grade 4 | C50: Science | D50: T2_G4_Science Explorers_WB B2B (27) | E50: 1:1 | F50: Book | G50: 2027-2028 | H50: Term 2 | I50: 4000011798 | J50: 19.34 | L50: =J50+K50 -> 19.34 | M50: 0 | N50: =M50*L50 -> 0 | O50: =L50+N50 -> 19.34 | P50: =IFERROR(O50/Q50,"") -> 0.035524696 | Q50: =SUMIFS(O:O,T:T,T50,B:B,B50,A:A,A50,G:G,G50,E:E,E50) -> 544.41 | R50: =V50-SUMIFS(Q:Q,A:A,A50,B:B,B50,G:G,G50,E:E,E50,T:T,"Fixed Price ( Base Price with GST)") -> 3165.752 | S50: =IF(T50="Fixed Price ( Base Price with GST)",O50,P50*R50) -> 112.46238 | T50: Based on Base % | U50: 5599 | V50: =IFERROR(U50*(1-30%),0) -> 3919.3 | W50: 490110 | X50: Core | Y50: =IFERROR(S50,0) -> 112.46238 | Z50: =IF(ISNUMBER(S50),S50,0) -> 112.46238 | AA50: =IFERROR(Z50/(1+M50),Z50) -> 112.46238 | AB50: =IF(ISNUMBER(J50),J50,0) -> 19.34 | AC50: =AA50-AB50 -> 93.122379 | AD50: =IFERROR(AC50/AA50,0) -> 0.82803138 | AE50: =IFERROR(AC50/AB50,0) -> 4.8150144 | AF50: =IF(AD50>=Assumptions!$B$3,"OK","Review") -> OK | AG50: =IFERROR(IF(Assumptions!$B$13="Cost Price",AB50,AA50)*SUMIF(Assumptions!$A$6:$A$10,X50,Assumptions!$B$6:$B$10),0) -> 8.9969903 | AH50: =IFERROR(IF(Assumptions!$B$13="Cost Price",AB50,AA50)*SUMIF(Assumptions!$A$6:$A$10,X50,Assumptions!$C$6:$C$10),0) -> 5.6231189 | AI50: =IFERROR(IF(Assumptions!$B$13="Cost Price",AB50,AA50)*SUMIF(Assumptions!$A$6:$A$10,X50,Assumptions!$D$6:$D$10),0) -> 11.246238 | AJ50: 17.213321 | AK50: =SUM(AG50:AJ50) -> 43.079668 | AL50: 0.33 | AM50: =AC50-AK50 -> 50.042711 | AN50: =IFERROR(AM50/AA50,0) -> 0.4449729 | AO50: =IF(AN50>=Assumptions!$B$3,"OK","Review") -> OK
A51: Corekit AY 2027-2028 | B51: Grade 4 | C51: Maths | D51: T2_G4_Math_Scholars_TB B2B (27) | E51: 1:1 | F51: Book | G51: 2027-2028 | H51: Term 2 | I51: 4000011799 | J51: 50.05 | L51: =J51+K51 -> 50.05 | M51: 0 | N51: =M51*L51 -> 0 | O51: =L51+N51 -> 50.05 | P51: =IFERROR(O51/Q51,"") -> 0.091934388 | Q51: =SUMIFS(O:O,T:T,T51,B:B,B51,A:A,A51,G:G,G51,E:E,E51) -> 544.41 | R51: =V51-SUMIFS(Q:Q,A:A,A51,B:B,B51,G:G,G51,E:E,E51,T:T,"Fixed Price ( Base Price with GST)") -> 3165.752 | S51: =IF(T51="Fixed Price ( Base Price with GST)",O51,P51*R51) -> 291.04147 | T51: Based on Base % | U51: 5599 | V51: =IFERROR(U51*(1-30%),0) -> 3919.3 | W51: 490110 | X51: Core | Y51: =IFERROR(S51,0) -> 291.04147 | Z51: =IF(ISNUMBER(S51),S51,0) -> 291.04147 | AA51: =IFERROR(Z51/(1+M51),Z51) -> 291.04147 | AB51: =IF(ISNUMBER(J51),J51,0) -> 50.05 | AC51: =AA51-AB51 -> 240.99147 | AD51: =IFERROR(AC51/AA51,0) -> 0.82803138 | AE51: =IFERROR(AC51/AB51,0) -> 4.8150144 | AF51: =IF(AD51>=Assumptions!$B$3,"OK","Review") -> OK | AG51: =IFERROR(IF(Assumptions!$B$13="Cost Price",AB51,AA51)*SUMIF(Assumptions!$A$6:$A$10,X51,Assumptions!$B$6:$B$10),0) -> 23.283318 | AH51: =IFERROR(IF(Assumptions!$B$13="Cost Price",AB51,AA51)*SUMIF(Assumptions!$A$6:$A$10,X51,Assumptions!$C$6:$C$10),0) -> 14.552074 | AI51: =IFERROR(IF(Assumptions!$B$13="Cost Price",AB51,AA51)*SUMIF(Assumptions!$A$6:$A$10,X51,Assumptions!$D$6:$D$10),0) -> 29.104147 | AJ51: 44.546366 | AK51: =SUM(AG51:AJ51) -> 111.4859 | AL51: 0.33 | AM51: =AC51-AK51 -> 129.50557 | AN51: =IFERROR(AM51/AA51,0) -> 0.4449729 | AO51: =IF(AN51>=Assumptions!$B$3,"OK","Review") -> OK
... A55: Corekit AY 2027-2028 | B55: Grade 4 | C55: IDP | D55: T2_G4_IDP_TB B2B (27) | E55: 1:1 | F55: Workbook | G55: 2027-2028 | H55: Term 2 | I55: 4000011803 | J55: 44.98 | L55: =J55+K55 -> 44.98 | M55: 0 | N55: =M55*L55 -> 0 | O55: =L55+N55 -> 44.98 | P55: =IFERROR(O55/Q55,"") -> 0.082621554 | Q55: =SUMIFS(O:O,T:T,T55,B:B,B55,A:A,A55,G:G,G55,E:E,E55) -> 544.41 | R55: =V55-SUMIFS(Q:Q,A:A,A55,B:B,B55,G:G,G55,E:E,E55,T:T,"Fixed Price ( Base Price with GST)") -> 3165.752 | S55: =IF(T55="Fixed Price ( Base Price with GST)",O55,P55*R55) -> 261.55935 | T55: Based on Base % | U55: 5599 | V55: =IFERROR(U55*(1-30%),0) -> 3919.3 | W55: 490110 | X55: Core | Y55: =IFERROR(S55,0) -> 261.55935 | Z55: =IF(ISNUMBER(S55),S55,0) -> 261.55935 | AA55: =IFERROR(Z55/(1+M55),Z55) -> 261.55935 | AB55: =IF(ISNUMBER(J55),J55,0) -> 44.98 | AC55: =AA55-AB55 -> 216.57935 | AD55: =IFERROR(AC55/AA55,0) -> 0.82803138 | AE55: =IFERROR(AC55/AB55,0) -> 4.8150144 | AF55: =IF(AD55>=Assumptions!$B$3,"OK","Review") -> OK | AG55: =IFERROR(IF(Assumptions!$B$13="Cost Price",AB55,AA55)*SUMIF(Assumptions!$A$6:$A$10,X55,Assumptions!$B$6:$B$10),0) -> 20.924748 | AH55: =IFERROR(IF(Assumptions!$B$13="Cost Price",AB55,AA55)*SUMIF(Assumptions!$A$6:$A$10,X55,Assumptions!$C$6:$C$10),0) -> 13.077967 | AI55: =IFERROR(IF(Assumptions!$B$13="Cost Price",AB55,AA55)*SUMIF(Assumptions!$A$6:$A$10,X55,Assumptions!$D$6:$D$10),0) -> 26.155935 | AJ55: 40.033877 | AK55: =SUM(AG55:AJ55) -> 100.19253 | AL55: 0.33 | AM55: =AC55-AK55 -> 116.38682 | AN55: =IFERROR(AM55/AA55,0) -> 0.4449729 | AO55: =IF(AN55>=Assumptions!$B$3,"OK","Review") -> OK
A56: Corekit AY 2027-2028 | B56: Grade 4 | C56: Combo Kit | D56: B2B Sci-Pi Combined Kit G4 27-28 | E56: 1:1 | F56: Kit | G56: 2027-2028 | H56: Term 1 | I56: 7000000225 | J56: 213.3 | K56: 10 | L56: =J56+K56 -> 223.3 | M56: 0.18 | N56: =M56*L56 -> 40.194 | O56: =L56+N56 -> 263.494 | P56: =IFERROR(O56/Q56,"") -> 0.69934231 | Q56: =SUMIFS(O:O,T:T,T56,B:B,B56,A:A,A56,G:G,G56,E:E,E56) -> 376.774 | R56: =V56-SUMIFS(Q:Q,A:A,A56,B:B,B56,G:G,G56,E:E,E56,T:T,"Fixed Price ( Base Price with GST)") -> 3165.752 | S56: =IF(T56="Fixed Price ( Base Price with GST)",O56,P56*R56) -> 263.494 | T56: Fixed Price ( Base Price with GST) | U56: 5599 | V56: =IFERROR(U56*(1-30%),0) -> 3919.3 | W56: 49119990 | X56: Core | Y56: =IFERROR(S56,0) -> 263.494 | Z56: =IF(ISNUMBER(S56),S56,0) -> 263.494 | AA56: =IFERROR(Z56/(1+M56),Z56) -> 223.3 | AB56: =IF(ISNUMBER(J56),J56,0) -> 213.3 | AC56: =AA56-AB56 -> 10 | AD56: =IFERROR(AC56/AA56,0) -> 0.044782803 | AE56: =IFERROR(AC56/AB56,0) -> 0.046882325 | AF56: =IF(AD56>=Assumptions!$B$3,"OK","Review") -> Review | AG56: =IFERROR(IF(Assumptions!$B$13="Cost Price",AB56,AA56)*SUMIF(Assumptions!$A$6:$A$10,X56,Assumptions!$B$6:$B$10),0) -> 17.864 | AH56: =IFERROR(IF(Assumptions!$B$13="Cost Price",AB56,AA56)*SUMIF(Assumptions!$A$6:$A$10,X56,Assumptions!$C$6:$C$10),0) -> 11.165 | AI56: =IFERROR(IF(Assumptions!$B$13="Cost Price",AB56,AA56)*SUMIF(Assumptions!$A$6:$A$10,X56,Assumptions!$D$6:$D$10),0) -> 22.33 | AJ56: 22.33 | AK56: =SUM(AG56:AJ56) -> 73.689 | AL56: 0.33 | AM56: =AC56-AK56 -> -63.689 | AN56: =IFERROR(AM56/AA56,0) -> -0.2852172 | AO56: =IF(AN56>=Assumptions!$B$3,"OK","Review") -> Review
A57: Corekit AY 2027-2028 | B57: Grade 4 | C57: Service | D57: Services Charges_25_26 | E57: 1:1 | F57: Services Charges | G57: 2027-2028 | H57: Term 1 | I57: 8400007 | J57: 96 | L57: =J57+K57 -> 96 | M57: 0.18 | N57: =M57*L57 -> 17.28 | O57: =L57+N57 -> 113.28 | P57: =IFERROR(O57/Q57,"") -> 0.30065769 | Q57: =SUMIFS(O:O,T:T,T57,B:B,B57,A:A,A57,G:G,G57,E:E,E57) -> 376.774 | R57: =V57-SUMIFS(Q:Q,A:A,A57,B:B,B57,G:G,G57,E:E,E57,T:T,"Fixed Price ( Base Price with GST)") -> 3165.752 | S57: =IF(T57="Fixed Price ( Base Price with GST)",O57,P57*R57) -> 113.28 | T57: Fixed Price ( Base Price with GST) | U57: 5599 | V57: =IFERROR(U57*(1-30%),0) -> 3919.3 | W57: 999299 | X57: Core | Y57: =IFERROR(S57,0) -> 113.28 | Z57: =IF(ISNUMBER(S57),S57,0) -> 113.28 | AA57: =IFERROR(Z57/(1+M57),Z57) -> 96 | AB57: =IF(ISNUMBER(J57),J57,0) -> 96 | AC57: =AA57-AB57 -> 0 | AD57: =IFERROR(AC57/AA57,0) -> 0 | AE57: =IFERROR(AC57/AB57,0) -> 0 | AF57: =IF(AD57>=Assumptions!$B$3,"OK","Review") -> Review | AG57: =IFERROR(IF(Assumptions!$B$13="Cost Price",AB57,AA57)*SUMIF(Assumptions!$A$6:$A$10,X57,Assumptions!$B$6:$B$10),0) -> 7.68 | AH57: =IFERROR(IF(Assumptions!$B$13="Cost Price",AB57,AA57)*SUMIF(Assumptions!$A$6:$A$10,X57,Assumptions!$C$6:$C$10),0) -> 4.8 | AI57: =IFERROR(IF(Assumptions!$B$13="Cost Price",AB57,AA57)*SUMIF(Assumptions!$A$6:$A$10,X57,Assumptions!$D$6:$D$10),0) -> 9.6 | AJ57: 9.6 | AK57: =SUM(AG57:AJ57) -> 31.68 | AL57: 0.33 | AM57: =AC57-AK57 -> -31.68 | AN57: =IFERROR(AM57/AA57,0) -> -0.33 | AO57: =IF(AN57>=Assumptions!$B$3,"OK","Review") -> Review
A58: Corekit AY 2027-2028 | B58: Grade 5 | C58: Science | D58: T1_G5_Science Explorers_TB B2B (27) | E58: 1:1 | F58: Book | G58: 2027-2028 | H58: Term 1 | I58: 4000011804 | J58: 39.65 | L58: =J58+K58 -> 39.65 | M58: 0 | N58: =M58*L58 -> 0 | O58: =L58+N58 -> 39.65 | P58: =IFERROR(O58/Q58,"") -> 0.071625991 | Q58: =SUMIFS(O:O,T:T,T58,B:B,B58,A:A,A58,G:G,G58,E:E,E58) -> 553.57 | R58: =V58-SUMIFS(Q:Q,A:A,A58,B:B,B58,G:G,G58,E:E,E58,T:T,"Fixed Price ( Base Price with GST)") -> 3056.72 | S58: =IF(T58="Fixed Price ( Base Price with GST)",O58,P58*R58) -> 218.9406 | T58: Based on Base % | U58: 5599 | V58: =IFERROR(U58*(1-30%),0) -> 3919.3 | W58: 490110 | X58: Core | Y58: =IFERROR(S58,0) -> 218.9406 | Z58: =IF(ISNUMBER(S58),S58,0) -> 218.9406 | AA58: =IFERROR(Z58/(1+M58),Z58) -> 218.9406 | AB58: =IF(ISNUMBER(J58),J58,0) -> 39.65 | AC58: =AA58-AB58 -> 179.2906 | AD58: =IFERROR(AC58/AA58,0) -> 0.81890065 | AE58: =IFERROR(AC58/AB58,0) -> 4.521831 | AF58: =IF(AD58>=Assumptions!$B$3,"OK","Review") -> OK | AG58: =IFERROR(IF(Assumptions!$B$13="Cost Price",AB58,AA58)*SUMIF(Assumptions!$A$6:$A$10,X58,Assumptions!$B$6:$B$10),0) -> 17.515248 | AH58: =IFERROR(IF(Assumptions!$B$13="Cost Price",AB58,AA58)*SUMIF(Assumptions!$A$6:$A$10,X58,Assumptions!$C$6:$C$10),0) -> 10.94703 | AI58: =IFERROR(IF(Assumptions!$B$13="Cost Price",AB58,AA58)*SUMIF(Assumptions!$A$6:$A$10,X58,Assumptions!$D$6:$D$10),0) -> 21.89406 | AJ58: 33.925078 | AK58: =SUM(AG58:AJ58) -> 84.281416 | AL58: 0.33 | AM58: =AC58-AK58 -> 95.009184 | AN58: =IFERROR(AM58/AA58,0) -> 0.43394959 | AO58: =IF(AN58>=Assumptions!$B$3,"OK","Review") -> OK
A59: Corekit AY 2027-2028 | B59: Grade 5 | C59: Science | D59: T1_G5_Science Explorers_WB B2B (27) | E59: 1:1 | F59: Book | G59: 2027-2028 | H59: Term 1 | I59: 4000011806 | J59: 19.51 | L59: =J59+K59 -> 19.51 | M59: 0 | N59: =M59*L59 -> 0 | O59: =L59+N59 -> 19.51 | P59: =IFERROR(O59/Q59,"") -> 0.035243962 | Q59: =SUMIFS(O:O,T:T,T59,B:B,B59,A:A,A59,G:G,G59,E:E,E59) -> 553.57 | R59: =V59-SUMIFS(Q:Q,A:A,A59,B:B,B59,G:G,G59,E:E,E59,T:T,"Fixed Price ( Base Price with GST)") -> 3056.72 | S59: =IF(T59="Fixed Price ( Base Price with GST)",O59,P59*R59) -> 107.73092 | T59: Based on Base % | U59: 5599 | V59: =IFERROR(U59*(1-30%),0) -> 3919.3 | W59: 490110 | X59: Core | Y59: =IFERROR(S59,0) -> 107.73092 | Z59: =IF(ISNUMBER(S59),S59,0) -> 107.73092 | AA59: =IFERROR(Z59/(1+M59),Z59) -> 107.73092 | AB59: =IF(ISNUMBER(J59),J59,0) -> 19.51 | AC59: =AA59-AB59 -> 88.220923 | AD59: =IFERROR(AC59/AA59,0) -> 0.81890065 | AE59: =IFERROR(AC59/AB59,0) -> 4.521831 | AF59: =IF(AD59>=Assumptions!$B$3,"OK","Review") -> OK | AG59: =IFERROR(IF(Assumptions!$B$13="Cost Price",AB59,AA59)*SUMIF(Assumptions!$A$6:$A$10,X59,Assumptions!$B$6:$B$10),0) -> 8.6184739 | AH59: =IFERROR(IF(Assumptions!$B$13="Cost Price",AB59,AA59)*SUMIF(Assumptions!$A$6:$A$10,X59,Assumptions!$C$6:$C$10),0) -> 5.3865462 | AI59: =IFERROR(IF(Assumptions!$B$13="Cost Price",AB59,AA59)*SUMIF(Assumptions!$A$6:$A$10,X59,Assumptions!$D$6:$D$10),0) -> 10.773092 | AJ59: 16.693021 | AK59: =SUM(AG59:AJ59) -> 41.471133 | AL59: 0.33 | AM59: =AC59-AK59 -> 46.74979 | AN59: =IFERROR(AM59/AA59,0) -> 0.43394959 | AO59: =IF(AN59>=Assumptions!$B$3,"OK","Review") -> OK
A60: Corekit AY 2027-2028 | B60: Grade 5 | C60: Maths | D60: T1_G5_Math_Scholars_TB B2B (27) | E60: 1:1 | F60: Book | G60: 2027-2028 | H60: Term 1 | I60: 4000011807 | J60: 48.5 | L60: =J60+K60 -> 48.5 | M60: 0 | N60: =M60*L60 -> 0 | O60: =L60+N60 -> 48.5 | P60: =IFERROR(O60/Q60,"") -> 0.087613129 | Q60: =SUMIFS(O:O,T:T,T60,B:B,B60,A:A,A60,G:G,G60,E:E,E60) -> 553.57 | R60: =V60-SUMIFS(Q:Q,A:A,A60,B:B,B60,G:G,G60,E:E,E60,T:T,"Fixed Price ( Base Price with GST)") -> 3056.72 | S60: =IF(T60="Fixed Price ( Base Price with GST)",O60,P60*R60) -> 267.8088 | T60: Based on Base % | U60: 5599 | V60: =IFERROR(U60*(1-30%),0) -> 3919.3 | W60: 490110 | X60: Core | Y60: =IFERROR(S60,0) -> 267.8088 | Z60: =IF(ISNUMBER(S60),S60,0) -> 267.8088 | AA60: =IFERROR(Z60/(1+M60),Z60) -> 267.8088 | AB60: =IF(ISNUMBER(J60),J60,0) -> 48.5 | AC60: =AA60-AB60 -> 219.3088 | AD60: =IFERROR(AC60/AA60,0) -> 0.81890065 | AE60: =IFERROR(AC60/AB60,0) -> 4.521831 | AF60: =IF(AD60>=Assumptions!$B$3,"OK","Review") -> OK | AG60: =IFERROR(IF(Assumptions!$B$13="Cost Price",AB60,AA60)*SUMIF(Assumptions!$A$6:$A$10,X60,Assumptions!$B$6:$B$10),0) -> 21.424704 | AH60: =IFERROR(IF(Assumptions!$B$13="Cost Price",AB60,AA60)*SUMIF(Assumptions!$A$6:$A$10,X60,Assumptions!$C$6:$C$10),0) -> 13.39044 | AI60: =IFERROR(IF(Assumptions!$B$13="Cost Price",AB60,AA60)*SUMIF(Assumptions!$A$6:$A$10,X60,Assumptions!$D$6:$D$10),0) -> 26.78088 | AJ60: 41.497258 | AK60: =SUM(AG60:AJ60) -> 103.09328 | AL60: 0.33 | AM60: =AC60-AK60 -> 116.21552 | AN60: =IFERROR(AM60/AA60,0) -> 0.43394959 | AO60: =IF(AN60>=Assumptions!$B$3,"OK","Review") -> OK
A61: Corekit AY 2027-2028 | B61: Grade 5 | C61: Maths | D61: T1_G5_Math_Scholars_WB B2B (27) | E61: 1:1 | F61: Book | G61: 2027-2028 | H61: Term 1 | I61: 4000011808 | J61: 23.91 | L61: =J61+K61 -> 23.91 | M61: 0 | N61: =M61*L61 -> 0 | O61: =L61+N61 -> 23.91 | P61: =IFERROR(O61/Q61,"") -> 0.04319237 | Q61: =SUMIFS(O:O,T:T,T61,B:B,B61,A:A,A61,G:G,G61,E:E,E61) -> 553.57 | R61: =V61-SUMIFS(Q:Q,A:A,A61,B:B,B61,G:G,G61,E:E,E61,T:T,"Fixed Price ( Base Price with GST)") -> 3056.72 | S61: =IF(T61="Fixed Price ( Base Price with GST)",O61,P61*R61) -> 132.02698 | T61: Based on Base % | U61: 5599 | V61: =IFERROR(U61*(1-30%),0) -> 3919.3 | W61: 490110 | X61: Core | Y61: =IFERROR(S61,0) -> 132.02698 | Z61: =IF(ISNUMBER(S61),S61,0) -> 132.02698 | AA61: =IFERROR(Z61/(1+M61),Z61) -> 132.02698 | AB61: =IF(ISNUMBER(J61),J61,0) -> 23.91 | AC61: =AA61-AB61 -> 108.11698 | AD61: =IFERROR(AC61/AA61,0) -> 0.81890065 | AE61: =IFERROR(AC61/AB61,0) -> 4.521831 | AF61: =IF(AD61>=Assumptions!$B$3,"OK","Review") -> OK | AG61: =IFERROR(IF(Assumptions!$B$13="Cost Price",AB61,AA61)*SUMIF(Assumptions!$A$6:$A$10,X61,Assumptions!$B$6:$B$10),0) -> 10.562158 | AH61: =IFERROR(IF(Assumptions!$B$13="Cost Price",AB61,AA61)*SUMIF(Assumptions!$A$6:$A$10,X61,Assumptions!$C$6:$C$10),0) -> 6.601349 | AI61: =IFERROR(IF(Assumptions!$B$13="Cost Price",AB61,AA61)*SUMIF(Assumptions!$A$6:$A$10,X61,Assumptions!$D$6:$D$10),0) -> 13.202698 | AJ61: 20.45772 | AK61: =SUM(AG61:AJ61) -> 50.823926 | AL61: 0.33 | AM61: =AC61-AK61 -> 57.293054 | AN61: =IFERROR(AM61/AA61,0) -> 0.43394959 | AO61: =IF(AN61>=Assumptions!$B$3,"OK","Review") -> OK
A62: Corekit AY 2027-2028 | B62: Grade 5 | C62: English | D62: Annual_G5_English_Comp B2B (27) | E62: 1:1 | F62: Book | G62: 2027-2028 | H62: Term 1 | I62: 4000011810 | J62: 40.62 | L62: =J62+K62 -> 40.62 | M62: 0 | N62: =M62*L62 -> 0 | O62: =L62+N62 -> 40.62 | P62: =IFERROR(O62/Q62,"") -> 0.073378254 | Q62: =SUMIFS(O:O,T:T,T62,B:B,B62,A:A,A62,G:G,G62,E:E,E62) -> 553.57 | R62: =V62-SUMIFS(Q:Q,A:A,A62,B:B,B62,G:G,G62,E:E,E62,T:T,"Fixed Price ( Base Price with GST)") -> 3056.72 | S62: =IF(T62="Fixed Price ( Base Price with GST)",O62,P62*R62) -> 224.29678 | T62: Based on Base % | U62: 5599 | V62: =IFERROR(U62*(1-30%),0) -> 3919.3 | W62: 490110 | X62: Core | Y62: =IFERROR(S62,0) -> 224.29678 | Z62: =IF(ISNUMBER(S62),S62,0) -> 224.29678 | AA62: =IFERROR(Z62/(1+M62),Z62) -> 224.29678 | AB62: =IF(ISNUMBER(J62),J62,0) -> 40.62 | AC62: =AA62-AB62 -> 183.67678 | AD62: =IFERROR(AC62/AA62,0) -> 0.81890065 | AE62: =IFERROR(AC62/AB62,0) -> 4.521831 | AF62: =IF(AD62>=Assumptions!$B$3,"OK","Review") -> OK | AG62: =IFERROR(IF(Assumptions!$B$13="Cost Price",AB62,AA62)*SUMIF(Assumptions!$A$6:$A$10,X62,Assumptions!$B$6:$B$10),0) -> 17.943742 | AH62: =IFERROR(IF(Assumptions!$B$13="Cost Price",AB62,AA62)*SUMIF(Assumptions!$A$6:$A$10,X62,Assumptions!$C$6:$C$10),0) -> 11.214839 | AI62: =IFERROR(IF(Assumptions!$B$13="Cost Price",AB62,AA62)*SUMIF(Assumptions!$A$6:$A$10,X62,Assumptions!$D$6:$D$10),0) -> 22.429678 | AJ62: 34.755023 | AK62: =SUM(AG62:AJ62) -> 86.343281 | AL62: 0.33 | AM62: =AC62-AK62 -> 97.333495 | AN62: =IFERROR(AM62/AA62,0) -> 0.43394959 | AO62: =IF(AN62>=Assumptions!$B$3,"OK","Review") -> OK
A63: Corekit AY 2027-2028 | B63: Grade 5 | C63: English | D63: T1_G5_English_RC B2B (27) | E63: 1:1 | F63: Workbook | G63: 2027-2028 | H63: Term 1 | I63: 4000011809 | J63: 55.07 | L63: =J63+K63 -> 55.07 | M63: 0 | N63: =M63*L63 -> 0 | O63: =L63+N63 -> 55.07 | P63: =IFERROR(O63/Q63,"") -> 0.099481547 | Q63: =SUMIFS(O:O,T:T,T63,B:B,B63,A:A,A63,G:G,G63,E:E,E63) -> 553.57 | R63: =V63-SUMIFS(Q:Q,A:A,A63,B:B,B63,G:G,G63,E:E,E63,T:T,"Fixed Price ( Base Price with GST)") -> 3056.72 | S63: =IF(T63="Fixed Price ( Base Price with GST)",O63,P63*R63) -> 304.08723 | T63: Based on Base % | U63: 5599 | V63: =IFERROR(U63*(1-30%),0) -> 3919.3 | W63: 490110 | X63: Core | Y63: =IFERROR(S63,0) -> 304.08723 | Z63: =IF(ISNUMBER(S63),S63,0) -> 304.08723 | AA63: =IFERROR(Z63/(1+M63),Z63) -> 304.08723 | AB63: =IF(ISNUMBER(J63),J63,0) -> 55.07 | AC63: =AA63-AB63 -> 249.01723 | AD63: =IFERROR(AC63/AA63,0) -> 0.81890065 | AE63: =IFERROR(AC63/AB63,0) -> 4.521831 | AF63: =IF(AD63>=Assumptions!$B$3,"OK","Review") -> OK | AG63: =IFERROR(IF(Assumptions!$B$13="Cost Price",AB63,AA63)*SUMIF(Assumptions!$A$6:$A$10,X63,Assumptions!$B$6:$B$10),0) -> 24.326979 | AH63: =IFERROR(IF(Assumptions!$B$13="Cost Price",AB63,AA63)*SUMIF(Assumptions!$A$6:$A$10,X63,Assumptions!$C$6:$C$10),0) -> 15.204362 | AI63: =IFERROR(IF(Assumptions!$B$13="Cost Price",AB63,AA63)*SUMIF(Assumptions!$A$6:$A$10,X63,Assumptions!$D$6:$D$10),0) -> 30.408723 | AJ63: 47.118639 | AK63: =SUM(AG63:AJ63) -> 117.0587 | AL63: 0.33 | AM63: =AC63-AK63 -> 131.95853 | AN63: =IFERROR(AM63/AA63,0) -> 0.43394959 | AO63: =IF(AN63>=Assumptions!$B$3,"OK","Review") -> OK
A64: Corekit AY 2027-2028 | B64: Grade 5 | C64: English | D64: T1_G5_English_WB B2B (27) | E64: 1:1 | F64: Workbook | G64: 2027-2028 | H64: Term 1 | I64: 4000011811 | J64: 19.51 | L64: =J64+K64 -> 19.51 | M64: 0 | N64: =M64*L64 -> 0 | O64: =L64+N64 -> 19.51 | P64: =IFERROR(O64/Q64,"") -> 0.035243962 | Q64: =SUMIFS(O:O,T:T,T64,B:B,B64,A:A,A64,G:G,G64,E:E,E64) -> 553.57 | R64: =V64-SUMIFS(Q:Q,A:A,A64,B:B,B64,G:G,G64,E:E,E64,T:T,"Fixed Price ( Base Price with GST)") -> 3056.72 | S64: =IF(T64="Fixed Price ( Base Price with GST)",O64,P64*R64) -> 107.73092 | T64: Based on Base % | U64: 5599 | V64: =IFERROR(U64*(1-30%),0) -> 3919.3 | W64: 490110 | X64: Core | Y64: =IFERROR(S64,0) -> 107.73092 | Z64: =IF(ISNUMBER(S64),S64,0) -> 107.73092 | AA64: =IFERROR(Z64/(1+M64),Z64) -> 107.73092 | AB64: =IF(ISNUMBER(J64),J64,0) -> 19.51 | AC64: =AA64-AB64 -> 88.220923 | AD64: =IFERROR(AC64/AA64,0) -> 0.81890065 | AE64: =IFERROR(AC64/AB64,0) -> 4.521831 | AF64: =IF(AD64>=Assumptions!$B$3,"OK","Review") -> OK | AG64: =IFERROR(IF(Assumptions!$B$13="Cost Price",AB64,AA64)*SUMIF(Assumptions!$A$6:$A$10,X64,Assumptions!$B$6:$B$10),0) -> 8.6184739 | AH64: =IFERROR(IF(Assumptions!$B$13="Cost Price",AB64,AA64)*SUMIF(Assumptions!$A$6:$A$10,X64,Assumptions!$C$6:$C$10),0) -> 5.3865462 | AI64: =IFERROR(IF(Assumptions!$B$13="Cost Price",AB64,AA64)*SUMIF(Assumptions!$A$6:$A$10,X64,Assumptions!$D$6:$D$10),0) -> 10.773092 | AJ64: 16.693021 | AK64: =SUM(AG64:AJ64) -> 41.471133 | AL64: 0.33 | AM64: =AC64-AK64 -> 46.74979 | AN64: =IFERROR(AM64/AA64,0) -> 0.43394959 | AO64: =IF(AN64>=Assumptions!$B$3,"OK","Review") -> OK
A65: Corekit AY 2027-2028 | B65: Grade 5 | C65: IDP | D65: T1_G5_IDP_TB B2B (27) | E65: 1:1 | F65: Workbook | G65: 2027-2028 | H65: Term 1 | I65: 4000011812 | J65: 39.94 | L65: =J65+K65 -> 39.94 | M65: 0 | N65: =M65*L65 -> 0 | O65: =L65+N65 -> 39.94 | P65: =IFERROR(O65/Q65,"") -> 0.072149864 | Q65: =SUMIFS(O:O,T:T,T65,B:B,B65,A:A,A65,G:G,G65,E:E,E65) -> 553.57 | R65: =V65-SUMIFS(Q:Q,A:A,A65,B:B,B65,G:G,G65,E:E,E65,T:T,"Fixed Price ( Base Price with GST)") -> 3056.72 | S65: =IF(T65="Fixed Price ( Base Price with GST)",O65,P65*R65) -> 220.54193 | T65: Based on Base % | U65: 5599 | V65: =IFERROR(U65*(1-30%),0) -> 3919.3 | W65: 490110 | X65: Core | Y65: =IFERROR(S65,0) -> 220.54193 | Z65: =IF(ISNUMBER(S65),S65,0) -> 220.54193 | AA65: =IFERROR(Z65/(1+M65),Z65) -> 220.54193 | AB65: =IF(ISNUMBER(J65),J65,0) -> 39.94 | AC65: =AA65-AB65 -> 180.60193 | AD65: =IFERROR(AC65/AA65,0) -> 0.81890065 | AE65: =IFERROR(AC65/AB65,0) -> 4.521831 | AF65: =IF(AD65>=Assumptions!$B$3,"OK","Review") -> OK | AG65: =IFERROR(IF(Assumptions!$B$13="Cost Price",AB65,AA65)*SUMIF(Assumptions!$A$6:$A$10,X65,Assumptions!$B$6:$B$10),0) -> 17.643354 | AH65: =IFERROR(IF(Assumptions!$B$13="Cost Price",AB65,AA65)*SUMIF(Assumptions!$A$6:$A$10,X65,Assumptions!$C$6:$C$10),0) -> 11.027097 | AI65: =IFERROR(IF(Assumptions!$B$13="Cost Price",AB65,AA65)*SUMIF(Assumptions!$A$6:$A$10,X65,Assumptions!$D$6:$D$10),0) -> 22.054193 | AJ65: 34.173206 | AK65: =SUM(AG65:AJ65) -> 84.89785 | AL65: 0.33 | AM65: =AC65-AK65 -> 95.704081 | AN65: =IFERROR(AM65/AA65,0) -> 0.43394959 | AO65: =IF(AN65>=Assumptions!$B$3,"OK","Review") -> OK
A66: Corekit AY 2027-2028 | B66: Grade 5 | C66: Science | D66: T2_G5_Science Explorers_TB B2B (27) | E66: 1:1 | F66: Book | G66: 2027-2028 | H66: Term 2 | I66: 4000011813 | J66: 41.81 | L66: =J66+K66 -> 41.81 | M66: 0 | N66: =M66*L66 -> 0 | O66: =L66+N66 -> 41.81 | P66: =IFERROR(O66/Q66,"") -> 0.075527937 | Q66: =SUMIFS(O:O,T:T,T66,B:B,B66,A:A,A66,G:G,G66,E:E,E66) -> 553.57 | R66: =V66-SUMIFS(Q:Q,A:A,A66,B:B,B66,G:G,G66,E:E,E66,T:T,"Fixed Price ( Base Price with GST)") -> 3056.72 | S66: =IF(T66="Fixed Price ( Base Price with GST)",O66,P66*R66) -> 230.86776 | T66: Based on Base % | U66: 5599 | V66: =IFERROR(U66*(1-30%),0) -> 3919.3 | W66: 490110 | X66: Core | Y66: =IFERROR(S66,0) -> 230.86776 | Z66: =IF(ISNUMBER(S66),S66,0) -> 230.86776 | AA66: =IFERROR(Z66/(1+M66),Z66) -> 230.86776 | AB66: =IF(ISNUMBER(J66),J66,0) -> 41.81 | AC66: =AA66-AB66 -> 189.05776 | AD66: =IFERROR(AC66/AA66,0) -> 0.81890065 | AE66: =IFERROR(AC66/AB66,0) -> 4.521831 | AF66: =IF(AD66>=Assumptions!$B$3,"OK","Review") -> OK | AG66: =IFERROR(IF(Assumptions!$B$13="Cost Price",AB66,AA66)*SUMIF(Assumptions!$A$6:$A$10,X66,Assumptions!$B$6:$B$10),0) -> 18.46942 | AH66: =IFERROR(IF(Assumptions!$B$13="Cost Price",AB66,AA66)*SUMIF(Assumptions!$A$6:$A$10,X66,Assumptions!$C$6:$C$10),0) -> 11.543388 | AI66: =IFERROR(IF(Assumptions!$B$13="Cost Price",AB66,AA66)*SUMIF(Assumptions!$A$6:$A$10,X66,Assumptions!$D$6:$D$10),0) -> 23.086776 | AJ66: 23.086776 | AK66: =SUM(AG66:AJ66) -> 76.186359 | AL66: 0.33 | AM66: =AC66-AK66 -> 112.8714 | AN66: =IFERROR(AM66/AA66,0) -> 0.48890065 | AO66: =IF(AN66>=Assumptions!$B$3,"OK","Review") -> OK
A67: Corekit AY 2027-2028 | B67: Grade 5 | C67: Science | D67: T2_G5_Science Explorers_WB B2B (27) | E67: 1:1 | F67: Book | G67: 2027-2028 | H67: Term 2 | I67: 4000011814 | J67: 17.95 | L67: =J67+K67 -> 17.95 | M67: 0 | N67: =M67*L67 -> 0 | O67: =L67+N67 -> 17.95 | P67: =IFERROR(O67/Q67,"") -> 0.03242589 | Q67: =SUMIFS(O:O,T:T,T67,B:B,B67,A:A,A67,G:G,G67,E:E,E67) -> 553.57 | R67: =V67-SUMIFS(Q:Q,A:A,A67,B:B,B67,G:G,G67,E:E,E67,T:T,"Fixed Price ( Base Price with GST)") -> 3056.72 | S67: =IF(T67="Fixed Price ( Base Price with GST)",O67,P67*R67) -> 99.116867 | T67: Based on Base % | U67: 5599 | V67: =IFERROR(U67*(1-30%),0) -> 3919.3 | W67: 490110 | X67: Core | Y67: =IFERROR(S67,0) -> 99.116867 | Z67: =IF(ISNUMBER(S67),S67,0) -> 99.116867 | AA67: =IFERROR(Z67/(1+M67),Z67) -> 99.116867 | AB67: =IF(ISNUMBER(J67),J67,0) -> 17.95 | AC67: =AA67-AB67 -> 81.166867 | AD67: =IFERROR(AC67/AA67,0) -> 0.81890065 | AE67: =IFERROR(AC67/AB67,0) -> 4.521831 | AF67: =IF(AD67>=Assumptions!$B$3,"OK","Review") -> OK | AG67: =IFERROR(IF(Assumptions!$B$13="Cost Price",AB67,AA67)*SUMIF(Assumptions!$A$6:$A$10,X67,Assumptions!$B$6:$B$10),0) -> 7.9293494 | AH67: =IFERROR(IF(Assumptions!$B$13="Cost Price",AB67,AA67)*SUMIF(Assumptions!$A$6:$A$10,X67,Assumptions!$C$6:$C$10),0) -> 4.9558433 | AI67: =IFERROR(IF(Assumptions!$B$13="Cost Price",AB67,AA67)*SUMIF(Assumptions!$A$6:$A$10,X67,Assumptions!$D$6:$D$10),0) -> 9.9116867 | AJ67: 15.358263 | AK67: =SUM(AG67:AJ67) -> 38.155143 | AL67: 0.33 | AM67: =AC67-AK67 -> 43.011724 | AN67: =IFERROR(AM67/AA67,0) -> 0.43394959 | AO67: =IF(AN67>=Assumptions!$B$3,"OK","Review") -> OK
A68: Corekit AY 2027-2028 | B68: Grade 5 | C68: Maths | D68: T2_G5_Math_Scholars_TB B2B (27) | E68: 1:1 | F68: Book | G68: 2027-2028 | H68: Term 2 | I68: 4000011815 | J68: 46.24 | L68: =J68+K68 -> 46.24 | M68: 0 | N68: =M68*L68 -> 0 | O68: =L68+N68 -> 46.24 | P68: =IFERROR(O68/Q68,"") -> 0.083530538 | Q68: =SUMIFS(O:O,T:T,T68,B:B,B68,A:A,A68,G:G,G68,E:E,E68) -> 553.57 | R68: =V68-SUMIFS(Q:Q,A:A,A68,B:B,B68,G:G,G68,E:E,E68,T:T,"Fixed Price ( Base Price with GST)") -> 3056.72 | S68: =IF(T68="Fixed Price ( Base Price with GST)",O68,P68*R68) -> 255.32947 | T68: Based on Base % | U68: 5599 | V68: =IFERROR(U68*(1-30%),0) -> 3919.3 | W68: 490110 | X68: Core | Y68: =IFERROR(S68,0) -> 255.32947 | Z68: =IF(ISNUMBER(S68),S68,0) -> 255.32947 | AA68: =IFERROR(Z68/(1+M68),Z68) -> 255.32947 | AB68: =IF(ISNUMBER(J68),J68,0) -> 46.24 | AC68: =AA68-AB68 -> 209.08947 | AD68: =IFERROR(AC68/AA68,0) -> 0.81890065 | AE68: =IFERROR(AC68/AB68,0) -> 4.521831 | AF68: =IF(AD68>=Assumptions!$B$3,"OK","Review") -> OK | AG68: =IFERROR(IF(Assumptions!$B$13="Cost Price",AB68,AA68)*SUMIF(Assumptions!$A$6:$A$10,X68,Assumptions!$B$6:$B$10),0) -> 20.426357 | AH68: =IFERROR(IF(Assumptions!$B$13="Cost Price",AB68,AA68)*SUMIF(Assumptions!$A$6:$A$10,X68,Assumptions!$C$6:$C$10),0) -> 12.766473 | AI68: =IFERROR(IF(Assumptions!$B$13="Cost Price",AB68,AA68)*SUMIF(Assumptions!$A$6:$A$10,X68,Assumptions!$D$6:$D$10),0) -> 25.532947 | AJ68: 39.563571 | AK68: =SUM(AG68:AJ68) -> 98.289348 | AL68: 0.33 | AM68: =AC68-AK68 -> 110.80012 | AN68: =IFERROR(AM68/AA68,0) -> 0.43394959 | AO68: =IF(AN68>=Assumptions!$B$3,"OK","Review") -> OK
... A72: Corekit AY 2027-2028 | B72: Grade 5 | C72: IDP | D72: T2_G5_IDP_TB B2B (27) | E72: 1:1 | F72: Book | G72: 2027-2028 | H72: Term 2 | I72: 4000011740 | J72: 43.29 | L72: =J72+K72 -> 43.29 | M72: 0 | N72: =M72*L72 -> 0 | O72: =L72+N72 -> 43.29 | P72: =IFERROR(O72/Q72,"") -> 0.078201492 | Q72: =SUMIFS(O:O,T:T,T72,B:B,B72,A:A,A72,G:G,G72,E:E,E72) -> 553.57 | R72: =V72-SUMIFS(Q:Q,A:A,A72,B:B,B72,G:G,G72,E:E,E72,T:T,"Fixed Price ( Base Price with GST)") -> 3056.72 | S72: =IF(T72="Fixed Price ( Base Price with GST)",O72,P72*R72) -> 239.04007 | T72: Based on Base % | U72: 5599 | V72: =IFERROR(U72*(1-30%),0) -> 3919.3 | W72: 490110 | X72: Core | Y72: =IFERROR(S72,0) -> 239.04007 | Z72: =IF(ISNUMBER(S72),S72,0) -> 239.04007 | AA72: =IFERROR(Z72/(1+M72),Z72) -> 239.04007 | AB72: =IF(ISNUMBER(J72),J72,0) -> 43.29 | AC72: =AA72-AB72 -> 195.75007 | AD72: =IFERROR(AC72/AA72,0) -> 0.81890065 | AE72: =IFERROR(AC72/AB72,0) -> 4.521831 | AF72: =IF(AD72>=Assumptions!$B$3,"OK","Review") -> OK | AG72: =IFERROR(IF(Assumptions!$B$13="Cost Price",AB72,AA72)*SUMIF(Assumptions!$A$6:$A$10,X72,Assumptions!$B$6:$B$10),0) -> 19.123205 | AH72: =IFERROR(IF(Assumptions!$B$13="Cost Price",AB72,AA72)*SUMIF(Assumptions!$A$6:$A$10,X72,Assumptions!$C$6:$C$10),0) -> 11.952003 | AI72: =IFERROR(IF(Assumptions!$B$13="Cost Price",AB72,AA72)*SUMIF(Assumptions!$A$6:$A$10,X72,Assumptions!$D$6:$D$10),0) -> 23.904007 | AJ72: 37.039511 | AK72: =SUM(AG72:AJ72) -> 92.018726 | AL72: 0.33 | AM72: =AC72-AK72 -> 103.73134 | AN72: =IFERROR(AM72/AA72,0) -> 0.43394959 | AO72: =IF(AN72>=Assumptions!$B$3,"OK","Review") -> OK
A73: Corekit AY 2027-2028 | B73: Grade 5 | C73: Combo Kit | D73: B2B Sci-Pi Combined Kit G5 27-28 | E73: 1:1 | F73: Kit | G73: 2027-2028 | H73: Term 1 | I73: 7000000226 | J73: 259.5 | K73: 10 | L73: =J73+K73 -> 269.5 | M73: 0.18 | N73: =M73*L73 -> 48.51 | O73: =L73+N73 -> 318.01 | P73: =IFERROR(O73/Q73,"") -> 0.7373461 | Q73: =SUMIFS(O:O,T:T,T73,B:B,B73,A:A,A73,G:G,G73,E:E,E73) -> 431.29 | R73: =V73-SUMIFS(Q:Q,A:A,A73,B:B,B73,G:G,G73,E:E,E73,T:T,"Fixed Price ( Base Price with GST)") -> 3056.72 | S73: =IF(T73="Fixed Price ( Base Price with GST)",O73,P73*R73) -> 318.01 | T73: Fixed Price ( Base Price with GST) | U73: 5599 | V73: =IFERROR(U73*(1-30%),0) -> 3919.3 | W73: 49119990 | X73: Core | Y73: =IFERROR(S73,0) -> 318.01 | Z73: =IF(ISNUMBER(S73),S73,0) -> 318.01 | AA73: =IFERROR(Z73/(1+M73),Z73) -> 269.5 | AB73: =IF(ISNUMBER(J73),J73,0) -> 259.5 | AC73: =AA73-AB73 -> 10 | AD73: =IFERROR(AC73/AA73,0) -> 0.037105751 | AE73: =IFERROR(AC73/AB73,0) -> 0.038535645 | AF73: =IF(AD73>=Assumptions!$B$3,"OK","Review") -> Review | AG73: =IFERROR(IF(Assumptions!$B$13="Cost Price",AB73,AA73)*SUMIF(Assumptions!$A$6:$A$10,X73,Assumptions!$B$6:$B$10),0) -> 21.56 | AH73: =IFERROR(IF(Assumptions!$B$13="Cost Price",AB73,AA73)*SUMIF(Assumptions!$A$6:$A$10,X73,Assumptions!$C$6:$C$10),0) -> 13.475 | AI73: =IFERROR(IF(Assumptions!$B$13="Cost Price",AB73,AA73)*SUMIF(Assumptions!$A$6:$A$10,X73,Assumptions!$D$6:$D$10),0) -> 26.95 | AJ73: 26.95 | AK73: =SUM(AG73:AJ73) -> 88.935 | AL73: 0.33 | AM73: =AC73-AK73 -> -78.935 | AN73: =IFERROR(AM73/AA73,0) -> -0.29289425 | AO73: =IF(AN73>=Assumptions!$B$3,"OK","Review") -> Review
A74: Corekit AY 2027-2028 | B74: Grade 5 | C74: Service | D74: Services Charges_25_26 | E74: 1:1 | F74: Services Charges | G74: 2027-2028 | H74: Term 1 | I74: 8400007 | J74: 96 | L74: =J74+K74 -> 96 | M74: 0.18 | N74: =M74*L74 -> 17.28 | O74: =L74+N74 -> 113.28 | P74: =IFERROR(O74/Q74,"") -> 0.2626539 | Q74: =SUMIFS(O:O,T:T,T74,B:B,B74,A:A,A74,G:G,G74,E:E,E74) -> 431.29 | R74: =V74-SUMIFS(Q:Q,A:A,A74,B:B,B74,G:G,G74,E:E,E74,T:T,"Fixed Price ( Base Price with GST)") -> 3056.72 | S74: =IF(T74="Fixed Price ( Base Price with GST)",O74,P74*R74) -> 113.28 | T74: Fixed Price ( Base Price with GST) | U74: 5599 | V74: =IFERROR(U74*(1-30%),0) -> 3919.3 | W74: 999299 | X74: Core | Y74: =IFERROR(S74,0) -> 113.28 | Z74: =IF(ISNUMBER(S74),S74,0) -> 113.28 | AA74: =IFERROR(Z74/(1+M74),Z74) -> 96 | AB74: =IF(ISNUMBER(J74),J74,0) -> 96 | AC74: =AA74-AB74 -> 0 | AD74: =IFERROR(AC74/AA74,0) -> 0 | AE74: =IFERROR(AC74/AB74,0) -> 0 | AF74: =IF(AD74>=Assumptions!$B$3,"OK","Review") -> Review | AG74: =IFERROR(IF(Assumptions!$B$13="Cost Price",AB74,AA74)*SUMIF(Assumptions!$A$6:$A$10,X74,Assumptions!$B$6:$B$10),0) -> 7.68 | AH74: =IFERROR(IF(Assumptions!$B$13="Cost Price",AB74,AA74)*SUMIF(Assumptions!$A$6:$A$10,X74,Assumptions!$C$6:$C$10),0) -> 4.8 | AI74: =IFERROR(IF(Assumptions!$B$13="Cost Price",AB74,AA74)*SUMIF(Assumptions!$A$6:$A$10,X74,Assumptions!$D$6:$D$10),0) -> 9.6 | AJ74: 9.6 | AK74: =SUM(AG74:AJ74) -> 31.68 | AL74: 0.33 | AM74: =AC74-AK74 -> -31.68 | AN74: =IFERROR(AM74/AA74,0) -> -0.33 | AO74: =IF(AN74>=Assumptions!$B$3,"OK","Review") -> Review
A75: Corekit AY 2027-2028 | B75: Grade 6 | C75: Science | D75: T1_G6_Science Explorers_TB B2B (27) | E75: 1:1 | F75: Workbook | G75: 2027-2028 | H75: Term 1 | I75: 4000011741 | J75: 52.4 | L75: =J75+K75 -> 52.4 | M75: 0 | N75: =M75*L75 -> 0 | O75: =L75+N75 -> 52.4 | P75: =IFERROR(O75/Q75,"") -> 0.093499634 | Q75: =SUMIFS(O:O,T:T,T75,B:B,B75,A:A,A75,G:G,G75,E:E,E75) -> 560.43 | R75: =V75-SUMIFS(Q:Q,A:A,A75,B:B,B75,G:G,G75,E:E,E75,T:T,"Fixed Price ( Base Price with GST)") -> 3063 | S75: =IF(T75="Fixed Price ( Base Price with GST)",O75,P75*R75) -> 286.38938 | T75: Based on Base % | U75: 5699 | V75: =IFERROR(U75*(1-30%),0) -> 3989.3 | W75: 490110 | X75: Core | Y75: =IFERROR(S75,0) -> 286.38938 | Z75: =IF(ISNUMBER(S75),S75,0) -> 286.38938 | AA75: =IFERROR(Z75/(1+M75),Z75) -> 286.38938 | AB75: =IF(ISNUMBER(J75),J75,0) -> 52.4 | AC75: =AA75-AB75 -> 233.98938 | AD75: =IFERROR(AC75/AA75,0) -> 0.81703232 | AE75: =IFERROR(AC75/AB75,0) -> 4.4654462 | AF75: =IF(AD75>=Assumptions!$B$3,"OK","Review") -> OK | AG75: =IFERROR(IF(Assumptions!$B$13="Cost Price",AB75,AA75)*SUMIF(Assumptions!$A$6:$A$10,X75,Assumptions!$B$6:$B$10),0) -> 22.91115 | AH75: =IFERROR(IF(Assumptions!$B$13="Cost Price",AB75,AA75)*SUMIF(Assumptions!$A$6:$A$10,X75,Assumptions!$C$6:$C$10),0) -> 14.319469 | AI75: =IFERROR(IF(Assumptions!$B$13="Cost Price",AB75,AA75)*SUMIF(Assumptions!$A$6:$A$10,X75,Assumptions!$D$6:$D$10),0) -> 28.638938 | AJ75: 44.62457 | AK75: =SUM(AG75:AJ75) -> 110.49413 | AL75: 0.33 | AM75: =AC75-AK75 -> 123.49525 | AN75: =IFERROR(AM75/AA75,0) -> 0.4312145 | AO75: =IF(AN75>=Assumptions!$B$3,"OK","Review") -> OK
A76: Corekit AY 2027-2028 | B76: Grade 6 | C76: Science | D76: T1_G6_Science Explorers_WB B2B (27) | E76: 1:1 | F76: Workbook | G76: 2027-2028 | H76: Term 1 | I76: 4000011742 | J76: 21.96 | L76: =J76+K76 -> 21.96 | M76: 0 | N76: =M76*L76 -> 0 | O76: =L76+N76 -> 21.96 | P76: =IFERROR(O76/Q76,"") -> 0.039184198 | Q76: =SUMIFS(O:O,T:T,T76,B:B,B76,A:A,A76,G:G,G76,E:E,E76) -> 560.43 | R76: =V76-SUMIFS(Q:Q,A:A,A76,B:B,B76,G:G,G76,E:E,E76,T:T,"Fixed Price ( Base Price with GST)") -> 3063 | S76: =IF(T76="Fixed Price ( Base Price with GST)",O76,P76*R76) -> 120.0212 | T76: Based on Base % | U76: 5699 | V76: =IFERROR(U76*(1-30%),0) -> 3989.3 | W76: 490110 | X76: Core | Y76: =IFERROR(S76,0) -> 120.0212 | Z76: =IF(ISNUMBER(S76),S76,0) -> 120.0212 | AA76: =IFERROR(Z76/(1+M76),Z76) -> 120.0212 | AB76: =IF(ISNUMBER(J76),J76,0) -> 21.96 | AC76: =AA76-AB76 -> 98.061198 | AD76: =IFERROR(AC76/AA76,0) -> 0.81703232 | AE76: =IFERROR(AC76/AB76,0) -> 4.4654462 | AF76: =IF(AD76>=Assumptions!$B$3,"OK","Review") -> OK | AG76: =IFERROR(IF(Assumptions!$B$13="Cost Price",AB76,AA76)*SUMIF(Assumptions!$A$6:$A$10,X76,Assumptions!$B$6:$B$10),0) -> 9.6016958 | AH76: =IFERROR(IF(Assumptions!$B$13="Cost Price",AB76,AA76)*SUMIF(Assumptions!$A$6:$A$10,X76,Assumptions!$C$6:$C$10),0) -> 6.0010599 | AI76: =IFERROR(IF(Assumptions!$B$13="Cost Price",AB76,AA76)*SUMIF(Assumptions!$A$6:$A$10,X76,Assumptions!$D$6:$D$10),0) -> 12.00212 | AJ76: 18.701442 | AK76: =SUM(AG76:AJ76) -> 46.306318 | AL76: 0.33 | AM76: =AC76-AK76 -> 51.75488 | AN76: =IFERROR(AM76/AA76,0) -> 0.4312145 | AO76: =IF(AN76>=Assumptions!$B$3,"OK","Review") -> OK
A77: Corekit AY 2027-2028 | B77: Grade 6 | C77: Maths | D77: T1_G6_Math_Scholars_TB B2B (27) | E77: 1:1 | F77: Book | G77: 2027-2028 | H77: Term 1 | I77: 4000011743 | J77: 54.96 | L77: =J77+K77 -> 54.96 | M77: 0 | N77: =M77*L77 -> 0 | O77: =L77+N77 -> 54.96 | P77: =IFERROR(O77/Q77,"") -> 0.098067555 | Q77: =SUMIFS(O:O,T:T,T77,B:B,B77,A:A,A77,G:G,G77,E:E,E77) -> 560.43 | R77: =V77-SUMIFS(Q:Q,A:A,A77,B:B,B77,G:G,G77,E:E,E77,T:T,"Fixed Price ( Base Price with GST)") -> 3063 | S77: =IF(T77="Fixed Price ( Base Price with GST)",O77,P77*R77) -> 300.38092 | T77: Based on Base % | U77: 5699 | V77: =IFERROR(U77*(1-30%),0) -> 3989.3 | W77: 490110 | X77: Core | Y77: =IFERROR(S77,0) -> 300.38092 | Z77: =IF(ISNUMBER(S77),S77,0) -> 300.38092 | AA77: =IFERROR(Z77/(1+M77),Z77) -> 300.38092 | AB77: =IF(ISNUMBER(J77),J77,0) -> 54.96 | AC77: =AA77-AB77 -> 245.42092 | AD77: =IFERROR(AC77/AA77,0) -> 0.81703232 | AE77: =IFERROR(AC77/AB77,0) -> 4.4654462 | AF77: =IF(AD77>=Assumptions!$B$3,"OK","Review") -> OK | AG77: =IFERROR(IF(Assumptions!$B$13="Cost Price",AB77,AA77)*SUMIF(Assumptions!$A$6:$A$10,X77,Assumptions!$B$6:$B$10),0) -> 24.030474 | AH77: =IFERROR(IF(Assumptions!$B$13="Cost Price",AB77,AA77)*SUMIF(Assumptions!$A$6:$A$10,X77,Assumptions!$C$6:$C$10),0) -> 15.019046 | AI77: =IFERROR(IF(Assumptions!$B$13="Cost Price",AB77,AA77)*SUMIF(Assumptions!$A$6:$A$10,X77,Assumptions!$D$6:$D$10),0) -> 30.038092 | AJ77: 46.804702 | AK77: =SUM(AG77:AJ77) -> 115.89231 | AL77: 0.33 | AM77: =AC77-AK77 -> 129.52861 | AN77: =IFERROR(AM77/AA77,0) -> 0.4312145 | AO77: =IF(AN77>=Assumptions!$B$3,"OK","Review") -> OK
A78: Corekit AY 2027-2028 | B78: Grade 6 | C78: English | D78: Annual_G6_English_Supp B2B (27) | E78: 1:1 | F78: Book | G78: 2027-2028 | H78: Term 1 | I78: 4000011745 | J78: 19.91 | L78: =J78+K78 -> 19.91 | M78: 0 | N78: =M78*L78 -> 0 | O78: =L78+N78 -> 19.91 | P78: =IFERROR(O78/Q78,"") -> 0.035526292 | Q78: =SUMIFS(O:O,T:T,T78,B:B,B78,A:A,A78,G:G,G78,E:E,E78) -> 560.43 | R78: =V78-SUMIFS(Q:Q,A:A,A78,B:B,B78,G:G,G78,E:E,E78,T:T,"Fixed Price ( Base Price with GST)") -> 3063 | S78: =IF(T78="Fixed Price ( Base Price with GST)",O78,P78*R78) -> 108.81703 | T78: Based on Base % | U78: 5699 | V78: =IFERROR(U78*(1-30%),0) -> 3989.3 | W78: 490110 | X78: Core | Y78: =IFERROR(S78,0) -> 108.81703 | Z78: =IF(ISNUMBER(S78),S78,0) -> 108.81703 | AA78: =IFERROR(Z78/(1+M78),Z78) -> 108.81703 | AB78: =IF(ISNUMBER(J78),J78,0) -> 19.91 | AC78: =AA78-AB78 -> 88.907033 | AD78: =IFERROR(AC78/AA78,0) -> 0.81703232 | AE78: =IFERROR(AC78/AB78,0) -> 4.4654462 | AF78: =IF(AD78>=Assumptions!$B$3,"OK","Review") -> OK | AG78: =IFERROR(IF(Assumptions!$B$13="Cost Price",AB78,AA78)*SUMIF(Assumptions!$A$6:$A$10,X78,Assumptions!$B$6:$B$10),0) -> 8.7053627 | AH78: =IFERROR(IF(Assumptions!$B$13="Cost Price",AB78,AA78)*SUMIF(Assumptions!$A$6:$A$10,X78,Assumptions!$C$6:$C$10),0) -> 5.4408517 | AI78: =IFERROR(IF(Assumptions!$B$13="Cost Price",AB78,AA78)*SUMIF(Assumptions!$A$6:$A$10,X78,Assumptions!$D$6:$D$10),0) -> 10.881703 | AJ78: 16.955634 | AK78: =SUM(AG78:AJ78) -> 41.983551 | AL78: 0.33 | AM78: =AC78-AK78 -> 46.923482 | AN78: =IFERROR(AM78/AA78,0) -> 0.4312145 | AO78: =IF(AN78>=Assumptions!$B$3,"OK","Review") -> OK
A79: Corekit AY 2027-2028 | B79: Grade 6 | C79: English | D79: T1_G6_English_TB B2B (27) | E79: 1:1 | F79: Book | G79: 2027-2028 | H79: Term 1 | I79: 4000011744 | J79: 57.51 | L79: =J79+K79 -> 57.51 | M79: 0 | N79: =M79*L79 -> 0 | O79: =L79+N79 -> 57.51 | P79: =IFERROR(O79/Q79,"") -> 0.10261763 | Q79: =SUMIFS(O:O,T:T,T79,B:B,B79,A:A,A79,G:G,G79,E:E,E79) -> 560.43 | R79: =V79-SUMIFS(Q:Q,A:A,A79,B:B,B79,G:G,G79,E:E,E79,T:T,"Fixed Price ( Base Price with GST)") -> 3063 | S79: =IF(T79="Fixed Price ( Base Price with GST)",O79,P79*R79) -> 314.31781 | T79: Based on Base % | U79: 5699 | V79: =IFERROR(U79*(1-30%),0) -> 3989.3 | W79: 490110 | X79: Core | Y79: =IFERROR(S79,0) -> 314.31781 | Z79: =IF(ISNUMBER(S79),S79,0) -> 314.31781 | AA79: =IFERROR(Z79/(1+M79),Z79) -> 314.31781 | AB79: =IF(ISNUMBER(J79),J79,0) -> 57.51 | AC79: =AA79-AB79 -> 256.80781 | AD79: =IFERROR(AC79/AA79,0) -> 0.81703232 | AE79: =IFERROR(AC79/AB79,0) -> 4.4654462 | AF79: =IF(AD79>=Assumptions!$B$3,"OK","Review") -> OK | AG79: =IFERROR(IF(Assumptions!$B$13="Cost Price",AB79,AA79)*SUMIF(Assumptions!$A$6:$A$10,X79,Assumptions!$B$6:$B$10),0) -> 25.145425 | AH79: =IFERROR(IF(Assumptions!$B$13="Cost Price",AB79,AA79)*SUMIF(Assumptions!$A$6:$A$10,X79,Assumptions!$C$6:$C$10),0) -> 15.71589 | AI79: =IFERROR(IF(Assumptions!$B$13="Cost Price",AB79,AA79)*SUMIF(Assumptions!$A$6:$A$10,X79,Assumptions!$D$6:$D$10),0) -> 31.431781 | AJ79: 48.976318 | AK79: =SUM(AG79:AJ79) -> 121.26941 | AL79: 0.33 | AM79: =AC79-AK79 -> 135.5384 | AN79: =IFERROR(AM79/AA79,0) -> 0.4312145 | AO79: =IF(AN79>=Assumptions!$B$3,"OK","Review") -> OK
A80: Corekit AY 2027-2028 | B80: Grade 6 | C80: English | D80: T1_G6_English_WB B2B (27) | E80: 1:1 | F80: Book | G80: 2027-2028 | H80: Term 1 | I80: 4000011746 | J80: 15.85 | L80: =J80+K80 -> 15.85 | M80: 0 | N80: =M80*L80 -> 0 | O80: =L80+N80 -> 15.85 | P80: =IFERROR(O80/Q80,"") -> 0.028281855 | Q80: =SUMIFS(O:O,T:T,T80,B:B,B80,A:A,A80,G:G,G80,E:E,E80) -> 560.43 | R80: =V80-SUMIFS(Q:Q,A:A,A80,B:B,B80,G:G,G80,E:E,E80,T:T,"Fixed Price ( Base Price with GST)") -> 3063 | S80: =IF(T80="Fixed Price ( Base Price with GST)",O80,P80*R80) -> 86.627322 | T80: Based on Base % | U80: 5699 | V80: =IFERROR(U80*(1-30%),0) -> 3989.3 | W80: 490110 | X80: Core | Y80: =IFERROR(S80,0) -> 86.627322 | Z80: =IF(ISNUMBER(S80),S80,0) -> 86.627322 | AA80: =IFERROR(Z80/(1+M80),Z80) -> 86.627322 | AB80: =IF(ISNUMBER(J80),J80,0) -> 15.85 | AC80: =AA80-AB80 -> 70.777322 | AD80: =IFERROR(AC80/AA80,0) -> 0.81703232 | AE80: =IFERROR(AC80/AB80,0) -> 4.4654462 | AF80: =IF(AD80>=Assumptions!$B$3,"OK","Review") -> OK | AG80: =IFERROR(IF(Assumptions!$B$13="Cost Price",AB80,AA80)*SUMIF(Assumptions!$A$6:$A$10,X80,Assumptions!$B$6:$B$10),0) -> 6.9301858 | AH80: =IFERROR(IF(Assumptions!$B$13="Cost Price",AB80,AA80)*SUMIF(Assumptions!$A$6:$A$10,X80,Assumptions!$C$6:$C$10),0) -> 4.3313661 | AI80: =IFERROR(IF(Assumptions!$B$13="Cost Price",AB80,AA80)*SUMIF(Assumptions!$A$6:$A$10,X80,Assumptions!$D$6:$D$10),0) -> 8.6627322 | AJ80: 13.498081 | AK80: =SUM(AG80:AJ80) -> 33.422365 | AL80: 0.33 | AM80: =AC80-AK80 -> 37.354957 | AN80: =IFERROR(AM80/AA80,0) -> 0.4312145 | AO80: =IF(AN80>=Assumptions!$B$3,"OK","Review") -> OK
A81: Corekit AY 2027-2028 | B81: Grade 6 | C81: SST | D81: T1_G6_SST_Mastering Social _TB B2B (27) | E81: 1:1 | F81: Book | G81: 2027-2028 | H81: Term 1 | I81: 4000011748 | J81: 70.11 | L81: =J81+K81 -> 70.11 | M81: 0 | N81: =M81*L81 -> 0 | O81: =L81+N81 -> 70.11 | P81: =IFERROR(O81/Q81,"") -> 0.12510037 | Q81: =SUMIFS(O:O,T:T,T81,B:B,B81,A:A,A81,G:G,G81,E:E,E81) -> 560.43 | R81: =V81-SUMIFS(Q:Q,A:A,A81,B:B,B81,G:G,G81,E:E,E81,T:T,"Fixed Price ( Base Price with GST)") -> 3063 | S81: =IF(T81="Fixed Price ( Base Price with GST)",O81,P81*R81) -> 383.18243 | T81: Based on Base % | U81: 5699 | V81: =IFERROR(U81*(1-30%),0) -> 3989.3 | W81: 490110 | X81: Core | Y81: =IFERROR(S81,0) -> 383.18243 | Z81: =IF(ISNUMBER(S81),S81,0) -> 383.18243 | AA81: =IFERROR(Z81/(1+M81),Z81) -> 383.18243 | AB81: =IF(ISNUMBER(J81),J81,0) -> 70.11 | AC81: =AA81-AB81 -> 313.07243 | AD81: =IFERROR(AC81/AA81,0) -> 0.81703232 | AE81: =IFERROR(AC81/AB81,0) -> 4.4654462 | AF81: =IF(AD81>=Assumptions!$B$3,"OK","Review") -> OK | AG81: =IFERROR(IF(Assumptions!$B$13="Cost Price",AB81,AA81)*SUMIF(Assumptions!$A$6:$A$10,X81,Assumptions!$B$6:$B$10),0) -> 30.654595 | AH81: =IFERROR(IF(Assumptions!$B$13="Cost Price",AB81,AA81)*SUMIF(Assumptions!$A$6:$A$10,X81,Assumptions!$C$6:$C$10),0) -> 19.159122 | AI81: =IFERROR(IF(Assumptions!$B$13="Cost Price",AB81,AA81)*SUMIF(Assumptions!$A$6:$A$10,X81,Assumptions!$D$6:$D$10),0) -> 38.318243 | AJ81: 59.706653 | AK81: =SUM(AG81:AJ81) -> 147.83861 | AL81: 0.33 | AM81: =AC81-AK81 -> 165.23382 | AN81: =IFERROR(AM81/AA81,0) -> 0.4312145 | AO81: =IF(AN81>=Assumptions!$B$3,"OK","Review") -> OK
A82: Corekit AY 2027-2028 | B82: Grade 6 | C82: Science | D82: T2_G6_Science Explorers_TB B2B (27) | E82: 1:1 | F82: Workbook | G82: 2027-2028 | H82: Term 2 | I82: 4000011749 | J82: 54.96 | L82: =J82+K82 -> 54.96 | M82: 0 | N82: =M82*L82 -> 0 | O82: =L82+N82 -> 54.96 | P82: =IFERROR(O82/Q82,"") -> 0.098067555 | Q82: =SUMIFS(O:O,T:T,T82,B:B,B82,A:A,A82,G:G,G82,E:E,E82) -> 560.43 | R82: =V82-SUMIFS(Q:Q,A:A,A82,B:B,B82,G:G,G82,E:E,E82,T:T,"Fixed Price ( Base Price with GST)") -> 3063 | S82: =IF(T82="Fixed Price ( Base Price with GST)",O82,P82*R82) -> 300.38092 | T82: Based on Base % | U82: 5699 | V82: =IFERROR(U82*(1-30%),0) -> 3989.3 | W82: 490110 | X82: Core | Y82: =IFERROR(S82,0) -> 300.38092 | Z82: =IF(ISNUMBER(S82),S82,0) -> 300.38092 | AA82: =IFERROR(Z82/(1+M82),Z82) -> 300.38092 | AB82: =IF(ISNUMBER(J82),J82,0) -> 54.96 | AC82: =AA82-AB82 -> 245.42092 | AD82: =IFERROR(AC82/AA82,0) -> 0.81703232 | AE82: =IFERROR(AC82/AB82,0) -> 4.4654462 | AF82: =IF(AD82>=Assumptions!$B$3,"OK","Review") -> OK | AG82: =IFERROR(IF(Assumptions!$B$13="Cost Price",AB82,AA82)*SUMIF(Assumptions!$A$6:$A$10,X82,Assumptions!$B$6:$B$10),0) -> 24.030474 | AH82: =IFERROR(IF(Assumptions!$B$13="Cost Price",AB82,AA82)*SUMIF(Assumptions!$A$6:$A$10,X82,Assumptions!$C$6:$C$10),0) -> 15.019046 | AI82: =IFERROR(IF(Assumptions!$B$13="Cost Price",AB82,AA82)*SUMIF(Assumptions!$A$6:$A$10,X82,Assumptions!$D$6:$D$10),0) -> 30.038092 | AJ82: 46.804702 | AK82: =SUM(AG82:AJ82) -> 115.89231 | AL82: 0.33 | AM82: =AC82-AK82 -> 129.52861 | AN82: =IFERROR(AM82/AA82,0) -> 0.4312145 | AO82: =IF(AN82>=Assumptions!$B$3,"OK","Review") -> OK
A83: Corekit AY 2027-2028 | B83: Grade 6 | C83: Science | D83: T2_G6_Science Explorers_WB B2B (27) | E83: 1:1 | F83: Workbook | G83: 2027-2028 | H83: Term 2 | I83: 4000011750 | J83: 20.59 | L83: =J83+K83 -> 20.59 | M83: 0 | N83: =M83*L83 -> 0 | O83: =L83+N83 -> 20.59 | P83: =IFERROR(O83/Q83,"") -> 0.036739646 | Q83: =SUMIFS(O:O,T:T,T83,B:B,B83,A:A,A83,G:G,G83,E:E,E83) -> 560.43 | R83: =V83-SUMIFS(Q:Q,A:A,A83,B:B,B83,G:G,G83,E:E,E83,T:T,"Fixed Price ( Base Price with GST)") -> 3063 | S83: =IF(T83="Fixed Price ( Base Price with GST)",O83,P83*R83) -> 112.53354 | T83: Based on Base % | U83: 5699 | V83: =IFERROR(U83*(1-30%),0) -> 3989.3 | W83: 490110 | X83: Core | Y83: =IFERROR(S83,0) -> 112.53354 | Z83: =IF(ISNUMBER(S83),S83,0) -> 112.53354 | AA83: =IFERROR(Z83/(1+M83),Z83) -> 112.53354 | AB83: =IF(ISNUMBER(J83),J83,0) -> 20.59 | AC83: =AA83-AB83 -> 91.943537 | AD83: =IFERROR(AC83/AA83,0) -> 0.81703232 | AE83: =IFERROR(AC83/AB83,0) -> 4.4654462 | AF83: =IF(AD83>=Assumptions!$B$3,"OK","Review") -> OK | AG83: =IFERROR(IF(Assumptions!$B$13="Cost Price",AB83,AA83)*SUMIF(Assumptions!$A$6:$A$10,X83,Assumptions!$B$6:$B$10),0) -> 9.0026829 | AH83: =IFERROR(IF(Assumptions!$B$13="Cost Price",AB83,AA83)*SUMIF(Assumptions!$A$6:$A$10,X83,Assumptions!$C$6:$C$10),0) -> 5.6266768 | AI83: =IFERROR(IF(Assumptions!$B$13="Cost Price",AB83,AA83)*SUMIF(Assumptions!$A$6:$A$10,X83,Assumptions!$D$6:$D$10),0) -> 11.253354 | AJ83: 17.534731 | AK83: =SUM(AG83:AJ83) -> 43.417444 | AL83: 0.33 | AM83: =AC83-AK83 -> 48.526092 | AN83: =IFERROR(AM83/AA83,0) -> 0.4312145 | AO83: =IF(AN83>=Assumptions!$B$3,"OK","Review") -> OK
A84: Corekit AY 2027-2028 | B84: Grade 6 | C84: Maths | D84: T2_G6_Math_Scholars_TB B2B (27) | E84: 1:1 | F84: Book | G84: 2027-2028 | H84: Term 2 | I84: 4000011751 | J84: 60.05 | L84: =J84+K84 -> 60.05 | M84: 0 | N84: =M84*L84 -> 0 | O84: =L84+N84 -> 60.05 | P84: =IFERROR(O84/Q84,"") -> 0.10714987 | Q84: =SUMIFS(O:O,T:T,T84,B:B,B84,A:A,A84,G:G,G84,E:E,E84) -> 560.43 | R84: =V84-SUMIFS(Q:Q,A:A,A84,B:B,B84,G:G,G84,E:E,E84,T:T,"Fixed Price ( Base Price with GST)") -> 3063 | S84: =IF(T84="Fixed Price ( Base Price with GST)",O84,P84*R84) -> 328.20004 | T84: Based on Base % | U84: 5699 | V84: =IFERROR(U84*(1-30%),0) -> 3989.3 | W84: 490110 | X84: Core | Y84: =IFERROR(S84,0) -> 328.20004 | Z84: =IF(ISNUMBER(S84),S84,0) -> 328.20004 | AA84: =IFERROR(Z84/(1+M84),Z84) -> 328.20004 | AB84: =IF(ISNUMBER(J84),J84,0) -> 60.05 | AC84: =AA84-AB84 -> 268.15004 | AD84: =IFERROR(AC84/AA84,0) -> 0.81703232 | AE84: =IFERROR(AC84/AB84,0) -> 4.4654462 | AF84: =IF(AD84>=Assumptions!$B$3,"OK","Review") -> OK | AG84: =IFERROR(IF(Assumptions!$B$13="Cost Price",AB84,AA84)*SUMIF(Assumptions!$A$6:$A$10,X84,Assumptions!$B$6:$B$10),0) -> 26.256003 | AH84: =IFERROR(IF(Assumptions!$B$13="Cost Price",AB84,AA84)*SUMIF(Assumptions!$A$6:$A$10,X84,Assumptions!$C$6:$C$10),0) -> 16.410002 | AI84: =IFERROR(IF(Assumptions!$B$13="Cost Price",AB84,AA84)*SUMIF(Assumptions!$A$6:$A$10,X84,Assumptions!$D$6:$D$10),0) -> 32.820004 | AJ84: 51.139417 | AK84: =SUM(AG84:AJ84) -> 126.62543 | AL84: 0.33 | AM84: =AC84-AK84 -> 141.52462 | AN84: =IFERROR(AM84/AA84,0) -> 0.4312145 | AO84: =IF(AN84>=Assumptions!$B$3,"OK","Review") -> OK
A85: Corekit AY 2027-2028 | B85: Grade 6 | C85: English | D85: T2_G6_English_TB B2B (27) | E85: 1:1 | F85: Book | G85: 2027-2028 | H85: Term 2 | I85: 4000011752 | J85: 53.42 | L85: =J85+K85 -> 53.42 | M85: 0 | N85: =M85*L85 -> 0 | O85: =L85+N85 -> 53.42 | P85: =IFERROR(O85/Q85,"") -> 0.095319665 | Q85: =SUMIFS(O:O,T:T,T85,B:B,B85,A:A,A85,G:G,G85,E:E,E85) -> 560.43 | R85: =V85-SUMIFS(Q:Q,A:A,A85,B:B,B85,G:G,G85,E:E,E85,T:T,"Fixed Price ( Base Price with GST)") -> 3063 | S85: =IF(T85="Fixed Price ( Base Price with GST)",O85,P85*R85) -> 291.96413 | T85: Based on Base % | U85: 5699 | V85: =IFERROR(U85*(1-30%),0) -> 3989.3 | W85: 490110 | X85: Core | Y85: =IFERROR(S85,0) -> 291.96413 | Z85: =IF(ISNUMBER(S85),S85,0) -> 291.96413 | AA85: =IFERROR(Z85/(1+M85),Z85) -> 291.96413 | AB85: =IF(ISNUMBER(J85),J85,0) -> 53.42 | AC85: =AA85-AB85 -> 238.54413 | AD85: =IFERROR(AC85/AA85,0) -> 0.81703232 | AE85: =IFERROR(AC85/AB85,0) -> 4.4654462 | AF85: =IF(AD85>=Assumptions!$B$3,"OK","Review") -> OK | AG85: =IFERROR(IF(Assumptions!$B$13="Cost Price",AB85,AA85)*SUMIF(Assumptions!$A$6:$A$10,X85,Assumptions!$B$6:$B$10),0) -> 23.357131 | AH85: =IFERROR(IF(Assumptions!$B$13="Cost Price",AB85,AA85)*SUMIF(Assumptions!$A$6:$A$10,X85,Assumptions!$C$6:$C$10),0) -> 14.598207 | AI85: =IFERROR(IF(Assumptions!$B$13="Cost Price",AB85,AA85)*SUMIF(Assumptions!$A$6:$A$10,X85,Assumptions!$D$6:$D$10),0) -> 29.196413 | AJ85: 45.493217 | AK85: =SUM(AG85:AJ85) -> 112.64497 | AL85: 0.33 | AM85: =AC85-AK85 -> 125.89917 | AN85: =IFERROR(AM85/AA85,0) -> 0.4312145 | AO85: =IF(AN85>=Assumptions!$B$3,"OK","Review") -> OK
... A87: Corekit AY 2027-2028 | B87: Grade 6 | C87: SST | D87: T2_G6_SST_Mastering Social _TB B2B (27) | E87: 1:1 | F87: Book | G87: 2027-2028 | H87: Term 2 | I87: 4000011754 | J87: 60.05 | L87: =J87+K87 -> 60.05 | M87: 0 | N87: =M87*L87 -> 0 | O87: =L87+N87 -> 60.05 | P87: =IFERROR(O87/Q87,"") -> 0.10714987 | Q87: =SUMIFS(O:O,T:T,T87,B:B,B87,A:A,A87,G:G,G87,E:E,E87) -> 560.43 | R87: =V87-SUMIFS(Q:Q,A:A,A87,B:B,B87,G:G,G87,E:E,E87,T:T,"Fixed Price ( Base Price with GST)") -> 3063 | S87: =IF(T87="Fixed Price ( Base Price with GST)",O87,P87*R87) -> 328.20004 | T87: Based on Base % | U87: 5699 | V87: =IFERROR(U87*(1-30%),0) -> 3989.3 | W87: 490110 | X87: Core | Y87: =IFERROR(S87,0) -> 328.20004 | Z87: =IF(ISNUMBER(S87),S87,0) -> 328.20004 | AA87: =IFERROR(Z87/(1+M87),Z87) -> 328.20004 | AB87: =IF(ISNUMBER(J87),J87,0) -> 60.05 | AC87: =AA87-AB87 -> 268.15004 | AD87: =IFERROR(AC87/AA87,0) -> 0.81703232 | AE87: =IFERROR(AC87/AB87,0) -> 4.4654462 | AF87: =IF(AD87>=Assumptions!$B$3,"OK","Review") -> OK | AG87: =IFERROR(IF(Assumptions!$B$13="Cost Price",AB87,AA87)*SUMIF(Assumptions!$A$6:$A$10,X87,Assumptions!$B$6:$B$10),0) -> 26.256003 | AH87: =IFERROR(IF(Assumptions!$B$13="Cost Price",AB87,AA87)*SUMIF(Assumptions!$A$6:$A$10,X87,Assumptions!$C$6:$C$10),0) -> 16.410002 | AI87: =IFERROR(IF(Assumptions!$B$13="Cost Price",AB87,AA87)*SUMIF(Assumptions!$A$6:$A$10,X87,Assumptions!$D$6:$D$10),0) -> 32.820004 | AJ87: 51.139417 | AK87: =SUM(AG87:AJ87) -> 126.62543 | AL87: 0.33 | AM87: =AC87-AK87 -> 141.52462 | AN87: =IFERROR(AM87/AA87,0) -> 0.4312145 | AO87: =IF(AN87>=Assumptions!$B$3,"OK","Review") -> OK
A88: Corekit AY 2027-2028 | B88: Grade 6 | C88: Combo Kit | D88: B2B Sci-Pi Combined Kit G6 27-28 | E88: 1:1 | F88: Kit | G88: 2027-2028 | H88: Term 1 | I88: 7000000218 | J88: 286.5 | K88: 10 | L88: =J88+K88 -> 296.5 | M88: 0.18 | N88: =M88*L88 -> 53.37 | O88: =L88+N88 -> 349.87 | P88: =IFERROR(O88/Q88,"") -> 0.75541401 | Q88: =SUMIFS(O:O,T:T,T88,B:B,B88,A:A,A88,G:G,G88,E:E,E88) -> 463.15 | R88: =V88-SUMIFS(Q:Q,A:A,A88,B:B,B88,G:G,G88,E:E,E88,T:T,"Fixed Price ( Base Price with GST)") -> 3063 | S88: =IF(T88="Fixed Price ( Base Price with GST)",O88,P88*R88) -> 349.87 | T88: Fixed Price ( Base Price with GST) | U88: 5699 | V88: =IFERROR(U88*(1-30%),0) -> 3989.3 | W88: 49119990 | X88: Core | Y88: =IFERROR(S88,0) -> 349.87 | Z88: =IF(ISNUMBER(S88),S88,0) -> 349.87 | AA88: =IFERROR(Z88/(1+M88),Z88) -> 296.5 | AB88: =IF(ISNUMBER(J88),J88,0) -> 286.5 | AC88: =AA88-AB88 -> 10 | AD88: =IFERROR(AC88/AA88,0) -> 0.033726813 | AE88: =IFERROR(AC88/AB88,0) -> 0.034904014 | AF88: =IF(AD88>=Assumptions!$B$3,"OK","Review") -> Review | AG88: =IFERROR(IF(Assumptions!$B$13="Cost Price",AB88,AA88)*SUMIF(Assumptions!$A$6:$A$10,X88,Assumptions!$B$6:$B$10),0) -> 23.72 | AH88: =IFERROR(IF(Assumptions!$B$13="Cost Price",AB88,AA88)*SUMIF(Assumptions!$A$6:$A$10,X88,Assumptions!$C$6:$C$10),0) -> 14.825 | AI88: =IFERROR(IF(Assumptions!$B$13="Cost Price",AB88,AA88)*SUMIF(Assumptions!$A$6:$A$10,X88,Assumptions!$D$6:$D$10),0) -> 29.65 | AJ88: 29.65 | AK88: =SUM(AG88:AJ88) -> 97.845 | AL88: 0.33 | AM88: =AC88-AK88 -> -87.845 | AN88: =IFERROR(AM88/AA88,0) -> -0.29627319 | AO88: =IF(AN88>=Assumptions!$B$3,"OK","Review") -> Review
A89: Corekit AY 2027-2028 | B89: Grade 6 | C89: Service | D89: Services Charges_25_26 | E89: 1:1 | F89: Services Charges | G89: 2027-2028 | H89: Term 1 | I89: 8400007 | J89: 96 | L89: =J89+K89 -> 96 | M89: 0.18 | N89: =M89*L89 -> 17.28 | O89: =L89+N89 -> 113.28 | P89: =IFERROR(O89/Q89,"") -> 0.24458599 | Q89: =SUMIFS(O:O,T:T,T89,B:B,B89,A:A,A89,G:G,G89,E:E,E89) -> 463.15 | R89: =V89-SUMIFS(Q:Q,A:A,A89,B:B,B89,G:G,G89,E:E,E89,T:T,"Fixed Price ( Base Price with GST)") -> 3063 | S89: =IF(T89="Fixed Price ( Base Price with GST)",O89,P89*R89) -> 113.28 | T89: Fixed Price ( Base Price with GST) | U89: 5699 | V89: =IFERROR(U89*(1-30%),0) -> 3989.3 | W89: 999299 | X89: Core | Y89: =IFERROR(S89,0) -> 113.28 | Z89: =IF(ISNUMBER(S89),S89,0) -> 113.28 | AA89: =IFERROR(Z89/(1+M89),Z89) -> 96 | AB89: =IF(ISNUMBER(J89),J89,0) -> 96 | AC89: =AA89-AB89 -> 0 | AD89: =IFERROR(AC89/AA89,0) -> 0 | AE89: =IFERROR(AC89/AB89,0) -> 0 | AF89: =IF(AD89>=Assumptions!$B$3,"OK","Review") -> Review | AG89: =IFERROR(IF(Assumptions!$B$13="Cost Price",AB89,AA89)*SUMIF(Assumptions!$A$6:$A$10,X89,Assumptions!$B$6:$B$10),0) -> 7.68 | AH89: =IFERROR(IF(Assumptions!$B$13="Cost Price",AB89,AA89)*SUMIF(Assumptions!$A$6:$A$10,X89,Assumptions!$C$6:$C$10),0) -> 4.8 | AI89: =IFERROR(IF(Assumptions!$B$13="Cost Price",AB89,AA89)*SUMIF(Assumptions!$A$6:$A$10,X89,Assumptions!$D$6:$D$10),0) -> 9.6 | AJ89: 9.6 | AK89: =SUM(AG89:AJ89) -> 31.68 | AL89: 0.33 | AM89: =AC89-AK89 -> -31.68 | AN89: =IFERROR(AM89/AA89,0) -> -0.33 | AO89: =IF(AN89>=Assumptions!$B$3,"OK","Review") -> Review
A90: Corekit AY 2027-2028 | B90: Grade 7 | C90: Science | D90: T1_G7_Science Explorers_TB B2B (27) | E90: 1:1 | F90: Workbook | G90: 2027-2028 | H90: Term 1 | I90: 4000011755 | J90: 51.85 | L90: =J90+K90 -> 51.85 | M90: 0 | N90: =M90*L90 -> 0 | O90: =L90+N90 -> 51.85 | P90: =IFERROR(O90/Q90,"") -> 0.077369583 | Q90: =SUMIFS(O:O,T:T,T90,B:B,B90,A:A,A90,G:G,G90,E:E,E90) -> 670.16 | R90: =V90-SUMIFS(Q:Q,A:A,A90,B:B,B90,G:G,G90,E:E,E90,T:T,"Fixed Price ( Base Price with GST)") -> 3057.572 | S90: =IF(T90="Fixed Price ( Base Price with GST)",O90,P90*R90) -> 236.56307 | T90: Based on Base % | U90: 5699 | V90: =IFERROR(U90*(1-30%),0) -> 3989.3 | W90: 490110 | X90: Core | Y90: =IFERROR(S90,0) -> 236.56307 | Z90: =IF(ISNUMBER(S90),S90,0) -> 236.56307 | AA90: =IFERROR(Z90/(1+M90),Z90) -> 236.56307 | AB90: =IF(ISNUMBER(J90),J90,0) -> 51.85 | AC90: =AA90-AB90 -> 184.71307 | AD90: =IFERROR(AC90/AA90,0) -> 0.78081955 | AE90: =IFERROR(AC90/AB90,0) -> 3.5624508 | AF90: =IF(AD90>=Assumptions!$B$3,"OK","Review") -> OK | AG90: =IFERROR(IF(Assumptions!$B$13="Cost Price",AB90,AA90)*SUMIF(Assumptions!$A$6:$A$10,X90,Assumptions!$B$6:$B$10),0) -> 18.925046 | AH90: =IFERROR(IF(Assumptions!$B$13="Cost Price",AB90,AA90)*SUMIF(Assumptions!$A$6:$A$10,X90,Assumptions!$C$6:$C$10),0) -> 11.828154 | AI90: =IFERROR(IF(Assumptions!$B$13="Cost Price",AB90,AA90)*SUMIF(Assumptions!$A$6:$A$10,X90,Assumptions!$D$6:$D$10),0) -> 23.656307 | AJ90: 36.884185 | AK90: =SUM(AG90:AJ90) -> 91.293691 | AL90: 0.33 | AM90: =AC90-AK90 -> 93.41938 | AN90: =IFERROR(AM90/AA90,0) -> 0.39490264 | AO90: =IF(AN90>=Assumptions!$B$3,"OK","Review") -> OK
A91: Corekit AY 2027-2028 | B91: Grade 7 | C91: Science | D91: T1_G7_Science Explorers_WB B2B (27) | E91: 1:1 | F91: Workbook | G91: 2027-2028 | H91: Term 1 | I91: 4000011756 | J91: 22.42 | L91: =J91+K91 -> 22.42 | M91: 0 | N91: =M91*L91 -> 0 | O91: =L91+N91 -> 22.42 | P91: =IFERROR(O91/Q91,"") -> 0.033454697 | Q91: =SUMIFS(O:O,T:T,T91,B:B,B91,A:A,A91,G:G,G91,E:E,E91) -> 670.16 | R91: =V91-SUMIFS(Q:Q,A:A,A91,B:B,B91,G:G,G91,E:E,E91,T:T,"Fixed Price ( Base Price with GST)") -> 3057.572 | S91: =IF(T91="Fixed Price ( Base Price with GST)",O91,P91*R91) -> 102.29015 | T91: Based on Base % | U91: 5699 | V91: =IFERROR(U91*(1-30%),0) -> 3989.3 | W91: 490110 | X91: Core | Y91: =IFERROR(S91,0) -> 102.29015 | Z91: =IF(ISNUMBER(S91),S91,0) -> 102.29015 | AA91: =IFERROR(Z91/(1+M91),Z91) -> 102.29015 | AB91: =IF(ISNUMBER(J91),J91,0) -> 22.42 | AC91: =AA91-AB91 -> 79.870146 | AD91: =IFERROR(AC91/AA91,0) -> 0.78081955 | AE91: =IFERROR(AC91/AB91,0) -> 3.5624508 | AF91: =IF(AD91>=Assumptions!$B$3,"OK","Review") -> OK | AG91: =IFERROR(IF(Assumptions!$B$13="Cost Price",AB91,AA91)*SUMIF(Assumptions!$A$6:$A$10,X91,Assumptions!$B$6:$B$10),0) -> 8.1832117 | AH91: =IFERROR(IF(Assumptions!$B$13="Cost Price",AB91,AA91)*SUMIF(Assumptions!$A$6:$A$10,X91,Assumptions!$C$6:$C$10),0) -> 5.1145073 | AI91: =IFERROR(IF(Assumptions!$B$13="Cost Price",AB91,AA91)*SUMIF(Assumptions!$A$6:$A$10,X91,Assumptions!$D$6:$D$10),0) -> 10.229015 | AJ91: 15.948764 | AK91: =SUM(AG91:AJ91) -> 39.475498 | AL91: 0.33 | AM91: =AC91-AK91 -> 40.394648 | AN91: =IFERROR(AM91/AA91,0) -> 0.39490264 | AO91: =IF(AN91>=Assumptions!$B$3,"OK","Review") -> OK
A92: Corekit AY 2027-2028 | B92: Grade 7 | C92: Maths | D92: T1_G7_Math_Scholars_TB B2B (27) | E92: 1:1 | F92: Book | G92: 2027-2028 | H92: Term 1 | I92: 4000011757 | J92: 72.88 | L92: =J92+K92 -> 72.88 | M92: 0 | N92: =M92*L92 -> 0 | O92: =L92+N92 -> 72.88 | P92: =IFERROR(O92/Q92,"") -> 0.10875015 | Q92: =SUMIFS(O:O,T:T,T92,B:B,B92,A:A,A92,G:G,G92,E:E,E92) -> 670.16 | R92: =V92-SUMIFS(Q:Q,A:A,A92,B:B,B92,G:G,G92,E:E,E92,T:T,"Fixed Price ( Base Price with GST)") -> 3057.572 | S92: =IF(T92="Fixed Price ( Base Price with GST)",O92,P92*R92) -> 332.51141 | T92: Based on Base % | U92: 5699 | V92: =IFERROR(U92*(1-30%),0) -> 3989.3 | W92: 490110 | X92: Core | Y92: =IFERROR(S92,0) -> 332.51141 | Z92: =IF(ISNUMBER(S92),S92,0) -> 332.51141 | AA92: =IFERROR(Z92/(1+M92),Z92) -> 332.51141 | AB92: =IF(ISNUMBER(J92),J92,0) -> 72.88 | AC92: =AA92-AB92 -> 259.63141 | AD92: =IFERROR(AC92/AA92,0) -> 0.78081955 | AE92: =IFERROR(AC92/AB92,0) -> 3.5624508 | AF92: =IF(AD92>=Assumptions!$B$3,"OK","Review") -> OK | AG92: =IFERROR(IF(Assumptions!$B$13="Cost Price",AB92,AA92)*SUMIF(Assumptions!$A$6:$A$10,X92,Assumptions!$B$6:$B$10),0) -> 26.600913 | AH92: =IFERROR(IF(Assumptions!$B$13="Cost Price",AB92,AA92)*SUMIF(Assumptions!$A$6:$A$10,X92,Assumptions!$C$6:$C$10),0) -> 16.625571 | AI92: =IFERROR(IF(Assumptions!$B$13="Cost Price",AB92,AA92)*SUMIF(Assumptions!$A$6:$A$10,X92,Assumptions!$D$6:$D$10),0) -> 33.251141 | AJ92: 51.844154 | AK92: =SUM(AG92:AJ92) -> 128.32178 | AL92: 0.33 | AM92: =AC92-AK92 -> 131.30963 | AN92: =IFERROR(AM92/AA92,0) -> 0.39490264 | AO92: =IF(AN92>=Assumptions!$B$3,"OK","Review") -> OK
A93: Corekit AY 2027-2028 | B93: Grade 7 | C93: English | D93: Annual_G7_English_Supp B2B (27) | E93: 1:1 | F93: Book | G93: 2027-2028 | H93: Term 1 | I93: 4000011760 | J93: 18.56 | L93: =J93+K93 -> 18.56 | M93: 0 | N93: =M93*L93 -> 0 | O93: =L93+N93 -> 18.56 | P93: =IFERROR(O93/Q93,"") -> 0.027694879 | Q93: =SUMIFS(O:O,T:T,T93,B:B,B93,A:A,A93,G:G,G93,E:E,E93) -> 670.16 | R93: =V93-SUMIFS(Q:Q,A:A,A93,B:B,B93,G:G,G93,E:E,E93,T:T,"Fixed Price ( Base Price with GST)") -> 3057.572 | S93: =IF(T93="Fixed Price ( Base Price with GST)",O93,P93*R93) -> 84.679086 | T93: Based on Base % | U93: 5699 | V93: =IFERROR(U93*(1-30%),0) -> 3989.3 | W93: 490110 | X93: Core | Y93: =IFERROR(S93,0) -> 84.679086 | Z93: =IF(ISNUMBER(S93),S93,0) -> 84.679086 | AA93: =IFERROR(Z93/(1+M93),Z93) -> 84.679086 | AB93: =IF(ISNUMBER(J93),J93,0) -> 18.56 | AC93: =AA93-AB93 -> 66.119086 | AD93: =IFERROR(AC93/AA93,0) -> 0.78081955 | AE93: =IFERROR(AC93/AB93,0) -> 3.5624508 | AF93: =IF(AD93>=Assumptions!$B$3,"OK","Review") -> OK | AG93: =IFERROR(IF(Assumptions!$B$13="Cost Price",AB93,AA93)*SUMIF(Assumptions!$A$6:$A$10,X93,Assumptions!$B$6:$B$10),0) -> 6.7743269 | AH93: =IFERROR(IF(Assumptions!$B$13="Cost Price",AB93,AA93)*SUMIF(Assumptions!$A$6:$A$10,X93,Assumptions!$C$6:$C$10),0) -> 4.2339543 | AI93: =IFERROR(IF(Assumptions!$B$13="Cost Price",AB93,AA93)*SUMIF(Assumptions!$A$6:$A$10,X93,Assumptions!$D$6:$D$10),0) -> 8.4679086 | AJ93: 13.202902 | AK93: =SUM(AG93:AJ93) -> 32.679092 | AL93: 0.33 | AM93: =AC93-AK93 -> 33.439994 | AN93: =IFERROR(AM93/AA93,0) -> 0.39490264 | AO93: =IF(AN93>=Assumptions!$B$3,"OK","Review") -> OK
A94: Corekit AY 2027-2028 | B94: Grade 7 | C94: English | D94: T1_G7_English_TB B2B (27) | E94: 1:1 | F94: Book | G94: 2027-2028 | H94: Term 1 | I94: 4000011759 | J94: 59.69 | L94: =J94+K94 -> 59.69 | M94: 0 | N94: =M94*L94 -> 0 | O94: =L94+N94 -> 59.69 | P94: =IFERROR(O94/Q94,"") -> 0.089068282 | Q94: =SUMIFS(O:O,T:T,T94,B:B,B94,A:A,A94,G:G,G94,E:E,E94) -> 670.16 | R94: =V94-SUMIFS(Q:Q,A:A,A94,B:B,B94,G:G,G94,E:E,E94,T:T,"Fixed Price ( Base Price with GST)") -> 3057.572 | S94: =IF(T94="Fixed Price ( Base Price with GST)",O94,P94*R94) -> 272.33269 | T94: Based on Base % | U94: 5699 | V94: =IFERROR(U94*(1-30%),0) -> 3989.3 | W94: 490110 | X94: Core | Y94: =IFERROR(S94,0) -> 272.33269 | Z94: =IF(ISNUMBER(S94),S94,0) -> 272.33269 | AA94: =IFERROR(Z94/(1+M94),Z94) -> 272.33269 | AB94: =IF(ISNUMBER(J94),J94,0) -> 59.69 | AC94: =AA94-AB94 -> 212.64269 | AD94: =IFERROR(AC94/AA94,0) -> 0.78081955 | AE94: =IFERROR(AC94/AB94,0) -> 3.5624508 | AF94: =IF(AD94>=Assumptions!$B$3,"OK","Review") -> OK | AG94: =IFERROR(IF(Assumptions!$B$13="Cost Price",AB94,AA94)*SUMIF(Assumptions!$A$6:$A$10,X94,Assumptions!$B$6:$B$10),0) -> 21.786615 | AH94: =IFERROR(IF(Assumptions!$B$13="Cost Price",AB94,AA94)*SUMIF(Assumptions!$A$6:$A$10,X94,Assumptions!$C$6:$C$10),0) -> 13.616634 | AI94: =IFERROR(IF(Assumptions!$B$13="Cost Price",AB94,AA94)*SUMIF(Assumptions!$A$6:$A$10,X94,Assumptions!$D$6:$D$10),0) -> 27.233269 | AJ94: 42.461273 | AK94: =SUM(AG94:AJ94) -> 105.09779 | AL94: 0.33 | AM94: =AC94-AK94 -> 107.5449 | AN94: =IFERROR(AM94/AA94,0) -> 0.39490264 | AO94: =IF(AN94>=Assumptions!$B$3,"OK","Review") -> OK
A95: Corekit AY 2027-2028 | B95: Grade 7 | C95: English | D95: T1_G7_English_WB B2B (27) | E95: 1:1 | F95: Book | G95: 2027-2028 | H95: Term 1 | I95: 4000011761 | J95: 14.84 | L95: =J95+K95 -> 14.84 | M95: 0 | N95: =M95*L95 -> 0 | O95: =L95+N95 -> 14.84 | P95: =IFERROR(O95/Q95,"") -> 0.022143966 | Q95: =SUMIFS(O:O,T:T,T95,B:B,B95,A:A,A95,G:G,G95,E:E,E95) -> 670.16 | R95: =V95-SUMIFS(Q:Q,A:A,A95,B:B,B95,G:G,G95,E:E,E95,T:T,"Fixed Price ( Base Price with GST)") -> 3057.572 | S95: =IF(T95="Fixed Price ( Base Price with GST)",O95,P95*R95) -> 67.706769 | T95: Based on Base % | U95: 5699 | V95: =IFERROR(U95*(1-30%),0) -> 3989.3 | W95: 490110 | X95: Core | Y95: =IFERROR(S95,0) -> 67.706769 | Z95: =IF(ISNUMBER(S95),S95,0) -> 67.706769 | AA95: =IFERROR(Z95/(1+M95),Z95) -> 67.706769 | AB95: =IF(ISNUMBER(J95),J95,0) -> 14.84 | AC95: =AA95-AB95 -> 52.866769 | AD95: =IFERROR(AC95/AA95,0) -> 0.78081955 | AE95: =IFERROR(AC95/AB95,0) -> 3.5624508 | AF95: =IF(AD95>=Assumptions!$B$3,"OK","Review") -> OK | AG95: =IFERROR(IF(Assumptions!$B$13="Cost Price",AB95,AA95)*SUMIF(Assumptions!$A$6:$A$10,X95,Assumptions!$B$6:$B$10),0) -> 5.4165415 | AH95: =IFERROR(IF(Assumptions!$B$13="Cost Price",AB95,AA95)*SUMIF(Assumptions!$A$6:$A$10,X95,Assumptions!$C$6:$C$10),0) -> 3.3853385 | AI95: =IFERROR(IF(Assumptions!$B$13="Cost Price",AB95,AA95)*SUMIF(Assumptions!$A$6:$A$10,X95,Assumptions!$D$6:$D$10),0) -> 6.7706769 | AJ95: 10.556631 | AK95: =SUM(AG95:AJ95) -> 26.129188 | AL95: 0.33 | AM95: =AC95-AK95 -> 26.737582 | AN95: =IFERROR(AM95/AA95,0) -> 0.39490264 | AO95: =IF(AN95>=Assumptions!$B$3,"OK","Review") -> OK
A96: Corekit AY 2027-2028 | B96: Grade 7 | C96: SST | D96: T1_G7_SST_Mastering Social _TB B2B (27) | E96: 1:1 | F96: Book | G96: 2027-2028 | H96: Term 1 | I96: 4000011762 | J96: 101.74 | L96: =J96+K96 -> 101.74 | M96: 0 | N96: =M96*L96 -> 0 | O96: =L96+N96 -> 101.74 | P96: =IFERROR(O96/Q96,"") -> 0.15181449 | Q96: =SUMIFS(O:O,T:T,T96,B:B,B96,A:A,A96,G:G,G96,E:E,E96) -> 670.16 | R96: =V96-SUMIFS(Q:Q,A:A,A96,B:B,B96,G:G,G96,E:E,E96,T:T,"Fixed Price ( Base Price with GST)") -> 3057.572 | S96: =IF(T96="Fixed Price ( Base Price with GST)",O96,P96*R96) -> 464.18374 | T96: Based on Base % | U96: 5699 | V96: =IFERROR(U96*(1-30%),0) -> 3989.3 | W96: 490110 | X96: Core | Y96: =IFERROR(S96,0) -> 464.18374 | Z96: =IF(ISNUMBER(S96),S96,0) -> 464.18374 | AA96: =IFERROR(Z96/(1+M96),Z96) -> 464.18374 | AB96: =IF(ISNUMBER(J96),J96,0) -> 101.74 | AC96: =AA96-AB96 -> 362.44374 | AD96: =IFERROR(AC96/AA96,0) -> 0.78081955 | AE96: =IFERROR(AC96/AB96,0) -> 3.5624508 | AF96: =IF(AD96>=Assumptions!$B$3,"OK","Review") -> OK | AG96: =IFERROR(IF(Assumptions!$B$13="Cost Price",AB96,AA96)*SUMIF(Assumptions!$A$6:$A$10,X96,Assumptions!$B$6:$B$10),0) -> 37.134699 | AH96: =IFERROR(IF(Assumptions!$B$13="Cost Price",AB96,AA96)*SUMIF(Assumptions!$A$6:$A$10,X96,Assumptions!$C$6:$C$10),0) -> 23.209187 | AI96: =IFERROR(IF(Assumptions!$B$13="Cost Price",AB96,AA96)*SUMIF(Assumptions!$A$6:$A$10,X96,Assumptions!$D$6:$D$10),0) -> 46.418374 | AJ96: 72.374098 | AK96: =SUM(AG96:AJ96) -> 179.13636 | AL96: 0.33 | AM96: =AC96-AK96 -> 183.30738 | AN96: =IFERROR(AM96/AA96,0) -> 0.39490264 | AO96: =IF(AN96>=Assumptions!$B$3,"OK","Review") -> OK
A97: Corekit AY 2027-2028 | B97: Grade 7 | C97: Science | D97: T2_G7_Science Explorers_TB B2B (27) | E97: 1:1 | F97: Workbook | G97: 2027-2028 | H97: Term 2 | I97: 4000011763 | J97: 57.08 | L97: =J97+K97 -> 57.08 | M97: 0 | N97: =M97*L97 -> 0 | O97: =L97+N97 -> 57.08 | P97: =IFERROR(O97/Q97,"") -> 0.08517369 | Q97: =SUMIFS(O:O,T:T,T97,B:B,B97,A:A,A97,G:G,G97,E:E,E97) -> 670.16 | R97: =V97-SUMIFS(Q:Q,A:A,A97,B:B,B97,G:G,G97,E:E,E97,T:T,"Fixed Price ( Base Price with GST)") -> 3057.572 | S97: =IF(T97="Fixed Price ( Base Price with GST)",O97,P97*R97) -> 260.42469 | T97: Based on Base % | U97: 5699 | V97: =IFERROR(U97*(1-30%),0) -> 3989.3 | W97: 490110 | X97: Core | Y97: =IFERROR(S97,0) -> 260.42469 | Z97: =IF(ISNUMBER(S97),S97,0) -> 260.42469 | AA97: =IFERROR(Z97/(1+M97),Z97) -> 260.42469 | AB97: =IF(ISNUMBER(J97),J97,0) -> 57.08 | AC97: =AA97-AB97 -> 203.34469 | AD97: =IFERROR(AC97/AA97,0) -> 0.78081955 | AE97: =IFERROR(AC97/AB97,0) -> 3.5624508 | AF97: =IF(AD97>=Assumptions!$B$3,"OK","Review") -> OK | AG97: =IFERROR(IF(Assumptions!$B$13="Cost Price",AB97,AA97)*SUMIF(Assumptions!$A$6:$A$10,X97,Assumptions!$B$6:$B$10),0) -> 20.833975 | AH97: =IFERROR(IF(Assumptions!$B$13="Cost Price",AB97,AA97)*SUMIF(Assumptions!$A$6:$A$10,X97,Assumptions!$C$6:$C$10),0) -> 13.021234 | AI97: =IFERROR(IF(Assumptions!$B$13="Cost Price",AB97,AA97)*SUMIF(Assumptions!$A$6:$A$10,X97,Assumptions!$D$6:$D$10),0) -> 26.042469 | AJ97: 40.604615 | AK97: =SUM(AG97:AJ97) -> 100.50229 | AL97: 0.33 | AM97: =AC97-AK97 -> 102.8424 | AN97: =IFERROR(AM97/AA97,0) -> 0.39490264 | AO97: =IF(AN97>=Assumptions!$B$3,"OK","Review") -> OK
A98: Corekit AY 2027-2028 | B98: Grade 7 | C98: Science | D98: T2_G7_Science Explorers_WB B2B (27) | E98: 1:1 | F98: Workbook | G98: 2027-2028 | H98: Term 2 | I98: 4000011764 | J98: 22.42 | L98: =J98+K98 -> 22.42 | M98: 0 | N98: =M98*L98 -> 0 | O98: =L98+N98 -> 22.42 | P98: =IFERROR(O98/Q98,"") -> 0.033454697 | Q98: =SUMIFS(O:O,T:T,T98,B:B,B98,A:A,A98,G:G,G98,E:E,E98) -> 670.16 | R98: =V98-SUMIFS(Q:Q,A:A,A98,B:B,B98,G:G,G98,E:E,E98,T:T,"Fixed Price ( Base Price with GST)") -> 3057.572 | S98: =IF(T98="Fixed Price ( Base Price with GST)",O98,P98*R98) -> 102.29015 | T98: Based on Base % | U98: 5699 | V98: =IFERROR(U98*(1-30%),0) -> 3989.3 | W98: 490110 | X98: Core | Y98: =IFERROR(S98,0) -> 102.29015 | Z98: =IF(ISNUMBER(S98),S98,0) -> 102.29015 | AA98: =IFERROR(Z98/(1+M98),Z98) -> 102.29015 | AB98: =IF(ISNUMBER(J98),J98,0) -> 22.42 | AC98: =AA98-AB98 -> 79.870146 | AD98: =IFERROR(AC98/AA98,0) -> 0.78081955 | AE98: =IFERROR(AC98/AB98,0) -> 3.5624508 | AF98: =IF(AD98>=Assumptions!$B$3,"OK","Review") -> OK | AG98: =IFERROR(IF(Assumptions!$B$13="Cost Price",AB98,AA98)*SUMIF(Assumptions!$A$6:$A$10,X98,Assumptions!$B$6:$B$10),0) -> 8.1832117 | AH98: =IFERROR(IF(Assumptions!$B$13="Cost Price",AB98,AA98)*SUMIF(Assumptions!$A$6:$A$10,X98,Assumptions!$C$6:$C$10),0) -> 5.1145073 | AI98: =IFERROR(IF(Assumptions!$B$13="Cost Price",AB98,AA98)*SUMIF(Assumptions!$A$6:$A$10,X98,Assumptions!$D$6:$D$10),0) -> 10.229015 | AJ98: 15.948764 | AK98: =SUM(AG98:AJ98) -> 39.475498 | AL98: 0.33 | AM98: =AC98-AK98 -> 40.394648 | AN98: =IFERROR(AM98/AA98,0) -> 0.39490264 | AO98: =IF(AN98>=Assumptions!$B$3,"OK","Review") -> OK
A99: Corekit AY 2027-2028 | B99: Grade 7 | C99: Maths | D99: T2_G7_Math_Scholars_TB B2B (27) | E99: 1:1 | F99: Book | G99: 2027-2028 | H99: Term 2 | I99: 4000011765 | J99: 78.07 | L99: =J99+K99 -> 78.07 | M99: 0 | N99: =M99*L99 -> 0 | O99: =L99+N99 -> 78.07 | P99: =IFERROR(O99/Q99,"") -> 0.11649457 | Q99: =SUMIFS(O:O,T:T,T99,B:B,B99,A:A,A99,G:G,G99,E:E,E99) -> 670.16 | R99: =V99-SUMIFS(Q:Q,A:A,A99,B:B,B99,G:G,G99,E:E,E99,T:T,"Fixed Price ( Base Price with GST)") -> 3057.572 | S99: =IF(T99="Fixed Price ( Base Price with GST)",O99,P99*R99) -> 356.19053 | T99: Based on Base % | U99: 5699 | V99: =IFERROR(U99*(1-30%),0) -> 3989.3 | W99: 490110 | X99: Core | Y99: =IFERROR(S99,0) -> 356.19053 | Z99: =IF(ISNUMBER(S99),S99,0) -> 356.19053 | AA99: =IFERROR(Z99/(1+M99),Z99) -> 356.19053 | AB99: =IF(ISNUMBER(J99),J99,0) -> 78.07 | AC99: =AA99-AB99 -> 278.12053 | AD99: =IFERROR(AC99/AA99,0) -> 0.78081955 | AE99: =IFERROR(AC99/AB99,0) -> 3.5624508 | AF99: =IF(AD99>=Assumptions!$B$3,"OK","Review") -> OK | AG99: =IFERROR(IF(Assumptions!$B$13="Cost Price",AB99,AA99)*SUMIF(Assumptions!$A$6:$A$10,X99,Assumptions!$B$6:$B$10),0) -> 28.495242 | AH99: =IFERROR(IF(Assumptions!$B$13="Cost Price",AB99,AA99)*SUMIF(Assumptions!$A$6:$A$10,X99,Assumptions!$C$6:$C$10),0) -> 17.809527 | AI99: =IFERROR(IF(Assumptions!$B$13="Cost Price",AB99,AA99)*SUMIF(Assumptions!$A$6:$A$10,X99,Assumptions!$D$6:$D$10),0) -> 35.619053 | AJ99: 55.536129 | AK99: =SUM(AG99:AJ99) -> 137.45995 | AL99: 0.33 | AM99: =AC99-AK99 -> 140.66058 | AN99: =IFERROR(AM99/AA99,0) -> 0.39490264 | AO99: =IF(AN99>=Assumptions!$B$3,"OK","Review") -> OK
A100: Corekit AY 2027-2028 | B100: Grade 7 | C100: English | D100: T2_G7_English_TB B2B (27) | E100: 1:1 | F100: Book | G100: 2027-2028 | H100: Term 2 | I100: 4000011766 | J100: 63.45 | L100: =J100+K100 -> 63.45 | M100: 0 | N100: =M100*L100 -> 0 | O100: =L100+N100 -> 63.45 | P100: =IFERROR(O100/Q100,"") -> 0.094678883 | Q100: =SUMIFS(O:O,T:T,T100,B:B,B100,A:A,A100,G:G,G100,E:E,E100) -> 670.16 | R100: =V100-SUMIFS(Q:Q,A:A,A100,B:B,B100,G:G,G100,E:E,E100,T:T,"Fixed Price ( Base Price with GST)") -> 3057.572 | S100: =IF(T100="Fixed Price ( Base Price with GST)",O100,P100*R100) -> 289.4875 | T100: Based on Base % | U100: 5699 | V100: =IFERROR(U100*(1-30%),0) -> 3989.3 | W100: 490110 | X100: Core | Y100: =IFERROR(S100,0) -> 289.4875 | Z100: =IF(ISNUMBER(S100),S100,0) -> 289.4875 | AA100: =IFERROR(Z100/(1+M100),Z100) -> 289.4875 | AB100: =IF(ISNUMBER(J100),J100,0) -> 63.45 | AC100: =AA100-AB100 -> 226.0375 | AD100: =IFERROR(AC100/AA100,0) -> 0.78081955 | AE100: =IFERROR(AC100/AB100,0) -> 3.5624508 | AF100: =IF(AD100>=Assumptions!$B$3,"OK","Review") -> OK | AG100: =IFERROR(IF(Assumptions!$B$13="Cost Price",AB100,AA100)*SUMIF(Assumptions!$A$6:$A$10,X100,Assumptions!$B$6:$B$10),0) -> 23.159 | AH100: =IFERROR(IF(Assumptions!$B$13="Cost Price",AB100,AA100)*SUMIF(Assumptions!$A$6:$A$10,X100,Assumptions!$C$6:$C$10),0) -> 14.474375 | AI100: =IFERROR(IF(Assumptions!$B$13="Cost Price",AB100,AA100)*SUMIF(Assumptions!$A$6:$A$10,X100,Assumptions!$D$6:$D$10),0) -> 28.94875 | AJ100: 45.135999 | AK100: =SUM(AG100:AJ100) -> 111.71812 | AL100: 0.33 | AM100: =AC100-AK100 -> 114.31938 | AN100: =IFERROR(AM100/AA100,0) -> 0.39490264 | AO100: =IF(AN100>=Assumptions!$B$3,"OK","Review") -> OK
... A102: Corekit AY 2027-2028 | B102: Grade 7 | C102: SST | D102: T2_G7_SST_Mastering Social _TB B2B (27) | E102: 1:1 | F102: Book | G102: 2027-2028 | H102: Term 2 | I102: 4000011768 | J102: 91.22 | L102: =J102+K102 -> 91.22 | M102: 0 | N102: =M102*L102 -> 0 | O102: =L102+N102 -> 91.22 | P102: =IFERROR(O102/Q102,"") -> 0.13611675 | Q102: =SUMIFS(O:O,T:T,T102,B:B,B102,A:A,A102,G:G,G102,E:E,E102) -> 670.16 | R102: =V102-SUMIFS(Q:Q,A:A,A102,B:B,B102,G:G,G102,E:E,E102,T:T,"Fixed Price ( Base Price with GST)") -> 3057.572 | S102: =IF(T102="Fixed Price ( Base Price with GST)",O102,P102*R102) -> 416.18676 | T102: Based on Base % | U102: 5699 | V102: =IFERROR(U102*(1-30%),0) -> 3989.3 | W102: 490110 | X102: Core | Y102: =IFERROR(S102,0) -> 416.18676 | Z102: =IF(ISNUMBER(S102),S102,0) -> 416.18676 | AA102: =IFERROR(Z102/(1+M102),Z102) -> 416.18676 | AB102: =IF(ISNUMBER(J102),J102,0) -> 91.22 | AC102: =AA102-AB102 -> 324.96676 | AD102: =IFERROR(AC102/AA102,0) -> 0.78081955 | AE102: =IFERROR(AC102/AB102,0) -> 3.5624508 | AF102: =IF(AD102>=Assumptions!$B$3,"OK","Review") -> OK | AG102: =IFERROR(IF(Assumptions!$B$13="Cost Price",AB102,AA102)*SUMIF(Assumptions!$A$6:$A$10,X102,Assumptions!$B$6:$B$10),0) -> 33.294941 | AH102: =IFERROR(IF(Assumptions!$B$13="Cost Price",AB102,AA102)*SUMIF(Assumptions!$A$6:$A$10,X102,Assumptions!$C$6:$C$10),0) -> 20.809338 | AI102: =IFERROR(IF(Assumptions!$B$13="Cost Price",AB102,AA102)*SUMIF(Assumptions!$A$6:$A$10,X102,Assumptions!$D$6:$D$10),0) -> 41.618676 | AJ102: 64.890556 | AK102: =SUM(AG102:AJ102) -> 160.61351 | AL102: 0.33 | AM102: =AC102-AK102 -> 164.35325 | AN102: =IFERROR(AM102/AA102,0) -> 0.39490264 | AO102: =IF(AN102>=Assumptions!$B$3,"OK","Review") -> OK
A103: Corekit AY 2027-2028 | B103: Grade 7 | C103: Combo Kit | D103: B2B Sci-Pi Combined Kit G7 27-28 | E103: 1:1 | F103: Kit | G103: 2027-2028 | H103: Term 1 | I103: 7000000227 | J103: 288.8 | K103: 10 | L103: =J103+K103 -> 298.8 | M103: 0.18 | N103: =M103*L103 -> 53.784 | O103: =L103+N103 -> 352.584 | P103: =IFERROR(O103/Q103,"") -> 0.75683891 | Q103: =SUMIFS(O:O,T:T,T103,B:B,B103,A:A,A103,G:G,G103,E:E,E103) -> 465.864 | R103: =V103-SUMIFS(Q:Q,A:A,A103,B:B,B103,G:G,G103,E:E,E103,T:T,"Fixed Price ( Base Price with GST)") -> 3057.572 | S103: =IF(T103="Fixed Price ( Base Price with GST)",O103,P103*R103) -> 352.584 | T103: Fixed Price ( Base Price with GST) | U103: 5699 | V103: =IFERROR(U103*(1-30%),0) -> 3989.3 | W103: 49119990 | X103: Core | Y103: =IFERROR(S103,0) -> 352.584 | Z103: =IF(ISNUMBER(S103),S103,0) -> 352.584 | AA103: =IFERROR(Z103/(1+M103),Z103) -> 298.8 | AB103: =IF(ISNUMBER(J103),J103,0) -> 288.8 | AC103: =AA103-AB103 -> 10 | AD103: =IFERROR(AC103/AA103,0) -> 0.033467202 | AE103: =IFERROR(AC103/AB103,0) -> 0.034626039 | AF103: =IF(AD103>=Assumptions!$B$3,"OK","Review") -> Review | AG103: =IFERROR(IF(Assumptions!$B$13="Cost Price",AB103,AA103)*SUMIF(Assumptions!$A$6:$A$10,X103,Assumptions!$B$6:$B$10),0) -> 23.904 | AH103: =IFERROR(IF(Assumptions!$B$13="Cost Price",AB103,AA103)*SUMIF(Assumptions!$A$6:$A$10,X103,Assumptions!$C$6:$C$10),0) -> 14.94 | AI103: =IFERROR(IF(Assumptions!$B$13="Cost Price",AB103,AA103)*SUMIF(Assumptions!$A$6:$A$10,X103,Assumptions!$D$6:$D$10),0) -> 29.88 | AJ103: 29.88 | AK103: =SUM(AG103:AJ103) -> 98.604 | AL103: 0.33 | AM103: =AC103-AK103 -> -88.604 | AN103: =IFERROR(AM103/AA103,0) -> -0.2965328 | AO103: =IF(AN103>=Assumptions!$B$3,"OK","Review") -> Review
A104: Corekit AY 2027-2028 | B104: Grade 7 | C104: Service | D104: Services Charges_25_26 | E104: 1:1 | F104: Services Charges | G104: 2027-2028 | H104: Term 1 | I104: 8400007 | J104: 96 | L104: =J104+K104 -> 96 | M104: 0.18 | N104: =M104*L104 -> 17.28 | O104: =L104+N104 -> 113.28 | P104: =IFERROR(O104/Q104,"") -> 0.24316109 | Q104: =SUMIFS(O:O,T:T,T104,B:B,B104,A:A,A104,G:G,G104,E:E,E104) -> 465.864 | R104: =V104-SUMIFS(Q:Q,A:A,A104,B:B,B104,G:G,G104,E:E,E104,T:T,"Fixed Price ( Base Price with GST)") -> 3057.572 | S104: =IF(T104="Fixed Price ( Base Price with GST)",O104,P104*R104) -> 113.28 | T104: Fixed Price ( Base Price with GST) | U104: 5699 | V104: =IFERROR(U104*(1-30%),0) -> 3989.3 | W104: 999299 | X104: Core | Y104: =IFERROR(S104,0) -> 113.28 | Z104: =IF(ISNUMBER(S104),S104,0) -> 113.28 | AA104: =IFERROR(Z104/(1+M104),Z104) -> 96 | AB104: =IF(ISNUMBER(J104),J104,0) -> 96 | AC104: =AA104-AB104 -> 0 | AD104: =IFERROR(AC104/AA104,0) -> 0 | AE104: =IFERROR(AC104/AB104,0) -> 0 | AF104: =IF(AD104>=Assumptions!$B$3,"OK","Review") -> Review | AG104: =IFERROR(IF(Assumptions!$B$13="Cost Price",AB104,AA104)*SUMIF(Assumptions!$A$6:$A$10,X104,Assumptions!$B$6:$B$10),0) -> 7.68 | AH104: =IFERROR(IF(Assumptions!$B$13="Cost Price",AB104,AA104)*SUMIF(Assumptions!$A$6:$A$10,X104,Assumptions!$C$6:$C$10),0) -> 4.8 | AI104: =IFERROR(IF(Assumptions!$B$13="Cost Price",AB104,AA104)*SUMIF(Assumptions!$A$6:$A$10,X104,Assumptions!$D$6:$D$10),0) -> 9.6 | AJ104: 9.6 | AK104: =SUM(AG104:AJ104) -> 31.68 | AL104: 0.33 | AM104: =AC104-AK104 -> -31.68 | AN104: =IFERROR(AM104/AA104,0) -> -0.33 | AO104: =IF(AN104>=Assumptions!$B$3,"OK","Review") -> Review
A105: Corekit AY 2027-2028 | B105: Grade 8 | C105: Science | D105: T1_G8_Science Explorers_TB B2B (27) | E105: 1:1 | F105: Workbook | G105: 2027-2028 | H105: Term 1 | I105: 4000011770 | J105: 51.97 | L105: =J105+K105 -> 51.97 | M105: 0 | N105: =M105*L105 -> 0 | O105: =L105+N105 -> 51.97 | P105: =IFERROR(O105/Q105,"") -> 0.083069595 | Q105: =SUMIFS(O:O,T:T,T105,B:B,B105,A:A,A105,G:G,G105,E:E,E105) -> 625.62 | R105: =V105-SUMIFS(Q:Q,A:A,A105,B:B,B105,G:G,G105,E:E,E105,T:T,"Fixed Price ( Base Price with GST)") -> 3074.564 | S105: =IF(T105="Fixed Price ( Base Price with GST)",O105,P105*R105) -> 255.40279 | T105: Based on Base % | U105: 5699 | V105: =IFERROR(U105*(1-30%),0) -> 3989.3 | W105: 490110 | X105: Core | Y105: =IFERROR(S105,0) -> 255.40279 | Z105: =IF(ISNUMBER(S105),S105,0) -> 255.40279 | AA105: =IFERROR(Z105/(1+M105),Z105) -> 255.40279 | AB105: =IF(ISNUMBER(J105),J105,0) -> 51.97 | AC105: =AA105-AB105 -> 203.43279 | AD105: =IFERROR(AC105/AA105,0) -> 0.79651749 | AE105: =IFERROR(AC105/AB105,0) -> 3.9144273 | AF105: =IF(AD105>=Assumptions!$B$3,"OK","Review") -> OK | AG105: =IFERROR(IF(Assumptions!$B$13="Cost Price",AB105,AA105)*SUMIF(Assumptions!$A$6:$A$10,X105,Assumptions!$B$6:$B$10),0) -> 20.432223 | AH105: =IFERROR(IF(Assumptions!$B$13="Cost Price",AB105,AA105)*SUMIF(Assumptions!$A$6:$A$10,X105,Assumptions!$C$6:$C$10),0) -> 12.770139 | AI105: =IFERROR(IF(Assumptions!$B$13="Cost Price",AB105,AA105)*SUMIF(Assumptions!$A$6:$A$10,X105,Assumptions!$D$6:$D$10),0) -> 25.540279 | AJ105: 39.742687 | AK105: =SUM(AG105:AJ105) -> 98.485328 | AL105: 0.33 | AM105: =AC105-AK105 -> 104.94746 | AN105: =IFERROR(AM105/AA105,0) -> 0.41090961 | AO105: =IF(AN105>=Assumptions!$B$3,"OK","Review") -> OK
A106: Corekit AY 2027-2028 | B106: Grade 8 | C106: Science | D106: T1_G8_Science Explorers_WB B2B (27) | E106: 1:1 | F106: Workbook | G106: 2027-2028 | H106: Term 1 | I106: 4000011771 | J106: 21.76 | L106: =J106+K106 -> 21.76 | M106: 0 | N106: =M106*L106 -> 0 | O106: =L106+N106 -> 21.76 | P106: =IFERROR(O106/Q106,"") -> 0.034781497 | Q106: =SUMIFS(O:O,T:T,T106,B:B,B106,A:A,A106,G:G,G106,E:E,E106) -> 625.62 | R106: =V106-SUMIFS(Q:Q,A:A,A106,B:B,B106,G:G,G106,E:E,E106,T:T,"Fixed Price ( Base Price with GST)") -> 3074.564 | S106: =IF(T106="Fixed Price ( Base Price with GST)",O106,P106*R106) -> 106.93794 | T106: Based on Base % | U106: 5699 | V106: =IFERROR(U106*(1-30%),0) -> 3989.3 | W106: 490110 | X106: Core | Y106: =IFERROR(S106,0) -> 106.93794 | Z106: =IF(ISNUMBER(S106),S106,0) -> 106.93794 | AA106: =IFERROR(Z106/(1+M106),Z106) -> 106.93794 | AB106: =IF(ISNUMBER(J106),J106,0) -> 21.76 | AC106: =AA106-AB106 -> 85.177938 | AD106: =IFERROR(AC106/AA106,0) -> 0.79651749 | AE106: =IFERROR(AC106/AB106,0) -> 3.9144273 | AF106: =IF(AD106>=Assumptions!$B$3,"OK","Review") -> OK | AG106: =IFERROR(IF(Assumptions!$B$13="Cost Price",AB106,AA106)*SUMIF(Assumptions!$A$6:$A$10,X106,Assumptions!$B$6:$B$10),0) -> 8.555035 | AH106: =IFERROR(IF(Assumptions!$B$13="Cost Price",AB106,AA106)*SUMIF(Assumptions!$A$6:$A$10,X106,Assumptions!$C$6:$C$10),0) -> 5.3468969 | AI106: =IFERROR(IF(Assumptions!$B$13="Cost Price",AB106,AA106)*SUMIF(Assumptions!$A$6:$A$10,X106,Assumptions!$D$6:$D$10),0) -> 10.693794 | AJ106: 16.640386 | AK106: =SUM(AG106:AJ106) -> 41.236112 | AL106: 0.33 | AM106: =AC106-AK106 -> 43.941826 | AN106: =IFERROR(AM106/AA106,0) -> 0.41090961 | AO106: =IF(AN106>=Assumptions!$B$3,"OK","Review") -> OK
A107: Corekit AY 2027-2028 | B107: Grade 8 | C107: Maths | D107: T1_G8_Math_Scholars_TB B2B (27) | E107: 1:1 | F107: Book | G107: 2027-2028 | H107: Term 1 | I107: 4000011772 | J107: 68.62 | L107: =J107+K107 -> 68.62 | M107: 0 | N107: =M107*L107 -> 0 | O107: =L107+N107 -> 68.62 | P107: =IFERROR(O107/Q107,"") -> 0.10968319 | Q107: =SUMIFS(O:O,T:T,T107,B:B,B107,A:A,A107,G:G,G107,E:E,E107) -> 625.62 | R107: =V107-SUMIFS(Q:Q,A:A,A107,B:B,B107,G:G,G107,E:E,E107,T:T,"Fixed Price ( Base Price with GST)") -> 3074.564 | S107: =IF(T107="Fixed Price ( Base Price with GST)",O107,P107*R107) -> 337.228 | T107: Based on Base % | U107: 5699 | V107: =IFERROR(U107*(1-30%),0) -> 3989.3 | W107: 490110 | X107: Core | Y107: =IFERROR(S107,0) -> 337.228 | Z107: =IF(ISNUMBER(S107),S107,0) -> 337.228 | AA107: =IFERROR(Z107/(1+M107),Z107) -> 337.228 | AB107: =IF(ISNUMBER(J107),J107,0) -> 68.62 | AC107: =AA107-AB107 -> 268.608 | AD107: =IFERROR(AC107/AA107,0) -> 0.79651749 | AE107: =IFERROR(AC107/AB107,0) -> 3.9144273 | AF107: =IF(AD107>=Assumptions!$B$3,"OK","Review") -> OK | AG107: =IFERROR(IF(Assumptions!$B$13="Cost Price",AB107,AA107)*SUMIF(Assumptions!$A$6:$A$10,X107,Assumptions!$B$6:$B$10),0) -> 26.97824 | AH107: =IFERROR(IF(Assumptions!$B$13="Cost Price",AB107,AA107)*SUMIF(Assumptions!$A$6:$A$10,X107,Assumptions!$C$6:$C$10),0) -> 16.8614 | AI107: =IFERROR(IF(Assumptions!$B$13="Cost Price",AB107,AA107)*SUMIF(Assumptions!$A$6:$A$10,X107,Assumptions!$D$6:$D$10),0) -> 33.7228 | AJ107: 52.475336 | AK107: =SUM(AG107:AJ107) -> 130.03778 | AL107: 0.33 | AM107: =AC107-AK107 -> 138.57022 | AN107: =IFERROR(AM107/AA107,0) -> 0.41090961 | AO107: =IF(AN107>=Assumptions!$B$3,"OK","Review") -> OK
A108: Corekit AY 2027-2028 | B108: Grade 8 | C108: English | D108: Annual_G8_English_Supp B2B (27) | E108: 1:1 | F108: Book | G108: 2027-2028 | H108: Term 1 | I108: 4000011774 | J108: 21.8 | L108: =J108+K108 -> 21.8 | M108: 0 | N108: =M108*L108 -> 0 | O108: =L108+N108 -> 21.8 | P108: =IFERROR(O108/Q108,"") -> 0.034845433 | Q108: =SUMIFS(O:O,T:T,T108,B:B,B108,A:A,A108,G:G,G108,E:E,E108) -> 625.62 | R108: =V108-SUMIFS(Q:Q,A:A,A108,B:B,B108,G:G,G108,E:E,E108,T:T,"Fixed Price ( Base Price with GST)") -> 3074.564 | S108: =IF(T108="Fixed Price ( Base Price with GST)",O108,P108*R108) -> 107.13451 | T108: Based on Base % | U108: 5699 | V108: =IFERROR(U108*(1-30%),0) -> 3989.3 | W108: 490110 | X108: Core | Y108: =IFERROR(S108,0) -> 107.13451 | Z108: =IF(ISNUMBER(S108),S108,0) -> 107.13451 | AA108: =IFERROR(Z108/(1+M108),Z108) -> 107.13451 | AB108: =IF(ISNUMBER(J108),J108,0) -> 21.8 | AC108: =AA108-AB108 -> 85.334515 | AD108: =IFERROR(AC108/AA108,0) -> 0.79651749 | AE108: =IFERROR(AC108/AB108,0) -> 3.9144273 | AF108: =IF(AD108>=Assumptions!$B$3,"OK","Review") -> OK | AG108: =IFERROR(IF(Assumptions!$B$13="Cost Price",AB108,AA108)*SUMIF(Assumptions!$A$6:$A$10,X108,Assumptions!$B$6:$B$10),0) -> 8.5707612 | AH108: =IFERROR(IF(Assumptions!$B$13="Cost Price",AB108,AA108)*SUMIF(Assumptions!$A$6:$A$10,X108,Assumptions!$C$6:$C$10),0) -> 5.3567257 | AI108: =IFERROR(IF(Assumptions!$B$13="Cost Price",AB108,AA108)*SUMIF(Assumptions!$A$6:$A$10,X108,Assumptions!$D$6:$D$10),0) -> 10.713451 | AJ108: 16.670975 | AK108: =SUM(AG108:AJ108) -> 41.311914 | AL108: 0.33 | AM108: =AC108-AK108 -> 44.022601 | AN108: =IFERROR(AM108/AA108,0) -> 0.41090961 | AO108: =IF(AN108>=Assumptions!$B$3,"OK","Review") -> OK
A109: Corekit AY 2027-2028 | B109: Grade 8 | C109: English | D109: T1_G8_English_TB B2B (27) | E109: 1:1 | F109: Book | G109: 2027-2028 | H109: Term 1 | I109: 4000011773 | J109: 60.31 | L109: =J109+K109 -> 60.31 | M109: 0 | N109: =M109*L109 -> 0 | O109: =L109+N109 -> 60.31 | P109: =IFERROR(O109/Q109,"") -> 0.096400371 | Q109: =SUMIFS(O:O,T:T,T109,B:B,B109,A:A,A109,G:G,G109,E:E,E109) -> 625.62 | R109: =V109-SUMIFS(Q:Q,A:A,A109,B:B,B109,G:G,G109,E:E,E109,T:T,"Fixed Price ( Base Price with GST)") -> 3074.564 | S109: =IF(T109="Fixed Price ( Base Price with GST)",O109,P109*R109) -> 296.38911 | T109: Based on Base % | U109: 5699 | V109: =IFERROR(U109*(1-30%),0) -> 3989.3 | W109: 490110 | X109: Core | Y109: =IFERROR(S109,0) -> 296.38911 | Z109: =IF(ISNUMBER(S109),S109,0) -> 296.38911 | AA109: =IFERROR(Z109/(1+M109),Z109) -> 296.38911 | AB109: =IF(ISNUMBER(J109),J109,0) -> 60.31 | AC109: =AA109-AB109 -> 236.07911 | AD109: =IFERROR(AC109/AA109,0) -> 0.79651749 | AE109: =IFERROR(AC109/AB109,0) -> 3.9144273 | AF109: =IF(AD109>=Assumptions!$B$3,"OK","Review") -> OK | AG109: =IFERROR(IF(Assumptions!$B$13="Cost Price",AB109,AA109)*SUMIF(Assumptions!$A$6:$A$10,X109,Assumptions!$B$6:$B$10),0) -> 23.711129 | AH109: =IFERROR(IF(Assumptions!$B$13="Cost Price",AB109,AA109)*SUMIF(Assumptions!$A$6:$A$10,X109,Assumptions!$C$6:$C$10),0) -> 14.819455 | AI109: =IFERROR(IF(Assumptions!$B$13="Cost Price",AB109,AA109)*SUMIF(Assumptions!$A$6:$A$10,X109,Assumptions!$D$6:$D$10),0) -> 29.638911 | AJ109: 46.120482 | AK109: =SUM(AG109:AJ109) -> 114.28998 | AL109: 0.33 | AM109: =AC109-AK109 -> 121.78913 | AN109: =IFERROR(AM109/AA109,0) -> 0.41090961 | AO109: =IF(AN109>=Assumptions!$B$3,"OK","Review") -> OK
A110: Corekit AY 2027-2028 | B110: Grade 8 | C110: English | D110: T1_G8_English_WB B2B (27) | E110: 1:1 | F110: Book | G110: 2027-2028 | H110: Term 1 | I110: 4000011775 | J110: 13.59 | L110: =J110+K110 -> 13.59 | M110: 0 | N110: =M110*L110 -> 0 | O110: =L110+N110 -> 13.59 | P110: =IFERROR(O110/Q110,"") -> 0.021722451 | Q110: =SUMIFS(O:O,T:T,T110,B:B,B110,A:A,A110,G:G,G110,E:E,E110) -> 625.62 | R110: =V110-SUMIFS(Q:Q,A:A,A110,B:B,B110,G:G,G110,E:E,E110,T:T,"Fixed Price ( Base Price with GST)") -> 3074.564 | S110: =IF(T110="Fixed Price ( Base Price with GST)",O110,P110*R110) -> 66.787067 | T110: Based on Base % | U110: 5699 | V110: =IFERROR(U110*(1-30%),0) -> 3989.3 | W110: 490110 | X110: Core | Y110: =IFERROR(S110,0) -> 66.787067 | Z110: =IF(ISNUMBER(S110),S110,0) -> 66.787067 | AA110: =IFERROR(Z110/(1+M110),Z110) -> 66.787067 | AB110: =IF(ISNUMBER(J110),J110,0) -> 13.59 | AC110: =AA110-AB110 -> 53.197067 | AD110: =IFERROR(AC110/AA110,0) -> 0.79651749 | AE110: =IFERROR(AC110/AB110,0) -> 3.9144273 | AF110: =IF(AD110>=Assumptions!$B$3,"OK","Review") -> OK | AG110: =IFERROR(IF(Assumptions!$B$13="Cost Price",AB110,AA110)*SUMIF(Assumptions!$A$6:$A$10,X110,Assumptions!$B$6:$B$10),0) -> 5.3429653 | AH110: =IFERROR(IF(Assumptions!$B$13="Cost Price",AB110,AA110)*SUMIF(Assumptions!$A$6:$A$10,X110,Assumptions!$C$6:$C$10),0) -> 3.3393533 | AI110: =IFERROR(IF(Assumptions!$B$13="Cost Price",AB110,AA110)*SUMIF(Assumptions!$A$6:$A$10,X110,Assumptions!$D$6:$D$10),0) -> 6.6787067 | AJ110: 10.392594 | AK110: =SUM(AG110:AJ110) -> 25.75362 | AL110: 0.33 | AM110: =AC110-AK110 -> 27.443447 | AN110: =IFERROR(AM110/AA110,0) -> 0.41090961 | AO110: =IF(AN110>=Assumptions!$B$3,"OK","Review") -> OK
A111: Corekit AY 2027-2028 | B111: Grade 8 | C111: SST | D111: T1_G8_SST_Mastering Social _TB B2B (27) | E111: 1:1 | F111: Book | G111: 2027-2028 | H111: Term 1 | I111: 4000011776 | J111: 85.28 | L111: =J111+K111 -> 85.28 | M111: 0 | N111: =M111*L111 -> 0 | O111: =L111+N111 -> 85.28 | P111: =IFERROR(O111/Q111,"") -> 0.13631278 | Q111: =SUMIFS(O:O,T:T,T111,B:B,B111,A:A,A111,G:G,G111,E:E,E111) -> 625.62 | R111: =V111-SUMIFS(Q:Q,A:A,A111,B:B,B111,G:G,G111,E:E,E111,T:T,"Fixed Price ( Base Price with GST)") -> 3074.564 | S111: =IF(T111="Fixed Price ( Base Price with GST)",O111,P111*R111) -> 419.10236 | T111: Based on Base % | U111: 5699 | V111: =IFERROR(U111*(1-30%),0) -> 3989.3 | W111: 490110 | X111: Core | Y111: =IFERROR(S111,0) -> 419.10236 | Z111: =IF(ISNUMBER(S111),S111,0) -> 419.10236 | AA111: =IFERROR(Z111/(1+M111),Z111) -> 419.10236 | AB111: =IF(ISNUMBER(J111),J111,0) -> 85.28 | AC111: =AA111-AB111 -> 333.82236 | AD111: =IFERROR(AC111/AA111,0) -> 0.79651749 | AE111: =IFERROR(AC111/AB111,0) -> 3.9144273 | AF111: =IF(AD111>=Assumptions!$B$3,"OK","Review") -> OK | AG111: =IFERROR(IF(Assumptions!$B$13="Cost Price",AB111,AA111)*SUMIF(Assumptions!$A$6:$A$10,X111,Assumptions!$B$6:$B$10),0) -> 33.528189 | AH111: =IFERROR(IF(Assumptions!$B$13="Cost Price",AB111,AA111)*SUMIF(Assumptions!$A$6:$A$10,X111,Assumptions!$C$6:$C$10),0) -> 20.955118 | AI111: =IFERROR(IF(Assumptions!$B$13="Cost Price",AB111,AA111)*SUMIF(Assumptions!$A$6:$A$10,X111,Assumptions!$D$6:$D$10),0) -> 41.910236 | AJ111: 65.215632 | AK111: =SUM(AG111:AJ111) -> 161.60917 | AL111: 0.33 | AM111: =AC111-AK111 -> 172.21319 | AN111: =IFERROR(AM111/AA111,0) -> 0.41090961 | AO111: =IF(AN111>=Assumptions!$B$3,"OK","Review") -> OK
...

Sheet Assumptions
A1: MARGIN MODEL CONTROLS – ALL AVAILABLE ACADEMIC YEARS / PRODUCT TYPES
A3: Target Net Margin % | B3: 0.3
A4: OPERATING COST PERCENTAGES BY PRODUCT TYPE
A5: Product Type | B5: Transportation % | C5: Warehouse & Facility % | D5: Employee Salary % | E5: Additional Services % | F5: Total Operating Cost %
A6: Core | B6: 0.08 | C6: 0.05 | D6: 0.1 | E6: 0.1 | F6: =SUM(B6:E6) -> 0.33
A7: MINI | B7: 0.08 | C7: 0.05 | D7: 0.1 | E7: 0.1 | F7: =SUM(B7:E7) -> 0.33
A8: MINI+WB | B8: 0.08 | C8: 0.05 | D8: 0.1 | E8: 0.1 | F8: =SUM(B8:E8) -> 0.33
A9: Optional | B9: 0.08 | C9: 0.05 | D9: 0.1 | E9: 0.1 | F9: =SUM(B9:E9) -> 0.33
A10: CSR | B10: 0.08 | C10: 0.05 | D10: 0.1 | E10: 0.1 | F10: =SUM(B10:E10) -> 0.33
A13: Operating Cost Basis | B13: Landing Price Excl GST
A15: Note | B15: CSR source uses its source MRP/base-value field as the cost/base input for margin analysis.

Sheet Source - Core 27-28
A1: Product Name | B1: Grades | C1: Subjects | D1: Item Name | E1: Ratio | F1: Item Type | G1: Edition | H1: Type | I1: Core Kit SKU | J1: CP | K1: Aprox Margin | L1: CP + Margin | M1: GST % | N1: GST Value | O1: Base Price with GST | P1: Base % | Q1: Base Bundle | R1: MRP Bundle | S1: MRP IND | T1: Value Type | U1: Selling Price | V1: HSN Code
A2: Corekit AY 2027-2028 | B2: Grade 1 | C2: Maths | D2: T1_G1_Math_Scholars_TB B2B (27) | E2: 1:1 | F2: Book | G2: 2027-2028 | H2: Term 1 | I2: 4000011860 | J2: 44.16 | L2: =J2+K2 -> 44.16 | M2: 0 | N2: =M2*L2 -> 0 | O2: =L2+N2 -> 44.16 | P2: =IFERROR(O2/Q2,"") -> 0.13933676 | Q2: =SUMIFS(O:O,T:T,T2,B:B,B2,A:A,A2,G:G,G2,E:E,E2) -> 316.93 | R2: =U2-SUMIFS(Q:Q,A:A,A2,B:B,B2,G:G,G2,E:E,E2,T:T,"Fixed Price ( Base Price with GST)") -> 4125.5182 | S2: =P2*R2 -> 574.83635 | T2: Based on Base % | U2: 4499 | V2: 490110
A3: Corekit AY 2027-2028 | B3: Grade 1 | C3: Maths | D3: T1_G1_Math_Scholars_WB B2B (27) | E3: 1:1 | F3: Book | G3: 2027-2028 | H3: Term 1 | I3: 4000011852 | J3: 20.94 | L3: =J3+K3 -> 20.94 | M3: 0 | N3: =M3*L3 -> 0 | O3: =L3+N3 -> 20.94 | P3: =IFERROR(O3/Q3,"") -> 0.066071372 | Q3: =SUMIFS(O:O,T:T,T3,B:B,B3,A:A,A3,G:G,G3,E:E,E3) -> 316.93 | R3: =U3-SUMIFS(Q:Q,A:A,A3,B:B,B3,G:G,G3,E:E,E3,T:T,"Fixed Price ( Base Price with GST)") -> 4125.5182 | S3: =P3*R3 -> 272.57865 | T3: Based on Base % | U3: 4499 | V3: 490110
A4: Corekit AY 2027-2028 | B4: Grade 1 | C4: English | D4: Annual_G1_English_RB B2B (27) | E4: 1:1 | F4: Book | G4: 2027-2028 | H4: Term 1 | I4: 4000011794 | J4: 19.56 | L4: =J4+K4 -> 19.56 | M4: 0 | N4: =M4*L4 -> 0 | O4: =L4+N4 -> 19.56 | P4: =IFERROR(O4/Q4,"") -> 0.061717098 | Q4: =SUMIFS(O:O,T:T,T4,B:B,B4,A:A,A4,G:G,G4,E:E,E4) -> 316.93 | R4: =U4-SUMIFS(Q:Q,A:A,A4,B:B,B4,G:G,G4,E:E,E4,T:T,"Fixed Price ( Base Price with GST)") -> 4125.5182 | S4: =P4*R4 -> 254.61501 | T4: Based on Base % | U4: 4499 | V4: 490110
A5: Corekit AY 2027-2028 | B5: Grade 1 | C5: English | D5: T1_G1_English_RC B2B (27) | E5: 1:1 | F5: Workbook | G5: 2027-2028 | H5: Term 1 | I5: 4000011783 | J5: 60.15 | L5: =J5+K5 -> 60.15 | M5: 0 | N5: =M5*L5 -> 0 | O5: =L5+N5 -> 60.15 | P5: =IFERROR(O5/Q5,"") -> 0.18978954 | Q5: =SUMIFS(O:O,T:T,T5,B:B,B5,A:A,A5,G:G,G5,E:E,E5) -> 316.93 | R5: =U5-SUMIFS(Q:Q,A:A,A5,B:B,B5,G:G,G5,E:E,E5,T:T,"Fixed Price ( Base Price with GST)") -> 4125.5182 | S5: =P5*R5 -> 782.98022 | T5: Based on Base % | U5: 4499 | V5: 490110
A6: Corekit AY 2027-2028 | B6: Grade 1 | C6: English | D6: T1_G1_English_WB B2B (27) | E6: 1:1 | F6: Workbook | G6: 2027-2028 | H6: Term 1 | I6: 4000011805 | J6: 20.94 | L6: =J6+K6 -> 20.94 | M6: 0 | N6: =M6*L6 -> 0 | O6: =L6+N6 -> 20.94 | P6: =IFERROR(O6/Q6,"") -> 0.066071372 | Q6: =SUMIFS(O:O,T:T,T6,B:B,B6,A:A,A6,G:G,G6,E:E,E6) -> 316.93 | R6: =U6-SUMIFS(Q:Q,A:A,A6,B:B,B6,G:G,G6,E:E,E6,T:T,"Fixed Price ( Base Price with GST)") -> 4125.5182 | S6: =P6*R6 -> 272.57865 | T6: Based on Base % | U6: 4499 | V6: 490110
A7: Corekit AY 2027-2028 | B7: Grade 1 | C7: Maths | D7: T2_G1_Math_Scholars_TB B2B (27) | E7: 1:1 | F7: Book | G7: 2027-2028 | H7: Term 2 | I7: 4000011816 | J7: 46.25 | L7: =J7+K7 -> 46.25 | M7: 0 | N7: =M7*L7 -> 0 | O7: =L7+N7 -> 46.25 | P7: =IFERROR(O7/Q7,"") -> 0.14593128 | Q7: =SUMIFS(O:O,T:T,T7,B:B,B7,A:A,A7,G:G,G7,E:E,E7) -> 316.93 | R7: =U7-SUMIFS(Q:Q,A:A,A7,B:B,B7,G:G,G7,E:E,E7,T:T,"Fixed Price ( Base Price with GST)") -> 4125.5182 | S7: =P7*R7 -> 602.04214 | T7: Based on Base % | U7: 4499 | V7: 490110
A8: Corekit AY 2027-2028 | B8: Grade 1 | C8: Maths | D8: T2_G1_Math_Scholars_WB B2B (27) | E8: 1:1 | F8: Book | G8: 2027-2028 | H8: Term 2 | I8: 4000011747 | J8: 19.51 | L8: =J8+K8 -> 19.51 | M8: 0 | N8: =M8*L8 -> 0 | O8: =L8+N8 -> 19.51 | P8: =IFERROR(O8/Q8,"") -> 0.061559335 | Q8: =SUMIFS(O:O,T:T,T8,B:B,B8,A:A,A8,G:G,G8,E:E,E8) -> 316.93 | R8: =U8-SUMIFS(Q:Q,A:A,A8,B:B,B8,G:G,G8,E:E,E8,T:T,"Fixed Price ( Base Price with GST)") -> 4125.5182 | S8: =P8*R8 -> 253.96416 | T8: Based on Base % | U8: 4499 | V8: 490110
A9: Corekit AY 2027-2028 | B9: Grade 1 | C9: English | D9: T2_G1_English_RC B2B (27) | E9: 1:1 | F9: Workbook | G9: 2027-2028 | H9: Term 2 | I9: 4000011758 | J9: 65.91 | L9: =J9+K9 -> 65.91 | M9: 0 | N9: =M9*L9 -> 0 | O9: =L9+N9 -> 65.91 | P9: =IFERROR(O9/Q9,"") -> 0.2079639 | Q9: =SUMIFS(O:O,T:T,T9,B:B,B9,A:A,A9,G:G,G9,E:E,E9) -> 316.93 | R9: =U9-SUMIFS(Q:Q,A:A,A9,B:B,B9,G:G,G9,E:E,E9,T:T,"Fixed Price ( Base Price with GST)") -> 4125.5182 | S9: =P9*R9 -> 857.95887 | T9: Based on Base % | U9: 4499 | V9: 490110
A10: Corekit AY 2027-2028 | B10: Grade 1 | C10: English | D10: T2_G1_English_WB B2B (27) | E10: 1:1 | F10: Workbook | G10: 2027-2028 | H10: Term 2 | I10: 4000011769 | J10: 19.51 | L10: =J10+K10 -> 19.51 | M10: 0 | N10: =M10*L10 -> 0 | O10: =L10+N10 -> 19.51 | P10: =IFERROR(O10/Q10,"") -> 0.061559335 | Q10: =SUMIFS(O:O,T:T,T10,B:B,B10,A:A,A10,G:G,G10,E:E,E10) -> 316.93 | R10: =U10-SUMIFS(Q:Q,A:A,A10,B:B,B10,G:G,G10,E:E,E10,T:T,"Fixed Price ( Base Price with GST)") -> 4125.5182 | S10: =P10*R10 -> 253.96416 | T10: Based on Base % | U10: 4499 | V10: 490110
A11: Corekit AY 2027-2028 | B11: Grade 1 | C11: Combo Kit | D11: B2B Sci-Pi Visual Maths Kit G1 27-28 | E11: 1:1 | F11: Kit | G11: 2027-2028 | H11: Term 1 | I11: 7000000216 | J11: 210.51 | K11: 10 | L11: =J11+K11 -> 220.51 | M11: 0.18 | N11: =M11*L11 -> 39.6918 | O11: =L11+N11 -> 260.2018 | P11: 0 | Q11: =O11 -> 260.2018 | R11: =Q11 -> 260.2018 | S11: =Q11 -> 260.2018 | T11: Fixed Price ( Base Price with GST) | U11: 4499 | V11: 49119990
A12: Corekit AY 2027-2028 | B12: Grade 1 | C12: Service | D12: Services Charges_25_26 | E12: 1:1 | F12: Services Charges | G12: 2027-2028 | H12: Term 1 | I12: 8400007 | J12: 96 | L12: =J12+K12 -> 96 | M12: 0.18 | N12: =M12*L12 -> 17.28 | O12: =L12+N12 -> 113.28 | P12: 0 | Q12: =O12 -> 113.28 | R12: =Q12 -> 113.28 | S12: =Q12 -> 113.28 | T12: Fixed Price ( Base Price with GST) | U12: 4499 | V12: 999299
A13: Corekit AY 2027-2028 | B13: Grade 2 | C13: Maths | D13: T1_G2_Math_Scholars_TB B2B (27) | E13: 1:1 | F13: Book | G13: 2027-2028 | H13: Term 1 | I13: 4000011861 | J13: 40.09 | L13: =J13+K13 -> 40.09 | M13: 0 | N13: =M13*L13 -> 0 | O13: =L13+N13 -> 40.09 | P13: =IFERROR(O13/Q13,"") -> 0.12098624 | Q13: =SUMIFS(O:O,T:T,T13,B:B,B13,A:A,A13,G:G,G13,E:E,E13) -> 331.36 | R13: =U13-SUMIFS(Q:Q,A:A,A13,B:B,B13,G:G,G13,E:E,E13,T:T,"Fixed Price ( Base Price with GST)") -> 4117.9544 | S13: =P13*R13 -> 498.21581 | T13: Based on Base % | U13: 4499 | V13: 490110
A14: Corekit AY 2027-2028 | B14: Grade 2 | C14: Maths | D14: T1_G2_Math_Scholars_WB B2B (27) | E14: 1:1 | F14: Book | G14: 2027-2028 | H14: Term 1 | I14: 4000011872 | J14: 21.01 | L14: =J14+K14 -> 21.01 | M14: 0 | N14: =M14*L14 -> 0 | O14: =L14+N14 -> 21.01 | P14: =IFERROR(O14/Q14,"") -> 0.06340536 | Q14: =SUMIFS(O:O,T:T,T14,B:B,B14,A:A,A14,G:G,G14,E:E,E14) -> 331.36 | R14: =U14-SUMIFS(Q:Q,A:A,A14,B:B,B14,G:G,G14,E:E,E14,T:T,"Fixed Price ( Base Price with GST)") -> 4117.9544 | S14: =P14*R14 -> 261.10038 | T14: Based on Base % | U14: 4499 | V14: 490110
A15: Corekit AY 2027-2028 | B15: Grade 2 | C15: English | D15: Annual_G2_English_RB B2B (27) | E15: 1:1 | F15: Book | G15: 2027-2028 | H15: Term 1 | I15: 4000011837 | J15: 20.1 | L15: =J15+K15 -> 20.1 | M15: 0 | N15: =M15*L15 -> 0 | O15: =L15+N15 -> 20.1 | P15: =IFERROR(O15/Q15,"") -> 0.060659102 | Q15: =SUMIFS(O:O,T:T,T15,B:B,B15,A:A,A15,G:G,G15,E:E,E15) -> 331.36 | R15: =U15-SUMIFS(Q:Q,A:A,A15,B:B,B15,G:G,G15,E:E,E15,T:T,"Fixed Price ( Base Price with GST)") -> 4117.9544 | S15: =P15*R15 -> 249.79142 | T15: Based on Base % | U15: 4499 | V15: 490110
A16: Corekit AY 2027-2028 | B16: Grade 2 | C16: English | D16: T1_G2_English_RC B2B (27) | E16: 1:1 | F16: Workbook | G16: 2027-2028 | H16: Term 1 | I16: 4000011826 | J16: 66.38 | L16: =J16+K16 -> 66.38 | M16: 0 | N16: =M16*L16 -> 0 | O16: =L16+N16 -> 66.38 | P16: =IFERROR(O16/Q16,"") -> 0.20032593 | Q16: =SUMIFS(O:O,T:T,T16,B:B,B16,A:A,A16,G:G,G16,E:E,E16) -> 331.36 | R16: =U16-SUMIFS(Q:Q,A:A,A16,B:B,B16,G:G,G16,E:E,E16,T:T,"Fixed Price ( Base Price with GST)") -> 4117.9544 | S16: =P16*R16 -> 824.93304 | T16: Based on Base % | U16: 4499 | V16: 490110
A17: Corekit AY 2027-2028 | B17: Grade 2 | C17: English | D17: T1_G2_English_WB B2B (27) | E17: 1:1 | F17: Workbook | G17: 2027-2028 | H17: Term 1 | I17: 4000011846 | J17: 25.48 | L17: =J17+K17 -> 25.48 | M17: 0 | N17: =M17*L17 -> 0 | O17: =L17+N17 -> 25.48 | P17: =IFERROR(O17/Q17,"") -> 0.07689522 | Q17: =SUMIFS(O:O,T:T,T17,B:B,B17,A:A,A17,G:G,G17,E:E,E17) -> 331.36 | R17: =U17-SUMIFS(Q:Q,A:A,A17,B:B,B17,G:G,G17,E:E,E17,T:T,"Fixed Price ( Base Price with GST)") -> 4117.9544 | S17: =P17*R17 -> 316.65101 | T17: Based on Base % | U17: 4499 | V17: 490110
A18: Corekit AY 2027-2028 | B18: Grade 2 | C18: Maths | D18: T2_G2_Math_Scholars_TB B2B (27) | E18: 1:1 | F18: Book | G18: 2027-2028 | H18: Term 2 | I18: 4000011847 | J18: 50.5 | L18: =J18+K18 -> 50.5 | M18: 0 | N18: =M18*L18 -> 0 | O18: =L18+N18 -> 50.5 | P18: =IFERROR(O18/Q18,"") -> 0.15240222 | Q18: =SUMIFS(O:O,T:T,T18,B:B,B18,A:A,A18,G:G,G18,E:E,E18) -> 331.36 | R18: =U18-SUMIFS(Q:Q,A:A,A18,B:B,B18,G:G,G18,E:E,E18,T:T,"Fixed Price ( Base Price with GST)") -> 4117.9544 | S18: =P18*R18 -> 627.5854 | T18: Based on Base % | U18: 4499 | V18: 490110
A19: Corekit AY 2027-2028 | B19: Grade 2 | C19: Maths | D19: T2_G2_Math_Scholars_WB B2B (27) | E19: 1:1 | F19: Book | G19: 2027-2028 | H19: Term 2 | I19: 4000011848 | J19: 21.01 | L19: =J19+K19 -> 21.01 | M19: 0 | N19: =M19*L19 -> 0 | O19: =L19+N19 -> 21.01 | P19: =IFERROR(O19/Q19,"") -> 0.06340536 | Q19: =SUMIFS(O:O,T:T,T19,B:B,B19,A:A,A19,G:G,G19,E:E,E19) -> 331.36 | R19: =U19-SUMIFS(Q:Q,A:A,A19,B:B,B19,G:G,G19,E:E,E19,T:T,"Fixed Price ( Base Price with GST)") -> 4117.9544 | S19: =P19*R19 -> 261.10038 | T19: Based on Base % | U19: 4499 | V19: 490110
A20: Corekit AY 2027-2028 | B20: Grade 2 | C20: English | D20: T2_G2_English_RC B2B (27) | E20: 1:1 | F20: Workbook | G20: 2027-2028 | H20: Term 2 | I20: 4000011849 | J20: 62.84 | L20: =J20+K20 -> 62.84 | M20: 0 | N20: =M20*L20 -> 0 | O20: =L20+N20 -> 62.84 | P20: =IFERROR(O20/Q20,"") -> 0.18964268 | Q20: =SUMIFS(O:O,T:T,T20,B:B,B20,A:A,A20,G:G,G20,E:E,E20) -> 331.36 | R20: =U20-SUMIFS(Q:Q,A:A,A20,B:B,B20,G:G,G20,E:E,E20,T:T,"Fixed Price ( Base Price with GST)") -> 4117.9544 | S20: =P20*R20 -> 780.93993 | T20: Based on Base % | U20: 4499 | V20: 490110
A21: Corekit AY 2027-2028 | B21: Grade 2 | C21: English | D21: T2_G2_English_WB B2B (27) | E21: 1:1 | F21: Workbook | G21: 2027-2028 | H21: Term 2 | I21: 4000011850 | J21: 23.95 | L21: =J21+K21 -> 23.95 | M21: 0 | N21: =M21*L21 -> 0 | O21: =L21+N21 -> 23.95 | P21: =IFERROR(O21/Q21,"") -> 0.072277885 | Q21: =SUMIFS(O:O,T:T,T21,B:B,B21,A:A,A21,G:G,G21,E:E,E21) -> 331.36 | R21: =U21-SUMIFS(Q:Q,A:A,A21,B:B,B21,G:G,G21,E:E,E21,T:T,"Fixed Price ( Base Price with GST)") -> 4117.9544 | S21: =P21*R21 -> 297.63703 | T21: Based on Base % | U21: 4499 | V21: 490110
A22: Corekit AY 2027-2028 | B22: Grade 2 | C22: Combo Kit | D22: B2B Sci-Pi Visual Maths Kit G2 27-28 | E22: 1:1 | F22: Kit | G22: 2027-2028 | H22: Term 1 | I22: 7000000223 | J22: 216.92 | K22: 10 | L22: =J22+K22 -> 226.92 | M22: 0.18 | N22: =M22*L22 -> 40.8456 | O22: =L22+N22 -> 267.7656 | P22: 0 | Q22: =O22 -> 267.7656 | R22: =Q22 -> 267.7656 | S22: =Q22 -> 267.7656 | T22: Fixed Price ( Base Price with GST) | U22: 4499 | V22: 49119990
A23: Corekit AY 2027-2028 | B23: Grade 2 | C23: Service | D23: Services Charges_25_26 | E23: 1:1 | F23: Services Charges | G23: 2027-2028 | H23: Term 1 | I23: 8400007 | J23: 96 | L23: =J23+K23 -> 96 | M23: 0.18 | N23: =M23*L23 -> 17.28 | O23: =L23+N23 -> 113.28 | P23: 0 | Q23: =O23 -> 113.28 | R23: =Q23 -> 113.28 | S23: =Q23 -> 113.28 | T23: Fixed Price ( Base Price with GST) | U23: 4499 | V23: 999299
A24: Corekit AY 2027-2028 | B24: Grade 3 | C24: Science | D24: T1_G3_Science Explorers_TB B2B (27) | E24: 1:1 | F24: Book | G24: 2027-2028 | H24: Term 1 | I24: 4000011851 | J24: 30 | L24: =J24+K24 -> 30 | M24: 0 | N24: =M24*L24 -> 0 | O24: =L24+N24 -> 30 | P24: =IFERROR(O24/Q24,"") -> 0.060504608 | Q24: =SUMIFS(O:O,T:T,T24,B:B,B24,A:A,A24,G:G,G24,E:E,E24) -> 495.83 | R24: =U24-SUMIFS(Q:Q,A:A,A24,B:B,B24,G:G,G24,E:E,E24,T:T,"Fixed Price ( Base Price with GST)") -> 5135.732 | S24: =P24*R24 -> 310.73545 | T24: Based on Base % | U24: 5599 | V24: 490110
